Workbook

Sheet Instructions
B2: Home Health Agency - Full Financial System (Daily Detail, Full Year)
B3: Sample Agency: Meridian Home Care Services | Illustrative Full-Year Demo (FY2025), Day-Level Detail
B5: PURPOSE
B6: A complete financial system for a mid-size home health agency, built at daily transaction granularity so any date range can be analyzed. All names, figures, and transactions are fictional/randomly generated for demonstration - they represent no real agency, client, or employee.
B10: TAB GUIDE
B11: Chart of Accounts | C11: Full account structure including balance sheet accounts, plus key rate/assumption cells.
B12: Caregiver Roster | C12: All 40 caregivers - role, pay type, rate, hire/term dates, certification tracking.
B13: Client Roster | C13: All 65 clients - payer, authorized units, service dates.
B14: Client Authorizations | C14: Medicaid/insurance authorization periods per client - flags expired/expiring authorizations.
B15: Caregiver Certifications | C15: Background check dates and certification expiry per caregiver - compliance tracking.
B16: Fixed Asset Register | C16: Vehicles, office/medical equipment - cost, useful life, monthly depreciation, net book value.
B17: Daily Visit Register | C17: Every single visit for the year (8,124 rows) - the source of truth for all revenue.
B18: Daily Payroll Register | C18: Every caregiver's pay every day (5,973 rows) - the source of truth for all labor cost.
B19: Missed Visits Log | C19: Uncovered/cancelled visits and the revenue lost - an operational KPI source.
B20: Payroll Summary | C20: Monthly payroll rollup from the Daily Payroll Register, with employer burden.
B21: Revenue by Payer | C21: Monthly revenue rollup from the Daily Visit Register, by payer.
B22: AR Aging | C22: Month-end receivable balance by payer, reflecting each payer's collection speed.
... B33: KPI Dashboard | C33: Profitability by caregiver and by client, utilization, turnover, missed-visit rate, and more.
B35: COLOR KEY
B36: Blue text | C36: Hardcoded input / source data.
B37: Black text | C37: Formula calculated from other cells.
B38: Green text | C38: Link pulling from another tab.
B39: Yellow fill | C39: Key assumption/rate, or a date-range input cell to edit.
B41: KEY DESIGN NOTE: DAILY DATA VOLUME
B42: The Daily Visit Register and Daily Payroll Register contain full day-level transaction detail (~14,000 rows combined) so any custom date range can be analyzed precisely. Monthly summary tabs (Payroll Summary, Revenue by Payer, AR Aging, Overhead, P&L) roll this up via formulas for readability and faster recalculation. The Custom Date-Range P&L tab queries the daily registers directly for any period you specify.

Sheet Chart of Accounts
B2: Chart of Accounts - Home Health Agency Structure
B3: Full structure including balance sheet accounts for the daily-detail financial system.
B5: Acct # | C5: Account Name | D5: Type | E5: Notes
B6: 1000 - ASSETS
B7: 1010 | C7: Cash - Operating Account | D7: Asset | E7: See Bank Reconciliation and Cash Flow tabs
B8: 1200 | C8: Accounts Receivable - Medicaid Waiver | D8: Asset | E8: See AR Aging tab
B9: 1210 | C9: Accounts Receivable - Private Pay | D9: Asset
B10: 1220 | C10: Accounts Receivable - Medicare | D10: Asset
B11: 1230 | C11: Accounts Receivable - Private Insurance | D11: Asset
B12: 1500 | C12: Fixed Assets - Vehicles | D12: Asset | E12: See Fixed Asset Register
B13: 1510 | C13: Fixed Assets - Office Equipment | D13: Asset
B14: 1520 | C14: Fixed Assets - Medical Equipment | D14: Asset
B15: 1590 | C15: Accumulated Depreciation | D15: Contra-Asset | E15: Reduces gross fixed assets to net book value
B16: 2000 - LIABILITIES
B17: 2100 | C17: Accrued Payroll Payable | D17: Liability | E17: Payroll earned but unpaid at period-end
B18: 2200 | C18: Payroll Taxes Payable | D18: Liability | E18: Employer + withheld employee taxes due
B19: 2500 | C19: Line of Credit Payable | D19: Liability | E19: See Line of Credit tab - revolving facility
B20: 3000 - EQUITY
B21: 3010 | C21: Owner's Capital Contribution | D21: Equity | E21: See Statement of Owner's Equity
B22: 3020 | C22: Owner's Draws | D22: Equity | E22: Distributions to owner, reduces equity
B23: 3030 | C23: Retained Earnings | D23: Equity | E23: Cumulative net income
B24: 4000 - REVENUE (by Payer)
B25: 4010 | C25: Revenue - Medicaid Waiver (Hourly) | D25: Income | E25: Billed at contracted hourly rate
B26: 4020 | C26: Revenue - Private Pay (Hourly) | D26: Income | E26: Fastest-collecting payer
B27: 4030 | C27: Revenue - Medicare Skilled (Per-Visit) | D27: Income | E27: Billed per visit/episode
B28: 4040 | C28: Revenue - Private Insurance (Per-Visit) | D28: Income | E28: Billed per payer fee schedule
B29: 4090 | C29: Contra - Claim Denials & Write-offs | D29: Contra-Income | E29: Netted against gross billed revenue
B30: 5000 - COST OF SERVICES (Direct Caregiver Labor)
B31: 5010 | C31: Caregiver Wages - Regular (Hourly) | D31: COGS
B32: 5020 | C32: Caregiver Wages - Overtime (Hourly) | D32: COGS | E32: 1.5x, weekly threshold basis
B33: 5030 | C33: Caregiver Pay - Per-Visit (LPN/RN/Therapy) | D33: COGS
B34: 5040 | C34: Mileage Reimbursement | D34: COGS | E34: IRS standard mileage rate
B35: 5050 | C35: Payroll Tax & Burden (Employer Share) | D35: COGS | E35: FICA, FUTA/SUTA, workers' comp, benefits
B36: 6000 - OPERATING EXPENSES (Overhead)
B37: 6010 | C37: Office Rent | D37: Opex
B38: 6020 | C38: Office Utilities | D38: Opex
B39: 6030 | C39: Admin Salaries (Office/Scheduling Staff) | D39: Opex
B40: 6040 | C40: Owner / Executive Compensation | D40: Opex
B41: 6050 | C41: Scheduling / EVV Software | D41: Opex | E41: Federally mandated for Medicaid personal care
B42: 6060 | C42: Accounting Software | D42: Opex
B43: 6070 | C43: Payroll Processing Fees | D43: Opex
B44: 6080 | C44: Insurance (Liability & Bonding) | D44: Opex
B45: 6090 | C45: Background Checks & Licensing | D45: Opex
B46: 6100 | C46: Marketing & Referral Development | D46: Opex
B47: 6110 | C47: Office Supplies | D47: Opex
B48: 6120 | C48: Telephone / Communications | D48: Opex
B49: 6130 | C49: Legal & Professional Fees | D49: Opex | E49: Includes outside tax preparer/CPA coordination
B50: 6140 | C50: Bank & Merchant Fees | D50: Opex
B51: 6150 | C51: Vehicle Fuel & Maintenance | D51: Opex
B52: 6160 | C52: Continuing Education / Training | D52: Opex
B53: 6170 | C53: Misc / Other Admin | D53: Opex
B54: 6180 | C54: Depreciation Expense | D54: Opex | E54: Non-cash; from Fixed Asset Register
B55: 6190 | C55: Line of Credit Interest | D55: Opex | E55: See Line of Credit tab
B58: KEY ASSUMPTION: PAYER RATES
B59: Payer | C59: Billing Unit | D59: Rate | E59: Avg Days to Pay | F59: Denial/Write-off %
B60: Medicaid Waiver | C60: Per Hour | D60: 26.5 | E60: 52 | F60: 0.03
B61: Private Pay | C61: Per Hour | D61: 34 | E61: 12 | F61: 0
B62: Medicare (Skilled) | C62: Per Visit | D62: 165 | E62: 38 | F62: 0.05
B63: Private Insurance | C63: Per Visit | D63: 135 | E63: 45 | F63: 0.07
B66: KEY ASSUMPTIONS: PAYROLL, MILEAGE, LOC
B67: Employer Payroll Burden Rate (FICA + FUTA/SUTA + Workers Comp + Benefits) | E67: 0.145
B68: IRS Standard Mileage Reimbursement Rate ($/mile) | E68: 0.67
B69: Weekly Overtime Threshold (hours) | E69: 40
B70: Owner Capital Injection (Opening) | E70: 130000
B71: Line of Credit Limit | E71: 175000
B72: Line of Credit Annual Interest Rate | E72: 0.0925

Sheet Caregiver Roster
B2: Caregiver Roster
B3: All caregivers for the demo year. Pay type and rate drive the Daily Payroll Register.
B5: Caregiver ID | C5: Name | D5: Role | E5: Pay Type | F5: Pay Rate | G5: Mileage Eligible | H5: Hire Date | I5: Term Date | J5: Status
B6: CG-001 | C6: Maria Garcia | D6: Personal Care Aide | E6: Hourly | F6: 14.56 | G6: Yes | H6: 45658 | I6: - | J6: Active
B7: CG-002 | C7: James Smith | D7: Home Health Aide | E7: Hourly | F7: 17.34 | G7: Yes | H7: 45658 | I7: - | J7: Active
B8: CG-003 | C8: Linda Johnson | D8: RN | E8: Per Visit | F8: 66.48 | G8: No | H8: 45658 | I8: - | J8: Active
B9: CG-004 | C9: Robert Williams | D9: Home Health Aide | E9: Hourly | F9: 16.05 | G9: Yes | H9: 45658 | I9: 45810 | J9: Terminated
B10: CG-005 | C10: Patricia Brown | D10: Home Health Aide | E10: Hourly | F10: 16 | G10: Yes | H10: 45658 | I10: - | J10: Active
B11: CG-006 | C11: John Jones | D11: Personal Care Aide | E11: Hourly | F11: 15.05 | G11: Yes | H11: 45658 | I11: - | J11: Active
B12: CG-007 | C12: Barbara Miller | D12: LPN | E12: Per Visit | F12: 48.09 | G12: No | H12: 45770 | I12: - | J12: Active
B13: CG-008 | C13: Michael Davis | D13: Personal Care Aide | E13: Hourly | F13: 15.19 | G13: Yes | H13: 45658 | I13: - | J13: Active
B14: CG-009 | C14: Jennifer Rodriguez | D14: LPN | E14: Per Visit | F14: 49.43 | G14: No | H14: 45658 | I14: - | J14: Active
B15: CG-010 | C15: David Martinez | D15: Home Health Aide | E15: Hourly | F15: 16.36 | G15: Yes | H15: 45658 | I15: - | J15: Active
B16: CG-011 | C16: Susan Hernandez | D16: Home Health Aide | E16: Hourly | F16: 16.65 | G16: Yes | H16: 45658 | I16: 45896 | J16: Terminated
B17: CG-012 | C17: Richard Lopez | D17: PT/OT Therapist | E17: Per Visit | F17: 73.58 | G17: No | H17: 45658 | I17: - | J17: Active
B18: CG-013 | C18: Jessica Wilson | D18: Personal Care Aide | E18: Hourly | F18: 16.71 | G18: Yes | H18: 45658 | I18: 45837 | J18: Terminated
B19: CG-014 | C19: Charles Anderson | D19: Home Health Aide | E19: Hourly | F19: 15.67 | G19: Yes | H19: 45658 | I19: - | J19: Active
B20: CG-015 | C20: Karen Thomas | D20: LPN | E20: Per Visit | F20: 61.79 | G20: No | H20: 45866 | I20: - | J20: Active
B21: CG-016 | C21: Joseph Taylor | D21: Home Health Aide | E21: Hourly | F21: 16.19 | G21: Yes | H21: 45658 | I21: - | J21: Active
B22: CG-017 | C22: Nancy Moore | D22: Home Health Aide | E22: Hourly | F22: 16.43 | G22: Yes | H22: 45658 | I22: - | J22: Active
B23: CG-018 | C23: Thomas Jackson | D23: Home Health Aide | E23: Hourly | F23: 17.84 | G23: Yes | H23: 45658 | I23: - | J23: Active
B24: CG-019 | C24: Betty Martin | D24: Personal Care Aide | E24: Hourly | F24: 14.93 | G24: Yes | H24: 45658 | I24: - | J24: Active
B25: CG-020 | C25: Christopher Lee | D25: Home Health Aide | E25: Hourly | F25: 16.45 | G25: Yes | H25: 46012 | I25: - | J25: Active
B26: CG-021 | C26: Sandra Perez | D26: LPN | E26: Per Visit | F26: 51.07 | G26: No | H26: 45658 | I26: - | J26: Active
B27: CG-022 | C27: Daniel Thompson | D27: LPN | E27: Per Visit | F27: 48.78 | G27: No | H27: 45803 | I27: - | J27: Active
B28: CG-023 | C28: Ashley White | D28: Home Health Aide | E28: Hourly | F28: 16.17 | G28: Yes | H28: 45658 | I28: - | J28: Active
B29: CG-024 | C29: Paul Harris | D29: PT/OT Therapist | E29: Per Visit | F29: 89.53 | G29: No | H29: 45658 | I29: - | J29: Active
B30: CG-025 | C30: Kimberly Sanchez | D30: Personal Care Aide | E30: Hourly | F30: 15.49 | G30: Yes | H30: 45915 | I30: - | J30: Active
... B42: CG-037 | C42: Melissa Nguyen | D42: RN | E42: Per Visit | F42: 79.8 | G42: No | H42: 45658 | I42: - | J42: Active
B43: CG-038 | C43: Ronald Hill | D43: Personal Care Aide | E43: Hourly | F43: 16.02 | G43: Yes | H43: 45658 | I43: 45801 | J43: Terminated
B44: CG-039 | C44: Deborah Flores | D44: LPN | E44: Per Visit | F44: 55.55 | G44: No | H44: 45733 | I44: - | J44: Active
B45: CG-040 | C45: Anthony Green | D45: RN | E45: Per Visit | F45: 75.18 | G45: No | H45: 45658 | I45: 45903 | J45: Terminated
B47: Total Caregivers: 40
B48: Active at Year-End: | C48: =COUNTIF(J6:J45,"Active") -> 35
B49: Terminated During Year (Turnover Count): | C49: =COUNTIF(J6:J45,"Terminated") -> 5
B50: Annualized Turnover Rate (Terminated ÷ Avg Headcount): | C50: =C49/((COUNTA(B6:B45)+C48)/2) -> 0.13333333

Sheet Client Roster
B2: Client Roster
B3: All clients for the demo year, by payer type, with authorized vs. actual weekly units.
B5: Client ID | C5: Client (Household) | D5: Payer | E5: Weekly Units (Actual) | F5: Weekly Units (Authorized) | G5: Unit Type | H5: Start Date | I5: End Date | J5: Status
B6: CL-001 | C6: Adams Household | D6: Medicare (Skilled) | E6: 3 | F6: 3.6 | G6: Visits/wk | H6: 45658 | I6: 45891 | J6: Discharged
B7: CL-002 | C7: Baker Household | D7: Medicare (Skilled) | E7: 1 | F7: 1.3 | G7: Visits/wk | H7: 45995 | I7: - | J7: Active
B8: CL-003 | C8: Carter Household | D8: Medicare (Skilled) | E8: 1 | F8: 1.2 | G8: Visits/wk | H8: 45658 | I8: 45820 | J8: Discharged
B9: CL-004 | C9: Diaz Household | D9: Private Pay | E9: 28 | F9: 30 | G9: Hours/wk | H9: 45658 | I9: - | J9: Active
B10: CL-005 | C10: Evans Household | D10: Medicaid Waiver | E10: 14 | F10: 16 | G10: Hours/wk | H10: 45658 | I10: - | J10: Active
B11: CL-006 | C11: Fisher Household | D11: Medicare (Skilled) | E11: 2 | F11: 2.5 | G11: Visits/wk | H11: 45903 | I11: - | J11: Active
B12: CL-007 | C12: Gray Household | D12: Medicaid Waiver | E12: 12 | F12: 14.5 | G12: Hours/wk | H12: 45873 | I12: - | J12: Active
B13: CL-008 | C13: Hughes Household | D13: Private Pay | E13: 6 | F13: 7.1 | G13: Hours/wk | H13: 45658 | I13: - | J13: Active
B14: CL-009 | C14: Irwin Household | D14: Medicaid Waiver | E14: 6 | F14: 7.5 | G14: Hours/wk | H14: 45958 | I14: - | J14: Active
B15: CL-010 | C15: Jenkins Household | D15: Medicare (Skilled) | E15: 2 | F15: 2.3 | G15: Visits/wk | H15: 45658 | I15: - | J15: Active
B16: CL-011 | C16: Kelly Household | D16: Medicaid Waiver | E16: 8 | F16: 9.8 | G16: Hours/wk | H16: 45936 | I16: - | J16: Active
B17: CL-012 | C17: Lambert Household | D17: Medicaid Waiver | E17: 12 | F17: 12.6 | G17: Hours/wk | H17: 45658 | I17: - | J17: Active
B18: CL-013 | C18: Morgan Household | D18: Medicare (Skilled) | E18: 3 | F18: 3.6 | G18: Visits/wk | H18: 45740 | I18: - | J18: Active
B19: CL-014 | C19: Nash Household | D19: Private Insurance | E19: 3 | F19: 3.4 | G19: Visits/wk | H19: 45658 | I19: - | J19: Active
B20: CL-015 | C20: Owens Household | D20: Medicaid Waiver | E20: 6 | F20: 7 | G20: Hours/wk | H20: 45658 | I20: - | J20: Active
... B29: CL-024 | C29: Xu Household | D29: Private Pay | E29: 20 | F29: 22.3 | G29: Hours/wk | H29: 45658 | I29: - | J29: Active
B30: CL-025 | C30: Yates Household | D30: Private Pay | E30: 8 | F30: 9.5 | G30: Hours/wk | H30: 45658 | I30: 45991 | J30: Discharged
B31: CL-026 | C31: Zimmerman Household | D31: Medicaid Waiver | E31: 10 | F31: 12.4 | G31: Hours/wk | H31: 45931 | I31: - | J31: Active
B32: CL-027 | C32: Bell Household | D32: Medicaid Waiver | E32: 12 | F32: 14.1 | G32: Hours/wk | H32: 45658 | I32: - | J32: Active
B33: CL-028 | C33: Cole Household | D33: Medicaid Waiver | E33: 6 | F33: 6.4 | G33: Hours/wk | H33: 45658 | I33: 45889 | J33: Discharged
B34: CL-029 | C34: Dunn Household | D34: Medicaid Waiver | E34: 10 | F34: 10.8 | G34: Hours/wk | H34: 45658 | I34: - | J34: Active
B35: CL-030 | C35: Ellis Household | D35: Private Pay | E35: 6 | F35: 7.4 | G35: Hours/wk | H35: 45658 | I35: - | J35: Active
B36: CL-031 | C36: Ford Household | D36: Medicaid Waiver | E36: 8 | F36: 9.1 | G36: Hours/wk | H36: 45658 | I36: - | J36: Active
B37: CL-032 | C37: Grant Household | D37: Private Insurance | E37: 2 | F37: 2.6 | G37: Visits/wk | H37: 46012 | I37: - | J37: Active
B38: CL-033 | C38: Hart Household | D38: Medicaid Waiver | E38: 14 | F38: 14.7 | G38: Hours/wk | H38: 45848 | I38: 45983 | J38: Discharged
B39: CL-034 | C39: Ingram Household | D39: Medicaid Waiver | E39: 20 | F39: 21.4 | G39: Hours/wk | H39: 45909 | I39: - | J39: Active
B40: CL-035 | C40: Jordan Household | D40: Medicaid Waiver | E40: 6 | F40: 7.4 | G40: Hours/wk | H40: 45752 | I40: - | J40: Active
B41: CL-036 | C41: Knight Household | D41: Medicaid Waiver | E41: 10 | F41: 11.1 | G41: Hours/wk | H41: 45658 | I41: - | J41: Active
B42: CL-037 | C42: Lane Household | D42: Medicaid Waiver | E42: 10 | F42: 10.9 | G42: Hours/wk | H42: 45658 | I42: - | J42: Active
B43: CL-038 | C43: Mills Household | D43: Medicaid Waiver | E43: 10 | F43: 11.5 | G43: Hours/wk | H43: 45658 | I43: - | J43: Active
B44: CL-039 | C44: Norris Household | D44: Private Pay | E44: 28 | F44: 29.7 | G44: Hours/wk | H44: 45658 | I44: - | J44: Active
B45: CL-040 | C45: Ortiz Household | D45: Medicare (Skilled) | E45: 2 | F45: 2.2 | G45: Visits/wk | H45: 45658 | I45: - | J45: Active
B46: CL-041 | C46: Pratt Household | D46: Private Pay | E46: 8 | F46: 9.4 | G46: Hours/wk | H46: 45658 | I46: - | J46: Active
B47: CL-042 | C47: Quincy Household | D47: Medicaid Waiver | E47: 20 | F47: 22.8 | G47: Hours/wk | H47: 45765 | I47: - | J47: Active
B48: CL-043 | C48: Ross Household | D48: Private Pay | E48: 6 | F48: 6.4 | G48: Hours/wk | H48: 45984 | I48: - | J48: Active
B49: CL-044 | C49: Shaw Household | D49: Private Insurance | E49: 2 | F49: 2.5 | G49: Visits/wk | H49: 45857 | I49: - | J49: Active
B50: CL-045 | C50: Tate Household | D50: Medicaid Waiver | E50: 14 | F50: 15.1 | G50: Hours/wk | H50: 45658 | I50: - | J50: Active
B51: CL-046 | C51: Usher Household | D51: Medicaid Waiver | E51: 10 | F51: 11.2 | G51: Hours/wk | H51: 45958 | I51: 45964 | J51: Discharged
B52: CL-047 | C52: Vega Household | D52: Private Pay | E52: 6 | F52: 7.4 | G52: Hours/wk | H52: 45658 | I52: - | J52: Active
B53: CL-048 | C53: Webb Household | D53: Medicaid Waiver | E53: 8 | F53: 9.5 | G53: Hours/wk | H53: 45658 | I53: - | J53: Active
B54: CL-049 | C54: York Household | D54: Private Pay | E54: 14 | F54: 17.2 | G54: Hours/wk | H54: 45658 | I54: - | J54: Active
B55: CL-050 | C55: Abbott Household | D55: Medicare (Skilled) | E55: 2 | F55: 2.8 | G55: Visits/wk | H55: 45658 | I55: - | J55: Active
B56: CL-051 | C56: Booth Household | D56: Medicare (Skilled) | E56: 2 | F56: 2.8 | G56: Visits/wk | H56: 45867 | I56: - | J56: Active
B57: CL-052 | C57: Crane Household | D57: Private Pay | E57: 12 | F57: 12.7 | G57: Hours/wk | H57: 45758 | I57: - | J57: Active
B58: CL-053 | C58: Dean Household | D58: Medicaid Waiver | E58: 28 | F58: 34.6 | G58: Hours/wk | H58: 45866 | I58: - | J58: Active
B59: CL-054 | C59: Estes Household | D59: Medicaid Waiver | E59: 20 | F59: 24.2 | G59: Hours/wk | H59: 45658 | I59: - | J59: Active
B60: CL-055 | C60: Frost Household | D60: Private Pay | E60: 28 | F60: 33.3 | G60: Hours/wk | H60: 45658 | I60: - | J60: Active
B61: CL-056 | C61: Gill Household | D61: Medicare (Skilled) | E61: 1 | F61: 1.4 | G61: Visits/wk | H61: 45658 | I61: - | J61: Active
B62: CL-057 | C62: Hood Household | D62: Private Pay | E62: 28 | F62: 34.5 | G62: Hours/wk | H62: 45658 | I62: - | J62: Active
B63: CL-058 | C63: Ives Household | D63: Private Insurance | E63: 2 | F63: 2.3 | G63: Visits/wk | H63: 45701 | I63: - | J63: Active
... B70: CL-065 | C70: Reyes Household | D70: Medicaid Waiver | E70: 14 | F70: 17.5 | G70: Hours/wk | H70: 45658 | I70: - | J70: Active
B72: Total Clients (Year): 65
B73: Active at Year-End: | C73: =COUNTIF(J6:J70,"Active") -> 59

Sheet Client Authorizations
B2: Client Authorization Register
B3: Medicaid/insurance authorization periods. Billing against an expired authorization is a real audit exposure.
B5: Client ID | C5: Client | D5: Payer | E5: Auth Start | F5: Auth End | G5: Days Until Expiry (as of 12/31) | H5: Status | I5: Action Needed
B6: CL-001 | C6: Adams Household | D6: Medicare (Skilled) | E6: 45658 | F6: 45866 | G6: =F6-DATE(2025,12,31) -> -156 | H6: =IF(G6<0,"EXPIRED",IF(G6<=30,"Expiring Soon","Current")) -> EXPIRED | I6: =IF(H6="EXPIRED","Renew immediately - billing exposure",IF(H6="Expiring Soon","Initiate renewal","None")) -> Renew immediately - billing exposure
B7: CL-002 | C7: Baker Household | D7: Medicare (Skilled) | E7: 45995 | F7: 46201 | G7: =F7-DATE(2025,12,31) -> 179 | H7: =IF(G7<0,"EXPIRED",IF(G7<=30,"Expiring Soon","Current")) -> Current | I7: =IF(H7="EXPIRED","Renew immediately - billing exposure",IF(H7="Expiring Soon","Initiate renewal","None")) -> None
B8: CL-003 | C8: Carter Household | D8: Medicare (Skilled) | E8: 45658 | F8: 45866 | G8: =F8-DATE(2025,12,31) -> -156 | H8: =IF(G8<0,"EXPIRED",IF(G8<=30,"Expiring Soon","Current")) -> EXPIRED | I8: =IF(H8="EXPIRED","Renew immediately - billing exposure",IF(H8="Expiring Soon","Initiate renewal","None")) -> Renew immediately - billing exposure
B9: CL-004 | C9: Diaz Household | D9: Private Pay | E9: 45658 | F9: 45866 | G9: =F9-DATE(2025,12,31) -> -156 | H9: =IF(G9<0,"EXPIRED",IF(G9<=30,"Expiring Soon","Current")) -> EXPIRED | I9: =IF(H9="EXPIRED","Renew immediately - billing exposure",IF(H9="Expiring Soon","Initiate renewal","None")) -> Renew immediately - billing exposure
B10: CL-005 | C10: Evans Household | D10: Medicaid Waiver | E10: 45658 | F10: 45866 | G10: =F10-DATE(2025,12,31) -> -156 | H10: =IF(G10<0,"EXPIRED",IF(G10<=30,"Expiring Soon","Current")) -> EXPIRED | I10: =IF(H10="EXPIRED","Renew immediately - billing exposure",IF(H10="Expiring Soon","Initiate renewal","None")) -> Renew immediately - billing exposure
B11: CL-006 | C11: Fisher Household | D11: Medicare (Skilled) | E11: 45903 | F11: 46109 | G11: =F11-DATE(2025,12,31) -> 87 | H11: =IF(G11<0,"EXPIRED",IF(G11<=30,"Expiring Soon","Current")) -> Current | I11: =IF(H11="EXPIRED","Renew immediately - billing exposure",IF(H11="Expiring Soon","Initiate renewal","None")) -> None
B12: CL-007 | C12: Gray Household | D12: Medicaid Waiver | E12: 45873 | F12: 46081 | G12: =F12-DATE(2025,12,31) -> 59 | H12: =IF(G12<0,"EXPIRED",IF(G12<=30,"Expiring Soon","Current")) -> Current | I12: =IF(H12="EXPIRED","Renew immediately - billing exposure",IF(H12="Expiring Soon","Initiate renewal","None")) -> None
B13: CL-008 | C13: Hughes Household | D13: Private Pay | E13: 45658 | F13: 45866 | G13: =F13-DATE(2025,12,31) -> -156 | H13: =IF(G13<0,"EXPIRED",IF(G13<=30,"Expiring Soon","Current")) -> EXPIRED | I13: =IF(H13="EXPIRED","Renew immediately - billing exposure",IF(H13="Expiring Soon","Initiate renewal","None")) -> Renew immediately - billing exposure
B14: CL-009 | C14: Irwin Household | D14: Medicaid Waiver | E14: 45958 | F14: 46140 | G14: =F14-DATE(2025,12,31) -> 118 | H14: =IF(G14<0,"EXPIRED",IF(G14<=30,"Expiring Soon","Current")) -> Current | I14: =IF(H14="EXPIRED","Renew immediately - billing exposure",IF(H14="Expiring Soon","Initiate renewal","None")) -> None
B15: CL-010 | C15: Jenkins Household | D15: Medicare (Skilled) | E15: 45658 | F15: 45866 | G15: =F15-DATE(2025,12,31) -> -156 | H15: =IF(G15<0,"EXPIRED",IF(G15<=30,"Expiring Soon","Current")) -> EXPIRED | I15: =IF(H15="EXPIRED","Renew immediately - billing exposure",IF(H15="Expiring Soon","Initiate renewal","None")) -> Renew immediately - billing exposure
B16: CL-011 | C16: Kelly Household | D16: Medicaid Waiver | E16: 45936 | F16: 46140 | G16: =F16-DATE(2025,12,31) -> 118 | H16: =IF(G16<0,"EXPIRED",IF(G16<=30,"Expiring Soon","Current")) -> Current | I16: =IF(H16="EXPIRED","Renew immediately - billing exposure",IF(H16="Expiring Soon","Initiate renewal","None")) -> None
B17: CL-012 | C17: Lambert Household | D17: Medicaid Waiver | E17: 45658 | F17: 45866 | G17: =F17-DATE(2025,12,31) -> -156 | H17: =IF(G17<0,"EXPIRED",IF(G17<=30,"Expiring Soon","Current")) -> EXPIRED | I17: =IF(H17="EXPIRED","Renew immediately - billing exposure",IF(H17="Expiring Soon","Initiate renewal","None")) -> Renew immediately - billing exposure
... B70: CL-065 | C70: Reyes Household | D70: Medicaid Waiver | E70: 45658 | F70: 45866 | G70: =F70-DATE(2025,12,31) -> -156 | H70: =IF(G70<0,"EXPIRED",IF(G70<=30,"Expiring Soon","Current")) -> EXPIRED | I70: =IF(H70="EXPIRED","Renew immediately - billing exposure",IF(H70="Expiring Soon","Initiate renewal","None")) -> Renew immediately - billing exposure
B72: Authorizations Expired or Expiring Within 30 Days: | C72: =COUNTIF(H6:H70,"EXPIRED")+COUNTIF(H6:H70,"Expiring Soon") -> 52

Sheet Caregiver Certifications
B2: Caregiver Certification & Background Check Register
B3: Background check and certification renewal tracking - lapses are a compliance/liability exposure.
B5: Caregiver ID | C5: Name | D5: Background Check Date | E5: Cert Expiry Date | F5: Days Until Expiry (as of 12/31) | G5: Status | H5: Action Needed
B6: CG-001 | C6: Maria Garcia | D6: 45658 | E6: 46023 | F6: =E6-DATE(2025,12,31) -> 1 | G6: =IF(F6<0,"EXPIRED",IF(F6<=60,"Expiring Soon","Current")) -> Expiring Soon | H6: =IF(G6="EXPIRED","Cannot bill for this caregiver - renew now",IF(G6="Expiring Soon","Schedule renewal","None")) -> Schedule renewal
B7: CG-002 | C7: James Smith | D7: 45658 | E7: 46023 | F7: =E7-DATE(2025,12,31) -> 1 | G7: =IF(F7<0,"EXPIRED",IF(F7<=60,"Expiring Soon","Current")) -> Expiring Soon | H7: =IF(G7="EXPIRED","Cannot bill for this caregiver - renew now",IF(G7="Expiring Soon","Schedule renewal","None")) -> Schedule renewal
B8: CG-003 | C8: Linda Johnson | D8: 45658 | E8: 46023 | F8: =E8-DATE(2025,12,31) -> 1 | G8: =IF(F8<0,"EXPIRED",IF(F8<=60,"Expiring Soon","Current")) -> Expiring Soon | H8: =IF(G8="EXPIRED","Cannot bill for this caregiver - renew now",IF(G8="Expiring Soon","Schedule renewal","None")) -> Schedule renewal
B9: CG-004 | C9: Robert Williams | D9: 45658 | E9: 46023 | F9: =E9-DATE(2025,12,31) -> 1 | G9: =IF(F9<0,"EXPIRED",IF(F9<=60,"Expiring Soon","Current")) -> Expiring Soon | H9: =IF(G9="EXPIRED","Cannot bill for this caregiver - renew now",IF(G9="Expiring Soon","Schedule renewal","None")) -> Schedule renewal
B10: CG-005 | C10: Patricia Brown | D10: 45658 | E10: 46023 | F10: =E10-DATE(2025,12,31) -> 1 | G10: =IF(F10<0,"EXPIRED",IF(F10<=60,"Expiring Soon","Current")) -> Expiring Soon | H10: =IF(G10="EXPIRED","Cannot bill for this caregiver - renew now",IF(G10="Expiring Soon","Schedule renewal","None")) -> Schedule renewal
B11: CG-006 | C11: John Jones | D11: 45658 | E11: 46023 | F11: =E11-DATE(2025,12,31) -> 1 | G11: =IF(F11<0,"EXPIRED",IF(F11<=60,"Expiring Soon","Current")) -> Expiring Soon | H11: =IF(G11="EXPIRED","Cannot bill for this caregiver - renew now",IF(G11="Expiring Soon","Schedule renewal","None")) -> Schedule renewal
B12: CG-007 | C12: Barbara Miller | D12: 45770 | E12: 46135 | F12: =E12-DATE(2025,12,31) -> 113 | G12: =IF(F12<0,"EXPIRED",IF(F12<=60,"Expiring Soon","Current")) -> Current | H12: =IF(G12="EXPIRED","Cannot bill for this caregiver - renew now",IF(G12="Expiring Soon","Schedule renewal","None")) -> None
B13: CG-008 | C13: Michael Davis | D13: 45658 | E13: 46023 | F13: =E13-DATE(2025,12,31) -> 1 | G13: =IF(F13<0,"EXPIRED",IF(F13<=60,"Expiring Soon","Current")) -> Expiring Soon | H13: =IF(G13="EXPIRED","Cannot bill for this caregiver - renew now",IF(G13="Expiring Soon","Schedule renewal","None")) -> Schedule renewal
B14: CG-009 | C14: Jennifer Rodriguez | D14: 45658 | E14: 46023 | F14: =E14-DATE(2025,12,31) -> 1 | G14: =IF(F14<0,"EXPIRED",IF(F14<=60,"Expiring Soon","Current")) -> Expiring Soon | H14: =IF(G14="EXPIRED","Cannot bill for this caregiver - renew now",IF(G14="Expiring Soon","Schedule renewal","None")) -> Schedule renewal
B15: CG-010 | C15: David Martinez | D15: 45658 | E15: 46023 | F15: =E15-DATE(2025,12,31) -> 1 | G15: =IF(F15<0,"EXPIRED",IF(F15<=60,"Expiring Soon","Current")) -> Expiring Soon | H15: =IF(G15="EXPIRED","Cannot bill for this caregiver - renew now",IF(G15="Expiring Soon","Schedule renewal","None")) -> Schedule renewal
B16: CG-011 | C16: Susan Hernandez | D16: 45658 | E16: 46023 | F16: =E16-DATE(2025,12,31) -> 1 | G16: =IF(F16<0,"EXPIRED",IF(F16<=60,"Expiring Soon","Current")) -> Expiring Soon | H16: =IF(G16="EXPIRED","Cannot bill for this caregiver - renew now",IF(G16="Expiring Soon","Schedule renewal","None")) -> Schedule renewal
B17: CG-012 | C17: Richard Lopez | D17: 45658 | E17: 46023 | F17: =E17-DATE(2025,12,31) -> 1 | G17: =IF(F17<0,"EXPIRED",IF(F17<=60,"Expiring Soon","Current")) -> Expiring Soon | H17: =IF(G17="EXPIRED","Cannot bill for this caregiver - renew now",IF(G17="Expiring Soon","Schedule renewal","None")) -> Schedule renewal
... B45: CG-040 | C45: Anthony Green | D45: 45658 | E45: 46023 | F45: =E45-DATE(2025,12,31) -> 1 | G45: =IF(F45<0,"EXPIRED",IF(F45<=60,"Expiring Soon","Current")) -> Expiring Soon | H45: =IF(G45="EXPIRED","Cannot bill for this caregiver - renew now",IF(G45="Expiring Soon","Schedule renewal","None")) -> Schedule renewal
B47: Certifications Expired or Expiring Within 60 Days: | C47: =COUNTIF(G6:G45,"EXPIRED")+COUNTIF(G6:G45,"Expiring Soon") -> 28

Sheet Fixed Asset Register
B2: Fixed Asset Register
B3: Vehicles and equipment, with straight-line monthly depreciation and net book value as of year-end.
B5: Asset ID | C5: Description | D5: Category | E5: Acquisition Date | F5: Cost | G5: Useful Life (Yrs) | H5: Salvage Value | I5: Monthly Depreciation | J5: Months Depreciated (FY) | K5: Accum. Depreciation (FY) | L5: Net Book Value (12/31)
B6: FA-001 | C6: 2023 Toyota Sienna (Agency Vehicle - Client Transport) | D6: Vehicle | E6: 45659 | F6: 28500 | G6: 5 | H6: 4000 | I6: =(F6-H6)/(G6*12) -> 408.33333 | J6: =MIN(12-MONTH(E6)+1,G6*12) -> 12 | K6: =I6*J6 -> 4900 | L6: =F6-K6 -> 23600
B7: FA-002 | C7: 2022 Honda CR-V (Agency Vehicle - Supervisor Use) | D7: Vehicle | E7: 45659 | F7: 22000 | G7: 5 | H7: 3000 | I7: =(F7-H7)/(G7*12) -> 316.66667 | J7: =MIN(12-MONTH(E7)+1,G7*12) -> 12 | K7: =I7*J7 -> 3800 | L7: =F7-K7 -> 18200
B8: FA-003 | C8: Office Computers and Workstations (5 units) | D8: Office Equipment | E8: 45662 | F8: 6500 | G8: 3 | H8: 0 | I8: =(F8-H8)/(G8*12) -> 180.55556 | J8: =MIN(12-MONTH(E8)+1,G8*12) -> 12 | K8: =I8*J8 -> 2166.6667 | L8: =F8-K8 -> 4333.3333
B9: FA-004 | C9: Office Furniture (desks, chairs, filing) | D9: Office Equipment | E9: 45662 | F9: 4200 | G9: 7 | H9: 0 | I9: =(F9-H9)/(G9*12) -> 50 | J9: =MIN(12-MONTH(E9)+1,G9*12) -> 12 | K9: =I9*J9 -> 600 | L9: =F9-K9 -> 3600
B10: FA-005 | C10: Medical Equipment (BP cuffs, scales, gait belts, pulse-ox - shared pool) | D10: Medical Equipment | E10: 45667 | F10: 3200 | G10: 4 | H10: 0 | I10: =(F10-H10)/(G10*12) -> 66.666667 | J10: =MIN(12-MONTH(E10)+1,G10*12) -> 12 | K10: =I10*J10 -> 800 | L10: =F10-K10 -> 2400
B11: FA-006 | C11: EVV / Scheduling System - Hardware and Setup (tablets for field staff) | D11: Office Equipment | E11: 45689 | F11: 2800 | G11: 3 | H11: 0 | I11: =(F11-H11)/(G11*12) -> 77.777778 | J11: =MIN(12-MONTH(E11)+1,G11*12) -> 11 | K11: =I11*J11 -> 855.55556 | L11: =F11-K11 -> 1944.4444
B12: FA-007 | C12: 2024 Ford Transit Connect (Agency Vehicle - Added for Growth) | D12: Vehicle | E12: 45884 | F12: 26500 | G12: 5 | H12: 3500 | I12: =(F12-H12)/(G12*12) -> 383.33333 | J12: =MIN(12-MONTH(E12)+1,G12*12) -> 5 | K12: =I12*J12 -> 1916.6667 | L12: =F12-K12 -> 24583.333
B13: FA-008 | C13: 2021 Honda Odyssey (Agency Vehicle - Added for Q4 Growth) | D13: Vehicle | E13: 45931 | F13: 21000 | G13: 5 | H13: 3000 | I13: =(F13-H13)/(G13*12) -> 300 | J13: =MIN(12-MONTH(E13)+1,G13*12) -> 3 | K13: =I13*J13 -> 900 | L13: =F13-K13 -> 20100
B14: FA-009 | C14: Additional Medical Equipment (wheelchairs, hospital bed rails - 2nd batch) | D14: Medical Equipment | E14: 45778 | F14: 2400 | G14: 4 | H14: 0 | I14: =(F14-H14)/(G14*12) -> 50 | J14: =MIN(12-MONTH(E14)+1,G14*12) -> 8 | K14: =I14*J14 -> 400 | L14: =F14-K14 -> 2000
B15: FA-010 | C15: Server / Network Infrastructure Upgrade | D15: Office Equipment | E15: 45731 | F15: 3600 | G15: 3 | H15: 0 | I15: =(F15-H15)/(G15*12) -> 100 | J15: =MIN(12-MONTH(E15)+1,G15*12) -> 10 | K15: =I15*J15 -> 1000 | L15: =F15-K15 -> 2600
B16: FA-011 | C16: Office Security System (cameras, access control) | D16: Office Equipment | E16: 45748 | F16: 1850 | G16: 5 | H16: 0 | I16: =(F16-H16)/(G16*12) -> 30.833333 | J16: =MIN(12-MONTH(E16)+1,G16*12) -> 9 | K16: =I16*J16 -> 277.5 | L16: =F16-K16 -> 1572.5
B17: FA-012 | C17: Leasehold Improvements (office buildout, ADA ramp) | D17: Leasehold Improvements | E17: 45672 | F17: 8500 | G17: 7 | H17: 0 | I17: =(F17-H17)/(G17*12) -> 101.19048 | J17: =MIN(12-MONTH(E17)+1,G17*12) -> 12 | K17: =I17*J17 -> 1214.2857 | L17: =F17-K17 -> 7285.7143
B19: TOTALS | F19: =SUM(F6:F17) -> 131050 | K19: =SUM(K6:K17) -> 18830.675 | L19: =SUM(L6:L17) -> 112219.33
B21: MONTHLY DEPRECIATION SCHEDULE
C22: Jan-2025 | D22: Feb-2025 | E22: Mar-2025 | F22: Apr-2025 | G22: May-2025 | H22: Jun-2025 | I22: Jul-2025 | J22: Aug-2025 | K22: Sep-2025 | L22: Oct-2025 | M22: Nov-2025 | N22: Dec-2025
B23: Total Monthly Depreciation | C23: 1123.42 | D23: 1201.2 | E23: 1301.2 | F23: 1332.03 | G23: 1382.03 | H23: 1382.03 | I23: 1382.03 | J23: 1765.36 | K23: 1765.36 | L23: 2065.36 | M23: 2065.36 | N23: 2065.36
B25: OTHER ASSETS (Non-Depreciable)
B26: Item | C26: Type | D26: Date | E26: Amount | F26: Notes
B27: Office Lease Security Deposit | C27: Security Deposit | D27: 45658 | E27: 4400 | F27: Refundable at end of lease term
B28: General Liability Insurance - Annual Premium (Prepaid) | C28: Prepaid Expense | D28: 45658 | E28: 11400 | F28: 12-month policy, amortized monthly to Insurance expense
B30: TOTAL OTHER ASSETS | E30: =SUM(E27:E28) -> 15800

Sheet Daily Visit Register
B2: Daily Visit Register - Every Visit, Full Year
B3: 8,124 visit records. Source of truth for all revenue calculations across the workbook.
B5: Visit ID | C5: Date | D5: Client ID | E5: Payer | F5: Caregiver ID | G5: Unit Type | H5: Gross Units | I5: Denied Units | J5: Net Units | K5: Rate | L5: Net Revenue | M5: Attributed Labor Cost
B6: V-000001 | C6: 45658 | D6: CL-001 | E6: Medicare (Skilled) | F6: CG-003 | G6: Visits | H6: 0.91 | I6: 0 | J6: =H6-I6 -> 0.91 | K6: 165 | L6: =J6*K6 -> 150.15 | M6: =H6*66.48*(1+'Chart of Accounts'!$E$67) -> 69.268836
B7: V-000002 | C7: 45658 | D7: CL-003 | E7: Medicare (Skilled) | F7: CG-021 | G7: Visits | H7: 0.99 | I7: 0 | J7: =H7-I7 -> 0.99 | K7: 165 | L7: =J7*K7 -> 163.35 | M7: =H7*51.07*(1+'Chart of Accounts'!$E$67) -> 57.890399
B8: V-000003 | C8: 45658 | D8: CL-004 | E8: Private Pay | F8: CG-004 | G8: Hours | H8: 4.39 | I8: 0 | J8: =H8-I8 -> 4.39 | K8: 34 | L8: =J8*K8 -> 149.26 | M8: =H8*16.05*(1+'Chart of Accounts'!$E$67) -> 80.676128
B9: V-000004 | C9: 45658 | D9: CL-005 | E9: Medicaid Waiver | F9: CG-005 | G9: Hours | H9: 5.03 | I9: 0 | J9: =H9-I9 -> 5.03 | K9: 26.5 | L9: =J9*K9 -> 133.295 | M9: =H9*16*(1+'Chart of Accounts'!$E$67) -> 92.1496
B10: V-000005 | C10: 45658 | D10: CL-012 | E10: Medicaid Waiver | F10: CG-010 | G10: Hours | H10: 4 | I10: 0 | J10: =H10-I10 -> 4 | K10: 26.5 | L10: =J10*K10 -> 106 | M10: =H10*16.36*(1+'Chart of Accounts'!$E$67) -> 74.9288
B11: V-000006 | C11: 45658 | D11: CL-014 | E11: Private Insurance | F11: CG-033 | G11: Visits | H11: 1.08 | I11: 0 | J11: =H11-I11 -> 1.08 | K11: 135 | L11: =J11*K11 -> 145.8 | M11: =H11*57.54*(1+'Chart of Accounts'!$E$67) -> 71.153964
B12: V-000007 | C12: 45658 | D12: CL-016 | E12: Private Pay | F12: CG-002 | G12: Hours | H12: 3.81 | I12: 0 | J12: =H12-I12 -> 3.81 | K12: 34 | L12: =J12*K12 -> 129.54 | M12: =H12*17.34*(1+'Chart of Accounts'!$E$67) -> 75.644883
B13: V-000008 | C13: 45658 | D13: CL-020 | E13: Medicaid Waiver | F13: CG-016 | G13: Hours | H13: 4.21 | I13: 0 | J13: =H13-I13 -> 4.21 | K13: 26.5 | L13: =J13*K13 -> 111.565 | M13: =H13*16.19*(1+'Chart of Accounts'!$E$67) -> 78.043086
B14: V-000009 | C14: 45658 | D14: CL-024 | E14: Private Pay | F14: CG-017 | G14: Hours | H14: 3.82 | I14: 0 | J14: =H14-I14 -> 3.82 | K14: 34 | L14: =J14*K14 -> 129.88 | M14: =H14*16.43*(1+'Chart of Accounts'!$E$67) -> 71.863177
B15: V-000010 | C15: 45658 | D15: CL-027 | E15: Medicaid Waiver | F15: CG-001 | G15: Hours | H15: 3.82 | I15: 0 | J15: =H15-I15 -> 3.82 | K15: 26.5 | L15: =J15*K15 -> 101.23 | M15: =H15*14.56*(1+'Chart of Accounts'!$E$67) -> 63.683984
B16: V-000011 | C16: 45658 | D16: CL-029 | E16: Medicaid Waiver | F16: CG-028 | G16: Hours | H16: 3.09 | I16: 0 | J16: =H16-I16 -> 3.09 | K16: 26.5 | L16: =J16*K16 -> 81.885 | M16: =H16*17.99*(1+'Chart of Accounts'!$E$67) -> 63.649519
B17: V-000012 | C17: 45658 | D17: CL-036 | E17: Medicaid Waiver | F17: CG-034 | G17: Hours | H17: 3.47 | I17: 0 | J17: =H17-I17 -> 3.47 | K17: 26.5 | L17: =J17*K17 -> 91.955 | M17: =H17*17.1*(1+'Chart of Accounts'!$E$67) -> 67.940865
B18: V-000013 | C18: 45658 | D18: CL-037 | E18: Medicaid Waiver | F18: CG-008 | G18: Hours | H18: 3.36 | I18: 0 | J18: =H18-I18 -> 3.36 | K18: 26.5 | L18: =J18*K18 -> 89.04 | M18: =H18*15.19*(1+'Chart of Accounts'!$E$67) -> 58.438968
B19: V-000014 | C19: 45658 | D19: CL-038 | E19: Medicaid Waiver | F19: CG-011 | G19: Hours | H19: 3.28 | I19: 0 | J19: =H19-I19 -> 3.28 | K19: 26.5 | L19: =J19*K19 -> 86.92 | M19: =H19*16.65*(1+'Chart of Accounts'!$E$67) -> 62.53074
B20: V-000015 | C20: 45658 | D20: CL-039 | E20: Private Pay | F20: CG-013 | G20: Hours | H20: 4.16 | I20: 0 | J20: =H20-I20 -> 4.16 | K20: 34 | L20: =J20*K20 -> 141.44 | M20: =H20*16.71*(1+'Chart of Accounts'!$E$67) -> 79.593072
B21: V-000016 | C21: 45658 | D21: CL-049 | E21: Private Pay | F21: CG-019 | G21: Hours | H21: 4.48 | I21: 0 | J21: =H21-I21 -> 4.48 | K21: 34 | L21: =J21*K21 -> 152.32 | M21: =H21*14.93*(1+'Chart of Accounts'!$E$67) -> 76.584928
B22: V-000017 | C22: 45658 | D22: CL-054 | E22: Medicaid Waiver | F22: CG-030 | G22: Hours | H22: 4.27 | I22: 0 | J22: =H22-I22 -> 4.27 | K22: 26.5 | L22: =J22*K22 -> 113.155 | M22: =H22*16.48*(1+'Chart of Accounts'!$E$67) -> 80.573192
B23: V-000018 | C23: 45658 | D23: CL-055 | E23: Private Pay | F23: CG-018 | G23: Hours | H23: 4.24 | I23: 0 | J23: =H23-I23 -> 4.24 | K23: 34 | L23: =J23*K23 -> 144.16 | M23: =H23*17.84*(1+'Chart of Accounts'!$E$67) -> 86.609632
B24: V-000019 | C24: 45658 | D24: CL-056 | E24: Medicare (Skilled) | F24: CG-009 | G24: Visits | H24: 0.95 | I24: 0 | J24: =H24-I24 -> 0.95 | K24: 165 | L24: =J24*K24 -> 156.75 | M24: =H24*49.43*(1+'Chart of Accounts'!$E$67) -> 53.767482
B25: V-000020 | C25: 45658 | D25: CL-057 | E25: Private Pay | F25: CG-028 | G25: Hours | H25: 4.14 | I25: 0 | J25: =H25-I25 -> 4.14 | K25: 34 | L25: =J25*K25 -> 140.76 | M25: =H25*17.99*(1+'Chart of Accounts'!$E$67) -> 85.277997
B26: V-000021 | C26: 45658 | D26: CL-059 | E26: Medicaid Waiver | F26: CG-038 | G26: Hours | H26: 3.56 | I26: 0 | J26: =H26-I26 -> 3.56 | K26: 26.5 | L26: =J26*K26 -> 94.34 | M26: =H26*16.02*(1+'Chart of Accounts'!$E$67) -> 65.300724
B27: V-000022 | C27: 45658 | D27: CL-060 | E27: Private Pay | F27: CG-034 | G27: Hours | H27: 4.03 | I27: 0 | J27: =H27-I27 -> 4.03 | K27: 34 | L27: =J27*K27 -> 137.02 | M27: =H27*17.1*(1+'Chart of Accounts'!$E$67) -> 78.905385
B28: V-000023 | C28: 45658 | D28: CL-064 | E28: Medicaid Waiver | F28: CG-014 | G28: Hours | H28: 3.44 | I28: 0 | J28: =H28-I28 -> 3.44 | K28: 26.5 | L28: =J28*K28 -> 91.16 | M28: =H28*15.67*(1+'Chart of Accounts'!$E$67) -> 61.720996
B29: V-000024 | C29: 45658 | D29: CL-065 | E29: Medicaid Waiver | F29: CG-001 | G29: Hours | H29: 5.01 | I29: 0 | J29: =H29-I29 -> 5.01 | K29: 26.5 | L29: =J29*K29 -> 132.765 | M29: =H29*14.56*(1+'Chart of Accounts'!$E$67) -> 83.522712
B30: V-000025 | C30: 45659 | D30: CL-004 | E30: Private Pay | F30: CG-004 | G30: Hours | H30: 3.86 | I30: 0 | J30: =H30-I30 -> 3.86 | K30: 34 | L30: =J30*K30 -> 131.24 | M30: =H30*16.05*(1+'Chart of Accounts'!$E$67) -> 70.936185
B31: V-000026 | C31: 45659 | D31: CL-008 | E31: Private Pay | F31: CG-008 | G31: Hours | H31: 3.23 | I31: 0 | J31: =H31-I31 -> 3.23 | K31: 34 | L31: =J31*K31 -> 109.82 | M31: =H31*15.19*(1+'Chart of Accounts'!$E$67) -> 56.177937
B32: V-000027 | C32: 45659 | D32: CL-015 | E32: Medicaid Waiver | F32: CG-006 | G32: Hours | H32: 2.95 | I32: 0 | J32: =H32-I32 -> 2.95 | K32: 26.5 | L32: =J32*K32 -> 78.175 | M32: =H32*15.05*(1+'Chart of Accounts'!$E$67) -> 50.835138
B33: V-000028 | C33: 45659 | D33: CL-016 | E33: Private Pay | F33: CG-002 | G33: Hours | H33: 4.2 | I33: 0 | J33: =H33-I33 -> 4.2 | K33: 34 | L33: =J33*K33 -> 142.8 | M33: =H33*17.34*(1+'Chart of Accounts'!$E$67) -> 83.38806
B34: V-000029 | C34: 45659 | D34: CL-018 | E34: Private Pay | F34: CG-011 | G34: Hours | H34: 2.83 | I34: 0 | J34: =H34-I34 -> 2.83 | K34: 34 | L34: =J34*K34 -> 96.22 | M34: =H34*16.65*(1+'Chart of Accounts'!$E$67) -> 53.951828
B35: V-000030 | C35: 45659 | D35: CL-020 | E35: Medicaid Waiver | F35: CG-016 | G35: Hours | H35: 3.63 | I35: 0 | J35: =H35-I35 -> 3.63 | K35: 26.5 | L35: =J35*K35 -> 96.195 | M35: =H35*16.19*(1+'Chart of Accounts'!$E$67) -> 67.291307
B36: V-000031 | C36: 45659 | D36: CL-022 | E36: Medicaid Waiver | F36: CG-013 | G36: Hours | H36: 3.2 | I36: 0 | J36: =H36-I36 -> 3.2 | K36: 26.5 | L36: =J36*K36 -> 84.8 | M36: =H36*16.71*(1+'Chart of Accounts'!$E$67) -> 61.22544
B37: V-000032 | C37: 45659 | D37: CL-024 | E37: Private Pay | F37: CG-017 | G37: Hours | H37: 3.98 | I37: 0 | J37: =H37-I37 -> 3.98 | K37: 34 | L37: =J37*K37 -> 135.32 | M37: =H37*16.43*(1+'Chart of Accounts'!$E$67) -> 74.873153
B38: V-000033 | C38: 45659 | D38: CL-025 | E38: Private Pay | F38: CG-019 | G38: Hours | H38: 3.97 | I38: 0 | J38: =H38-I38 -> 3.97 | K38: 34 | L38: =J38*K38 -> 134.98 | M38: =H38*14.93*(1+'Chart of Accounts'!$E$67) -> 67.866555
B39: V-000034 | C39: 45659 | D39: CL-028 | E39: Medicaid Waiver | F39: CG-023 | G39: Hours | H39: 3.06 | I39: 0 | J39: =H39-I39 -> 3.06 | K39: 26.5 | L39: =J39*K39 -> 81.09 | M39: =H39*16.17*(1+'Chart of Accounts'!$E$67) -> 56.654829
B40: V-000035 | C40: 45659 | D40: CL-030 | E40: Private Pay | F40: CG-018 | G40: Hours | H40: 3.17 | I40: 0 | J40: =H40-I40 -> 3.17 | K40: 34 | L40: =J40*K40 -> 107.78 | M40: =H40*17.84*(1+'Chart of Accounts'!$E$67) -> 64.752956
B41: V-000036 | C41: 45659 | D41: CL-031 | E41: Medicaid Waiver | F41: CG-038 | G41: Hours | H41: 4.06 | I41: 0 | J41: =H41-I41 -> 4.06 | K41: 26.5 | L41: =J41*K41 -> 107.59 | M41: =H41*16.02*(1+'Chart of Accounts'!$E$67) -> 74.472174
B42: V-000037 | C42: 45659 | D42: CL-039 | E42: Private Pay | F42: CG-013 | G42: Hours | H42: 4.33 | I42: 0 | J42: =H42-I42 -> 4.33 | K42: 34 | L42: =J42*K42 -> 147.22 | M42: =H42*16.71*(1+'Chart of Accounts'!$E$67) -> 82.845674
B43: V-000038 | C43: 45659 | D43: CL-041 | E43: Private Pay | F43: CG-030 | G43: Hours | H43: 3.76 | I43: 0 | J43: =H43-I43 -> 3.76 | K43: 34 | L43: =J43*K43 -> 127.84 | M43: =H43*16.48*(1+'Chart of Accounts'!$E$67) -> 70.949696
B44: V-000039 | C44: 45659 | D44: CL-047 | E44: Private Pay | F44: CG-006 | G44: Hours | H44: 2.85 | I44: 0 | J44: =H44-I44 -> 2.85 | K44: 34 | L44: =J44*K44 -> 96.9 | M44: =H44*15.05*(1+'Chart of Accounts'!$E$67) -> 49.111913
B45: V-000040 | C45: 45659 | D45: CL-048 | E45: Medicaid Waiver | F45: CG-014 | G45: Hours | H45: 4.15 | I45: 0 | J45: =H45-I45 -> 4.15 | K45: 26.5 | L45: =J45*K45 -> 109.975 | M45: =H45*15.67*(1+'Chart of Accounts'!$E$67) -> 74.459923
B46: V-000041 | C46: 45659 | D46: CL-054 | E46: Medicaid Waiver | F46: CG-030 | G46: Hours | H46: 4.05 | I46: 0 | J46: =H46-I46 -> 4.05 | K46: 26.5 | L46: =J46*K46 -> 107.325 | M46: =H46*16.48*(1+'Chart of Accounts'!$E$67) -> 76.42188
B47: V-000042 | C47: 45659 | D47: CL-055 | E47: Private Pay | F47: CG-018 | G47: Hours | H47: 4.13 | I47: 0 | J47: =H47-I47 -> 4.13 | K47: 34 | L47: =J47*K47 -> 140.42 | M47: =H47*17.84*(1+'Chart of Accounts'!$E$67) -> 84.362684
B48: V-000043 | C48: 45659 | D48: CL-057 | E48: Private Pay | F48: CG-028 | G48: Hours | H48: 3.61 | I48: 0 | J48: =H48-I48 -> 3.61 | K48: 34 | L48: =J48*K48 -> 122.74 | M48: =H48*17.99*(1+'Chart of Accounts'!$E$67) -> 74.360765
B49: V-000044 | C49: 45659 | D49: CL-060 | E49: Private Pay | F49: CG-034 | G49: Hours | H49: 3.95 | I49: 0 | J49: =H49-I49 -> 3.95 | K49: 34 | L49: =J49*K49 -> 134.3 | M49: =H49*17.1*(1+'Chart of Accounts'!$E$67) -> 77.339025
B50: V-000045 | C50: 45660 | D50: CL-001 | E50: Medicare (Skilled) | F50: CG-003 | G50: Visits | H50: 0.99 | I50: 0 | J50: =H50-I50 -> 0.99 | K50: 165 | L50: =J50*K50 -> 163.35 | M50: =H50*66.48*(1+'Chart of Accounts'!$E$67) -> 75.358404
B51: V-000046 | C51: 45660 | D51: CL-004 | E51: Private Pay | F51: CG-004 | G51: Hours | H51: 4.02 | I51: 0 | J51: =H51-I51 -> 4.02 | K51: 34 | L51: =J51*K51 -> 136.68 | M51: =H51*16.05*(1+'Chart of Accounts'!$E$67) -> 73.876545
B52: V-000047 | C52: 45660 | D52: CL-005 | E52: Medicaid Waiver | F52: CG-005 | G52: Hours | H52: 5.06 | I52: 0 | J52: =H52-I52 -> 5.06 | K52: 26.5 | L52: =J52*K52 -> 134.09 | M52: =H52*16*(1+'Chart of Accounts'!$E$67) -> 92.6992
B53: V-000048 | C53: 45660 | D53: CL-010 | E53: Medicare (Skilled) | F53: CG-012 | G53: Visits | H53: 1.07 | I53: 0 | J53: =H53-I53 -> 1.07 | K53: 165 | L53: =J53*K53 -> 176.55 | M53: =H53*73.58*(1+'Chart of Accounts'!$E$67) -> 90.146537
B54: V-000049 | C54: 45660 | D54: CL-012 | E54: Medicaid Waiver | F54: CG-010 | G54: Hours | H54: 3.8 | I54: 0 | J54: =H54-I54 -> 3.8 | K54: 26.5 | L54: =J54*K54 -> 100.7 | M54: =H54*16.36*(1+'Chart of Accounts'!$E$67) -> 71.18236
B55: V-000050 | C55: 45660 | D55: CL-014 | E55: Private Insurance | F55: CG-033 | G55: Visits | H55: 0.99 | I55: 0 | J55: =H55-I55 -> 0.99 | K55: 135 | L55: =J55*K55 -> 133.65 | M55: =H55*57.54*(1+'Chart of Accounts'!$E$67) -> 65.224467
B56: V-000051 | C56: 45660 | D56: CL-016 | E56: Private Pay | F56: CG-002 | G56: Hours | H56: 4.13 | I56: 0 | J56: =H56-I56 -> 4.13 | K56: 34 | L56: =J56*K56 -> 140.42 | M56: =H56*17.34*(1+'Chart of Accounts'!$E$67) -> 81.998259
B57: V-000052 | C57: 45660 | D57: CL-019 | E57: Medicare (Skilled) | F57: CG-024 | G57: Visits | H57: 0.97 | I57: 0 | J57: =H57-I57 -> 0.97 | K57: 165 | L57: =J57*K57 -> 160.05 | M57: =H57*89.53*(1+'Chart of Accounts'!$E$67) -> 99.436494
B58: V-000053 | C58: 45660 | D58: CL-020 | E58: Medicaid Waiver | F58: CG-016 | G58: Hours | H58: 3.81 | I58: 0 | J58: =H58-I58 -> 3.81 | K58: 26.5 | L58: =J58*K58 -> 100.965 | M58: =H58*16.19*(1+'Chart of Accounts'!$E$67) -> 70.628066
B59: V-000054 | C59: 45660 | D59: CL-021 | E59: Private Insurance | F59: CG-040 | G59: Visits | H59: 1.08 | I59: 0 | J59: =H59-I59 -> 1.08 | K59: 135 | L59: =J59*K59 -> 145.8 | M59: =H59*75.18*(1+'Chart of Accounts'!$E$67) -> 92.967588
B60: V-000055 | C60: 45660 | D60: CL-023 | E60: Medicare (Skilled) | F60: CG-021 | G60: Visits | H60: 0.94 | I60: 0 | J60: =H60-I60 -> 0.94 | K60: 165 | L60: =J60*K60 -> 155.1 | M60: =H60*51.07*(1+'Chart of Accounts'!$E$67) -> 54.966641
B61: V-000056 | C61: 45660 | D61: CL-024 | E61: Private Pay | F61: CG-017 | G61: Hours | H61: 4.04 | I61: 0 | J61: =H61-I61 -> 4.04 | K61: 34 | L61: =J61*K61 -> 137.36 | M61: =H61*16.43*(1+'Chart of Accounts'!$E$67) -> 76.001894
B62: V-000057 | C62: 45660 | D62: CL-027 | E62: Medicaid Waiver | F62: CG-001 | G62: Hours | H62: 4.17 | I62: 0.125 | J62: =H62-I62 -> 4.045 | K62: 26.5 | L62: =J62*K62 -> 107.1925 | M62: =H62*14.56*(1+'Chart of Accounts'!$E$67) -> 69.518904
B63: V-000058 | C63: 45660 | D63: CL-029 | E63: Medicaid Waiver | F63: CG-028 | G63: Hours | H63: 3.2 | I63: 0 | J63: =H63-I63 -> 3.2 | K63: 26.5 | L63: =J63*K63 -> 84.8 | M63: =H63*17.99*(1+'Chart of Accounts'!$E$67) -> 65.91536
B64: V-000059 | C64: 45660 | D64: CL-036 | E64: Medicaid Waiver | F64: CG-034 | G64: Hours | H64: 3.44 | I64: 0 | J64: =H64-I64 -> 3.44 | K64: 26.5 | L64: =J64*K64 -> 91.16 | M64: =H64*17.1*(1+'Chart of Accounts'!$E$67) -> 67.35348
B65: V-000060 | C65: 45660 | D65: CL-037 | E65: Medicaid Waiver | F65: CG-008 | G65: Hours | H65: 3.23 | I65: 0 | J65: =H65-I65 -> 3.23 | K65: 26.5 | L65: =J65*K65 -> 85.595 | M65: =H65*15.19*(1+'Chart of Accounts'!$E$67) -> 56.177937
B66: V-000061 | C66: 45660 | D66: CL-038 | E66: Medicaid Waiver | F66: CG-011 | G66: Hours | H66: 3.23 | I66: 0 | J66: =H66-I66 -> 3.23 | K66: 26.5 | L66: =J66*K66 -> 85.595 | M66: =H66*16.65*(1+'Chart of Accounts'!$E$67) -> 61.577528
B67: V-000062 | C67: 45660 | D67: CL-039 | E67: Private Pay | F67: CG-013 | G67: Hours | H67: 3.78 | I67: 0 | J67: =H67-I67 -> 3.78 | K67: 34 | L67: =J67*K67 -> 128.52 | M67: =H67*16.71*(1+'Chart of Accounts'!$E$67) -> 72.322551
B68: V-000063 | C68: 45660 | D68: CL-040 | E68: Medicare (Skilled) | F68: CG-012 | G68: Visits | H68: 1.05 | I68: 0 | J68: =H68-I68 -> 1.05 | K68: 165 | L68: =J68*K68 -> 173.25 | M68: =H68*73.58*(1+'Chart of Accounts'!$E$67) -> 88.461555
B69: V-000064 | C69: 45660 | D69: CL-045 | E69: Medicaid Waiver | F69: CG-023 | G69: Hours | H69: 4.38 | I69: 0 | J69: =H69-I69 -> 4.38 | K69: 26.5 | L69: =J69*K69 -> 116.07 | M69: =H69*16.17*(1+'Chart of Accounts'!$E$67) -> 81.094167
B70: V-000065 | C70: 45660 | D70: CL-049 | E70: Private Pay | F70: CG-019 | G70: Hours | H70: 4.75 | I70: 0 | J70: =H70-I70 -> 4.75 | K70: 34 | L70: =J70*K70 -> 161.5 | M70: =H70*14.93*(1+'Chart of Accounts'!$E$67) -> 81.200537
B71: V-000066 | C71: 45660 | D71: CL-050 | E71: Medicare (Skilled) | F71: CG-024 | G71: Visits | H71: 1.1 | I71: 0 | J71: =H71-I71 -> 1.1 | K71: 165 | L71: =J71*K71 -> 181.5 | M71: =H71*89.53*(1+'Chart of Accounts'!$E$67) -> 112.76304
B72: V-000067 | C72: 45660 | D72: CL-054 | E72: Medicaid Waiver | F72: CG-030 | G72: Hours | H72: 3.89 | I72: 0 | J72: =H72-I72 -> 3.89 | K72: 26.5 | L72: =J72*K72 -> 103.085 | M72: =H72*16.48*(1+'Chart of Accounts'!$E$67) -> 73.402744
B73: V-000068 | C73: 45660 | D73: CL-055 | E73: Private Pay | F73: CG-018 | G73: Hours | H73: 3.7 | I73: 0 | J73: =H73-I73 -> 3.7 | K73: 34 | L73: =J73*K73 -> 125.8 | M73: =H73*17.84*(1+'Chart of Accounts'!$E$67) -> 75.57916
B74: V-000069 | C74: 45660 | D74: CL-057 | E74: Private Pay | F74: CG-028 | G74: Hours | H74: 3.83 | I74: 0 | J74: =H74-I74 -> 3.83 | K74: 34 | L74: =J74*K74 -> 130.22 | M74: =H74*17.99*(1+'Chart of Accounts'!$E$67) -> 78.892447
B75: V-000070 | C75: 45660 | D75: CL-059 | E75: Medicaid Waiver | F75: CG-038 | G75: Hours | H75: 3.5 | I75: 0.105 | J75: =H75-I75 -> 3.395 | K75: 26.5 | L75: =J75*K75 -> 89.9675 | M75: =H75*16.02*(1+'Chart of Accounts'!$E$67) -> 64.20015
B76: V-000071 | C76: 45660 | D76: CL-060 | E76: Private Pay | F76: CG-034 | G76: Hours | H76: 3.83 | I76: 0 | J76: =H76-I76 -> 3.83 | K76: 34 | L76: =J76*K76 -> 130.22 | M76: =H76*17.1*(1+'Chart of Accounts'!$E$67) -> 74.989485
B77: V-000072 | C77: 45660 | D77: CL-063 | E77: Private Insurance | F77: CG-037 | G77: Visits | H77: 1.09 | I77: 0 | J77: =H77-I77 -> 1.09 | K77: 135 | L77: =J77*K77 -> 147.15 | M77: =H77*79.8*(1+'Chart of Accounts'!$E$67) -> 99.59439
B78: V-000073 | C78: 45660 | D78: CL-064 | E78: Medicaid Waiver | F78: CG-014 | G78: Hours | H78: 3.08 | I78: 0 | J78: =H78-I78 -> 3.08 | K78: 26.5 | L78: =J78*K78 -> 81.62 | M78: =H78*15.67*(1+'Chart of Accounts'!$E$67) -> 55.261822
B79: V-000074 | C79: 45660 | D79: CL-065 | E79: Medicaid Waiver | F79: CG-001 | G79: Hours | H79: 4.74 | I79: 0 | J79: =H79-I79 -> 4.74 | K79: 26.5 | L79: =J79*K79 -> 125.61 | M79: =H79*14.56*(1+'Chart of Accounts'!$E$67) -> 79.021488
B80: V-000075 | C80: 45661 | D80: CL-004 | E80: Private Pay | F80: CG-004 | G80: Hours | H80: 4.25 | I80: 0 | J80: =H80-I80 -> 4.25 | K80: 34 | L80: =J80*K80 -> 144.5 | M80: =H80*16.05*(1+'Chart of Accounts'!$E$67) -> 78.103313
B81: V-000076 | C81: 45661 | D81: CL-020 | E81: Medicaid Waiver | F81: CG-016 | G81: Hours | H81: 3.8 | I81: 0 | J81: =H81-I81 -> 3.8 | K81: 26.5 | L81: =J81*K81 -> 100.7 | M81: =H81*16.19*(1+'Chart of Accounts'!$E$67) -> 70.44269
B82: V-000077 | C82: 45661 | D82: CL-039 | E82: Private Pay | F82: CG-013 | G82: Hours | H82: 4.08 | I82: 0 | J82: =H82-I82 -> 4.08 | K82: 34 | L82: =J82*K82 -> 138.72 | M82: =H82*16.71*(1+'Chart of Accounts'!$E$67) -> 78.062436
B83: V-000078 | C83: 45661 | D83: CL-055 | E83: Private Pay | F83: CG-018 | G83: Hours | H83: 3.9 | I83: 0 | J83: =H83-I83 -> 3.9 | K83: 34 | L83: =J83*K83 -> 132.6 | M83: =H83*17.84*(1+'Chart of Accounts'!$E$67) -> 79.66452
B84: V-000079 | C84: 45661 | D84: CL-057 | E84: Private Pay | F84: CG-028 | G84: Hours | H84: 4.07 | I84: 0 | J84: =H84-I84 -> 4.07 | K84: 34 | L84: =J84*K84 -> 138.38 | M84: =H84*17.99*(1+'Chart of Accounts'!$E$67) -> 83.836099
B85: V-000080 | C85: 45661 | D85: CL-060 | E85: Private Pay | F85: CG-034 | G85: Hours | H85: 3.65 | I85: 0 | J85: =H85-I85 -> 3.65 | K85: 34 | L85: =J85*K85 -> 124.1 | M85: =H85*17.1*(1+'Chart of Accounts'!$E$67) -> 71.465175
B86: V-000081 | C86: 45662 | D86: CL-004 | E86: Private Pay | F86: CG-004 | G86: Hours | H86: 4.21 | I86: 0 | J86: =H86-I86 -> 4.21 | K86: 34 | L86: =J86*K86 -> 143.14 | M86: =H86*16.05*(1+'Chart of Accounts'!$E$67) -> 77.368223
B87: V-000082 | C87: 45662 | D87: CL-020 | E87: Medicaid Waiver | F87: CG-016 | G87: Hours | H87: 3.66 | I87: 0 | J87: =H87-I87 -> 3.66 | K87: 26.5 | L87: =J87*K87 -> 96.99 | M87: =H87*16.19*(1+'Chart of Accounts'!$E$67) -> 67.847433
B88: V-000083 | C88: 45662 | D88: CL-039 | E88: Private Pay | F88: CG-013 | G88: Hours | H88: 3.73 | I88: 0 | J88: =H88-I88 -> 3.73 | K88: 34 | L88: =J88*K88 -> 126.82 | M88: =H88*16.71*(1+'Chart of Accounts'!$E$67) -> 71.365904
B89: V-000084 | C89: 45662 | D89: CL-055 | E89: Private Pay | F89: CG-018 | G89: Hours | H89: 3.98 | I89: 0 | J89: =H89-I89 -> 3.98 | K89: 34 | L89: =J89*K89 -> 135.32 | M89: =H89*17.84*(1+'Chart of Accounts'!$E$67) -> 81.298664
B90: V-000085 | C90: 45662 | D90: CL-057 | E90: Private Pay | F90: CG-028 | G90: Hours | H90: 3.83 | I90: 0 | J90: =H90-I90 -> 3.83 | K90: 34 | L90: =J90*K90 -> 130.22 | M90: =H90*17.99*(1+'Chart of Accounts'!$E$67) -> 78.892447
B91: V-000086 | C91: 45662 | D91: CL-060 | E91: Private Pay | F91: CG-034 | G91: Hours | H91: 3.79 | I91: 0 | J91: =H91-I91 -> 3.79 | K91: 34 | L91: =J91*K91 -> 128.86 | M91: =H91*17.1*(1+'Chart of Accounts'!$E$67) -> 74.206305
B92: V-000087 | C92: 45663 | D92: CL-001 | E92: Medicare (Skilled) | F92: CG-003 | G92: Visits | H92: 1.02 | I92: 0 | J92: =H92-I92 -> 1.02 | K92: 165 | L92: =J92*K92 -> 168.3 | M92: =H92*66.48*(1+'Chart of Accounts'!$E$67) -> 77.641992
B93: V-000088 | C93: 45663 | D93: CL-004 | E93: Private Pay | F93: CG-004 | G93: Hours | H93: 3.69 | I93: 0 | J93: =H93-I93 -> 3.69 | K93: 34 | L93: =J93*K93 -> 125.46 | M93: =H93*16.05*(1+'Chart of Accounts'!$E$67) -> 67.812052
B94: V-000089 | C94: 45663 | D94: CL-005 | E94: Medicaid Waiver | F94: CG-005 | G94: Hours | H94: 4.45 | I94: 0.134 | J94: =H94-I94 -> 4.316 | K94: 26.5 | L94: =J94*K94 -> 114.374 | M94: =H94*16*(1+'Chart of Accounts'!$E$67) -> 81.524
B95: V-000090 | C95: 45663 | D95: CL-008 | E95: Private Pay | F95: CG-008 | G95: Hours | H95: 3.18 | I95: 0 | J95: =H95-I95 -> 3.18 | K95: 34 | L95: =J95*K95 -> 108.12 | M95: =H95*15.19*(1+'Chart of Accounts'!$E$67) -> 55.308309
B96: V-000091 | C96: 45663 | D96: CL-012 | E96: Medicaid Waiver | F96: CG-010 | G96: Hours | H96: 4.34 | I96: 0 | J96: =H96-I96 -> 4.34 | K96: 26.5 | L96: =J96*K96 -> 115.01 | M96: =H96*16.36*(1+'Chart of Accounts'!$E$67) -> 81.297748
B97: V-000092 | C97: 45663 | D97: CL-014 | E97: Private Insurance | F97: CG-033 | G97: Visits | H97: 0.96 | I97: 0 | J97: =H97-I97 -> 0.96 | K97: 135 | L97: =J97*K97 -> 129.6 | M97: =H97*57.54*(1+'Chart of Accounts'!$E$67) -> 63.247968
B98: V-000093 | C98: 45663 | D98: CL-015 | E98: Medicaid Waiver | F98: CG-006 | G98: Hours | H98: 3.02 | I98: 0 | J98: =H98-I98 -> 3.02 | K98: 26.5 | L98: =J98*K98 -> 80.03 | M98: =H98*15.05*(1+'Chart of Accounts'!$E$67) -> 52.041395
B99: V-000094 | C99: 45663 | D99: CL-016 | E99: Private Pay | F99: CG-002 | G99: Hours | H99: 4.31 | I99: 0 | J99: =H99-I99 -> 4.31 | K99: 34 | L99: =J99*K99 -> 146.54 | M99: =H99*17.34*(1+'Chart of Accounts'!$E$67) -> 85.572033
B100: V-000095 | C100: 45663 | D100: CL-018 | E100: Private Pay | F100: CG-011 | G100: Hours | H100: 2.72 | I100: 0 | J100: =H100-I100 -> 2.72 | K100: 34 | L100: =J100*K100 -> 92.48 | M100: =H100*16.65*(1+'Chart of Accounts'!$E$67) -> 51.85476
B101: V-000096 | C101: 45663 | D101: CL-020 | E101: Medicaid Waiver | F101: CG-016 | G101: Hours | H101: 4.29 | I101: 0.129 | J101: =H101-I101 -> 4.161 | K101: 26.5 | L101: =J101*K101 -> 110.2665 | M101: =H101*16.19*(1+'Chart of Accounts'!$E$67) -> 79.526089
B102: V-000097 | C102: 45663 | D102: CL-022 | E102: Medicaid Waiver | F102: CG-013 | G102: Hours | H102: 3.16 | I102: 0 | J102: =H102-I102 -> 3.16 | K102: 26.5 | L102: =J102*K102 -> 83.74 | M102: =H102*16.71*(1+'Chart of Accounts'!$E$67) -> 60.460122
...

Sheet Daily Payroll Register
B2: Daily Payroll Register - Every Caregiver, Every Day, Full Year
B3: 5,973 payroll records. Source of truth for all direct labor cost across the workbook.
B5: Pay ID | C5: Date | D5: Caregiver ID | E5: Pay Type | F5: Reg Hours | G5: OT Hours | H5: Rate | I5: Reg Pay | J5: OT Pay | K5: Miles | L5: Mileage Pay | M5: Visits | N5: Per-Visit Pay | O5: Gross Pay
B6: P-000001 | C6: 45658 | D6: CG-003 | E6: Per Visit | H6: 66.48 | M6: 1 | N6: =M6*H6 -> 66.48 | O6: =N6 -> 66.48
B7: P-000002 | C7: 45658 | D7: CG-021 | E7: Per Visit | H7: 51.07 | M7: 1 | N7: =M7*H7 -> 51.07 | O7: =N7 -> 51.07
B8: P-000003 | C8: 45658 | D8: CG-004 | E8: Hourly | F8: 4.39 | G8: 0 | H8: 16.05 | I8: =F8*H8 -> 70.4595 | J8: =G8*H8*1.5 -> 0 | K8: 11.51 | L8: =K8*'Chart of Accounts'!$E$68 -> 7.7117 | O8: =I8+J8+L8 -> 78.1712
B9: P-000004 | C9: 45658 | D9: CG-005 | E9: Hourly | F9: 5.03 | G9: 0 | H9: 16 | I9: =F9*H9 -> 80.48 | J9: =G9*H9*1.5 -> 0 | K9: 11.77 | L9: =K9*'Chart of Accounts'!$E$68 -> 7.8859 | O9: =I9+J9+L9 -> 88.3659
B10: P-000005 | C10: 45658 | D10: CG-010 | E10: Hourly | F10: 4 | G10: 0 | H10: 16.36 | I10: =F10*H10 -> 65.44 | J10: =G10*H10*1.5 -> 0 | K10: 13.16 | L10: =K10*'Chart of Accounts'!$E$68 -> 8.8172 | O10: =I10+J10+L10 -> 74.2572
B11: P-000006 | C11: 45658 | D11: CG-033 | E11: Per Visit | H11: 57.54 | M11: 1 | N11: =M11*H11 -> 57.54 | O11: =N11 -> 57.54
B12: P-000007 | C12: 45658 | D12: CG-002 | E12: Hourly | F12: 3.81 | G12: 0 | H12: 17.34 | I12: =F12*H12 -> 66.0654 | J12: =G12*H12*1.5 -> 0 | K12: 9.87 | L12: =K12*'Chart of Accounts'!$E$68 -> 6.6129 | O12: =I12+J12+L12 -> 72.6783
B13: P-000008 | C13: 45658 | D13: CG-016 | E13: Hourly | F13: 4.21 | G13: 0 | H13: 16.19 | I13: =F13*H13 -> 68.1599 | J13: =G13*H13*1.5 -> 0 | K13: 12.19 | L13: =K13*'Chart of Accounts'!$E$68 -> 8.1673 | O13: =I13+J13+L13 -> 76.3272
B14: P-000009 | C14: 45658 | D14: CG-017 | E14: Hourly | F14: 3.82 | G14: 0 | H14: 16.43 | I14: =F14*H14 -> 62.7626 | J14: =G14*H14*1.5 -> 0 | K14: 8.83 | L14: =K14*'Chart of Accounts'!$E$68 -> 5.9161 | O14: =I14+J14+L14 -> 68.6787
B15: P-000010 | C15: 45658 | D15: CG-001 | E15: Hourly | F15: 8.83 | G15: 0 | H15: 14.56 | I15: =F15*H15 -> 128.5648 | J15: =G15*H15*1.5 -> 0 | K15: 24.15 | L15: =K15*'Chart of Accounts'!$E$68 -> 16.1805 | O15: =I15+J15+L15 -> 144.7453
B16: P-000011 | C16: 45658 | D16: CG-028 | E16: Hourly | F16: 7.23 | G16: 0 | H16: 17.99 | I16: =F16*H16 -> 130.0677 | J16: =G16*H16*1.5 -> 0 | K16: 17.27 | L16: =K16*'Chart of Accounts'!$E$68 -> 11.5709 | O16: =I16+J16+L16 -> 141.6386
B17: P-000012 | C17: 45658 | D17: CG-034 | E17: Hourly | F17: 7.5 | G17: 0 | H17: 17.1 | I17: =F17*H17 -> 128.25 | J17: =G17*H17*1.5 -> 0 | K17: 16.79 | L17: =K17*'Chart of Accounts'!$E$68 -> 11.2493 | O17: =I17+J17+L17 -> 139.4993
B18: P-000013 | C18: 45658 | D18: CG-008 | E18: Hourly | F18: 3.36 | G18: 0 | H18: 15.19 | I18: =F18*H18 -> 51.0384 | J18: =G18*H18*1.5 -> 0 | K18: 7.74 | L18: =K18*'Chart of Accounts'!$E$68 -> 5.1858 | O18: =I18+J18+L18 -> 56.2242
B19: P-000014 | C19: 45658 | D19: CG-011 | E19: Hourly | F19: 3.28 | G19: 0 | H19: 16.65 | I19: =F19*H19 -> 54.612 | J19: =G19*H19*1.5 -> 0 | K19: 10.26 | L19: =K19*'Chart of Accounts'!$E$68 -> 6.8742 | O19: =I19+J19+L19 -> 61.4862
B20: P-000015 | C20: 45658 | D20: CG-013 | E20: Hourly | F20: 4.16 | G20: 0 | H20: 16.71 | I20: =F20*H20 -> 69.5136 | J20: =G20*H20*1.5 -> 0 | K20: 10.57 | L20: =K20*'Chart of Accounts'!$E$68 -> 7.0819 | O20: =I20+J20+L20 -> 76.5955
B21: P-000016 | C21: 45658 | D21: CG-019 | E21: Hourly | F21: 4.48 | G21: 0 | H21: 14.93 | I21: =F21*H21 -> 66.8864 | J21: =G21*H21*1.5 -> 0 | K21: 11.38 | L21: =K21*'Chart of Accounts'!$E$68 -> 7.6246 | O21: =I21+J21+L21 -> 74.511
B22: P-000017 | C22: 45658 | D22: CG-030 | E22: Hourly | F22: 4.27 | G22: 0 | H22: 16.48 | I22: =F22*H22 -> 70.3696 | J22: =G22*H22*1.5 -> 0 | K22: 10.99 | L22: =K22*'Chart of Accounts'!$E$68 -> 7.3633 | O22: =I22+J22+L22 -> 77.7329
B23: P-000018 | C23: 45658 | D23: CG-018 | E23: Hourly | F23: 4.24 | G23: 0 | H23: 17.84 | I23: =F23*H23 -> 75.6416 | J23: =G23*H23*1.5 -> 0 | K23: 9.68 | L23: =K23*'Chart of Accounts'!$E$68 -> 6.4856 | O23: =I23+J23+L23 -> 82.1272
B24: P-000019 | C24: 45658 | D24: CG-009 | E24: Per Visit | H24: 49.43 | M24: 1 | N24: =M24*H24 -> 49.43 | O24: =N24 -> 49.43
B25: P-000020 | C25: 45658 | D25: CG-038 | E25: Hourly | F25: 3.56 | G25: 0 | H25: 16.02 | I25: =F25*H25 -> 57.0312 | J25: =G25*H25*1.5 -> 0 | K25: 8.32 | L25: =K25*'Chart of Accounts'!$E$68 -> 5.5744 | O25: =I25+J25+L25 -> 62.6056
B26: P-000021 | C26: 45658 | D26: CG-014 | E26: Hourly | F26: 3.44 | G26: 0 | H26: 15.67 | I26: =F26*H26 -> 53.9048 | J26: =G26*H26*1.5 -> 0 | K26: 8.46 | L26: =K26*'Chart of Accounts'!$E$68 -> 5.6682 | O26: =I26+J26+L26 -> 59.573
B27: P-000022 | C27: 45659 | D27: CG-004 | E27: Hourly | F27: 3.86 | G27: 0 | H27: 16.05 | I27: =F27*H27 -> 61.953 | J27: =G27*H27*1.5 -> 0 | K27: 9.41 | L27: =K27*'Chart of Accounts'!$E$68 -> 6.3047 | O27: =I27+J27+L27 -> 68.2577
B28: P-000023 | C28: 45659 | D28: CG-008 | E28: Hourly | F28: 3.23 | G28: 0 | H28: 15.19 | I28: =F28*H28 -> 49.0637 | J28: =G28*H28*1.5 -> 0 | K28: 8.04 | L28: =K28*'Chart of Accounts'!$E$68 -> 5.3868 | O28: =I28+J28+L28 -> 54.4505
B29: P-000024 | C29: 45659 | D29: CG-006 | E29: Hourly | F29: 5.8 | G29: 0 | H29: 15.05 | I29: =F29*H29 -> 87.29 | J29: =G29*H29*1.5 -> 0 | K29: 15.92 | L29: =K29*'Chart of Accounts'!$E$68 -> 10.6664 | O29: =I29+J29+L29 -> 97.9564
B30: P-000025 | C30: 45659 | D30: CG-002 | E30: Hourly | F30: 4.2 | G30: 0 | H30: 17.34 | I30: =F30*H30 -> 72.828 | J30: =G30*H30*1.5 -> 0 | K30: 10.39 | L30: =K30*'Chart of Accounts'!$E$68 -> 6.9613 | O30: =I30+J30+L30 -> 79.7893
B31: P-000026 | C31: 45659 | D31: CG-011 | E31: Hourly | F31: 2.83 | G31: 0 | H31: 16.65 | I31: =F31*H31 -> 47.1195 | J31: =G31*H31*1.5 -> 0 | K31: 8.24 | L31: =K31*'Chart of Accounts'!$E$68 -> 5.5208 | O31: =I31+J31+L31 -> 52.6403
B32: P-000027 | C32: 45659 | D32: CG-016 | E32: Hourly | F32: 3.63 | G32: 0 | H32: 16.19 | I32: =F32*H32 -> 58.7697 | J32: =G32*H32*1.5 -> 0 | K32: 12.45 | L32: =K32*'Chart of Accounts'!$E$68 -> 8.3415 | O32: =I32+J32+L32 -> 67.1112
B33: P-000028 | C33: 45659 | D33: CG-013 | E33: Hourly | F33: 7.53 | G33: 0 | H33: 16.71 | I33: =F33*H33 -> 125.8263 | J33: =G33*H33*1.5 -> 0 | K33: 20.73 | L33: =K33*'Chart of Accounts'!$E$68 -> 13.8891 | O33: =I33+J33+L33 -> 139.7154
B34: P-000029 | C34: 45659 | D34: CG-017 | E34: Hourly | F34: 3.98 | G34: 0 | H34: 16.43 | I34: =F34*H34 -> 65.3914 | J34: =G34*H34*1.5 -> 0 | K34: 10.38 | L34: =K34*'Chart of Accounts'!$E$68 -> 6.9546 | O34: =I34+J34+L34 -> 72.346
B35: P-000030 | C35: 45659 | D35: CG-019 | E35: Hourly | F35: 3.97 | G35: 0 | H35: 14.93 | I35: =F35*H35 -> 59.2721 | J35: =G35*H35*1.5 -> 0 | K35: 13.78 | L35: =K35*'Chart of Accounts'!$E$68 -> 9.2326 | O35: =I35+J35+L35 -> 68.5047
B36: P-000031 | C36: 45659 | D36: CG-023 | E36: Hourly | F36: 3.06 | G36: 0 | H36: 16.17 | I36: =F36*H36 -> 49.4802 | J36: =G36*H36*1.5 -> 0 | K36: 6.93 | L36: =K36*'Chart of Accounts'!$E$68 -> 4.6431 | O36: =I36+J36+L36 -> 54.1233
... B42: P-000037 | C42: 45659 | D42: CG-034 | E42: Hourly | F42: 3.95 | G42: 0 | H42: 17.1 | I42: =F42*H42 -> 67.545 | J42: =G42*H42*1.5 -> 0 | K42: 11.7 | L42: =K42*'Chart of Accounts'!$E$68 -> 7.839 | O42: =I42+J42+L42 -> 75.384
B43: P-000038 | C43: 45660 | D43: CG-003 | E43: Per Visit | H43: 66.48 | M43: 1 | N43: =M43*H43 -> 66.48 | O43: =N43 -> 66.48
B44: P-000039 | C44: 45660 | D44: CG-004 | E44: Hourly | F44: 4.02 | G44: 0 | H44: 16.05 | I44: =F44*H44 -> 64.521 | J44: =G44*H44*1.5 -> 0 | K44: 13.21 | L44: =K44*'Chart of Accounts'!$E$68 -> 8.8507 | O44: =I44+J44+L44 -> 73.3717
B45: P-000040 | C45: 45660 | D45: CG-005 | E45: Hourly | F45: 5.06 | G45: 0 | H45: 16 | I45: =F45*H45 -> 80.96 | J45: =G45*H45*1.5 -> 0 | K45: 13.8 | L45: =K45*'Chart of Accounts'!$E$68 -> 9.246 | O45: =I45+J45+L45 -> 90.206
B46: P-000041 | C46: 45660 | D46: CG-012 | E46: Per Visit | H46: 73.58 | M46: 2 | N46: =M46*H46 -> 147.16 | O46: =N46 -> 147.16
B47: P-000042 | C47: 45660 | D47: CG-010 | E47: Hourly | F47: 3.8 | G47: 0 | H47: 16.36 | I47: =F47*H47 -> 62.168 | J47: =G47*H47*1.5 -> 0 | K47: 12.3 | L47: =K47*'Chart of Accounts'!$E$68 -> 8.241 | O47: =I47+J47+L47 -> 70.409
B48: P-000043 | C48: 45660 | D48: CG-033 | E48: Per Visit | H48: 57.54 | M48: 1 | N48: =M48*H48 -> 57.54 | O48: =N48 -> 57.54
B49: P-000044 | C49: 45660 | D49: CG-002 | E49: Hourly | F49: 4.13 | G49: 0 | H49: 17.34 | I49: =F49*H49 -> 71.6142 | J49: =G49*H49*1.5 -> 0 | K49: 11.24 | L49: =K49*'Chart of Accounts'!$E$68 -> 7.5308 | O49: =I49+J49+L49 -> 79.145
B50: P-000045 | C50: 45660 | D50: CG-024 | E50: Per Visit | H50: 89.53 | M50: 2 | N50: =M50*H50 -> 179.06 | O50: =N50 -> 179.06
B51: P-000046 | C51: 45660 | D51: CG-016 | E51: Hourly | F51: 3.81 | G51: 0 | H51: 16.19 | I51: =F51*H51 -> 61.6839 | J51: =G51*H51*1.5 -> 0 | K51: 10.96 | L51: =K51*'Chart of Accounts'!$E$68 -> 7.3432 | O51: =I51+J51+L51 -> 69.0271
B52: P-000047 | C52: 45660 | D52: CG-040 | E52: Per Visit | H52: 75.18 | M52: 1 | N52: =M52*H52 -> 75.18 | O52: =N52 -> 75.18
B53: P-000048 | C53: 45660 | D53: CG-021 | E53: Per Visit | H53: 51.07 | M53: 1 | N53: =M53*H53 -> 51.07 | O53: =N53 -> 51.07
B54: P-000049 | C54: 45660 | D54: CG-017 | E54: Hourly | F54: 4.04 | G54: 0 | H54: 16.43 | I54: =F54*H54 -> 66.3772 | J54: =G54*H54*1.5 -> 0 | K54: 12.59 | L54: =K54*'Chart of Accounts'!$E$68 -> 8.4353 | O54: =I54+J54+L54 -> 74.8125
B55: P-000050 | C55: 45660 | D55: CG-001 | E55: Hourly | F55: 8.91 | G55: 0 | H55: 14.56 | I55: =F55*H55 -> 129.7296 | J55: =G55*H55*1.5 -> 0 | K55: 28.2 | L55: =K55*'Chart of Accounts'!$E$68 -> 18.894 | O55: =I55+J55+L55 -> 148.6236
B56: P-000051 | C56: 45660 | D56: CG-028 | E56: Hourly | F56: 7.03 | G56: 0 | H56: 17.99 | I56: =F56*H56 -> 126.4697 | J56: =G56*H56*1.5 -> 0 | K56: 16.11 | L56: =K56*'Chart of Accounts'!$E$68 -> 10.7937 | O56: =I56+J56+L56 -> 137.2634
B57: P-000052 | C57: 45660 | D57: CG-034 | E57: Hourly | F57: 7.27 | G57: 0 | H57: 17.1 | I57: =F57*H57 -> 124.317 | J57: =G57*H57*1.5 -> 0 | K57: 20.23 | L57: =K57*'Chart of Accounts'!$E$68 -> 13.5541 | O57: =I57+J57+L57 -> 137.8711
B58: P-000053 | C58: 45660 | D58: CG-008 | E58: Hourly | F58: 3.23 | G58: 0 | H58: 15.19 | I58: =F58*H58 -> 49.0637 | J58: =G58*H58*1.5 -> 0 | K58: 11.44 | L58: =K58*'Chart of Accounts'!$E$68 -> 7.6648 | O58: =I58+J58+L58 -> 56.7285
B59: P-000054 | C59: 45660 | D59: CG-011 | E59: Hourly | F59: 3.23 | G59: 0 | H59: 16.65 | I59: =F59*H59 -> 53.7795 | J59: =G59*H59*1.5 -> 0 | K59: 9.36 | L59: =K59*'Chart of Accounts'!$E$68 -> 6.2712 | O59: =I59+J59+L59 -> 60.0507
B60: P-000055 | C60: 45660 | D60: CG-013 | E60: Hourly | F60: 3.78 | G60: 0 | H60: 16.71 | I60: =F60*H60 -> 63.1638 | J60: =G60*H60*1.5 -> 0 | K60: 8.54 | L60: =K60*'Chart of Accounts'!$E$68 -> 5.7218 | O60: =I60+J60+L60 -> 68.8856
B61: P-000056 | C61: 45660 | D61: CG-023 | E61: Hourly | F61: 4.38 | G61: 0 | H61: 16.17 | I61: =F61*H61 -> 70.8246 | J61: =G61*H61*1.5 -> 0 | K61: 12.98 | L61: =K61*'Chart of Accounts'!$E$68 -> 8.6966 | O61: =I61+J61+L61 -> 79.5212
B62: P-000057 | C62: 45660 | D62: CG-019 | E62: Hourly | F62: 4.75 | G62: 0 | H62: 14.93 | I62: =F62*H62 -> 70.9175 | J62: =G62*H62*1.5 -> 0 | K62: 16.07 | L62: =K62*'Chart of Accounts'!$E$68 -> 10.7669 | O62: =I62+J62+L62 -> 81.6844
B63: P-000058 | C63: 45660 | D63: CG-030 | E63: Hourly | F63: 3.89 | G63: 0 | H63: 16.48 | I63: =F63*H63 -> 64.1072 | J63: =G63*H63*1.5 -> 0 | K63: 10.71 | L63: =K63*'Chart of Accounts'!$E$68 -> 7.1757 | O63: =I63+J63+L63 -> 71.2829
B64: P-000059 | C64: 45660 | D64: CG-018 | E64: Hourly | F64: 3.7 | G64: 0 | H64: 17.84 | I64: =F64*H64 -> 66.008 | J64: =G64*H64*1.5 -> 0 | K64: 8.4 | L64: =K64*'Chart of Accounts'!$E$68 -> 5.628 | O64: =I64+J64+L64 -> 71.636
B65: P-000060 | C65: 45660 | D65: CG-038 | E65: Hourly | F65: 3.5 | G65: 0 | H65: 16.02 | I65: =F65*H65 -> 56.07 | J65: =G65*H65*1.5 -> 0 | K65: 9.17 | L65: =K65*'Chart of Accounts'!$E$68 -> 6.1439 | O65: =I65+J65+L65 -> 62.2139
B66: P-000061 | C66: 45660 | D66: CG-037 | E66: Per Visit | H66: 79.8 | M66: 1 | N66: =M66*H66 -> 79.8 | O66: =N66 -> 79.8
B67: P-000062 | C67: 45660 | D67: CG-014 | E67: Hourly | F67: 3.08 | G67: 0 | H67: 15.67 | I67: =F67*H67 -> 48.2636 | J67: =G67*H67*1.5 -> 0 | K67: 8.94 | L67: =K67*'Chart of Accounts'!$E$68 -> 5.9898 | O67: =I67+J67+L67 -> 54.2534
B68: P-000063 | C68: 45661 | D68: CG-004 | E68: Hourly | F68: 4.25 | G68: 0 | H68: 16.05 | I68: =F68*H68 -> 68.2125 | J68: =G68*H68*1.5 -> 0 | K68: 14.19 | L68: =K68*'Chart of Accounts'!$E$68 -> 9.5073 | O68: =I68+J68+L68 -> 77.7198
B69: P-000064 | C69: 45661 | D69: CG-016 | E69: Hourly | F69: 3.8 | G69: 0 | H69: 16.19 | I69: =F69*H69 -> 61.522 | J69: =G69*H69*1.5 -> 0 | K69: 9.54 | L69: =K69*'Chart of Accounts'!$E$68 -> 6.3918 | O69: =I69+J69+L69 -> 67.9138
B70: P-000065 | C70: 45661 | D70: CG-013 | E70: Hourly | F70: 4.08 | G70: 0 | H70: 16.71 | I70: =F70*H70 -> 68.1768 | J70: =G70*H70*1.5 -> 0 | K70: 10.27 | L70: =K70*'Chart of Accounts'!$E$68 -> 6.8809 | O70: =I70+J70+L70 -> 75.0577
B71: P-000066 | C71: 45661 | D71: CG-018 | E71: Hourly | F71: 3.9 | G71: 0 | H71: 17.84 | I71: =F71*H71 -> 69.576 | J71: =G71*H71*1.5 -> 0 | K71: 13.1 | L71: =K71*'Chart of Accounts'!$E$68 -> 8.777 | O71: =I71+J71+L71 -> 78.353
B72: P-000067 | C72: 45661 | D72: CG-028 | E72: Hourly | F72: 4.07 | G72: 0 | H72: 17.99 | I72: =F72*H72 -> 73.2193 | J72: =G72*H72*1.5 -> 0 | K72: 9.88 | L72: =K72*'Chart of Accounts'!$E$68 -> 6.6196 | O72: =I72+J72+L72 -> 79.8389
B73: P-000068 | C73: 45661 | D73: CG-034 | E73: Hourly | F73: 3.65 | G73: 0 | H73: 17.1 | I73: =F73*H73 -> 62.415 | J73: =G73*H73*1.5 -> 0 | K73: 12.35 | L73: =K73*'Chart of Accounts'!$E$68 -> 8.2745 | O73: =I73+J73+L73 -> 70.6895
B74: P-000069 | C74: 45662 | D74: CG-004 | E74: Hourly | F74: 4.21 | G74: 0 | H74: 16.05 | I74: =F74*H74 -> 67.5705 | J74: =G74*H74*1.5 -> 0 | K74: 13.12 | L74: =K74*'Chart of Accounts'!$E$68 -> 8.7904 | O74: =I74+J74+L74 -> 76.3609
B75: P-000070 | C75: 45662 | D75: CG-016 | E75: Hourly | F75: 3.66 | G75: 0 | H75: 16.19 | I75: =F75*H75 -> 59.2554 | J75: =G75*H75*1.5 -> 0 | K75: 12.13 | L75: =K75*'Chart of Accounts'!$E$68 -> 8.1271 | O75: =I75+J75+L75 -> 67.3825
B76: P-000071 | C76: 45662 | D76: CG-013 | E76: Hourly | F76: 3.73 | G76: 0 | H76: 16.71 | I76: =F76*H76 -> 62.3283 | J76: =G76*H76*1.5 -> 0 | K76: 9.55 | L76: =K76*'Chart of Accounts'!$E$68 -> 6.3985 | O76: =I76+J76+L76 -> 68.7268
B77: P-000072 | C77: 45662 | D77: CG-018 | E77: Hourly | F77: 3.98 | G77: 0 | H77: 17.84 | I77: =F77*H77 -> 71.0032 | J77: =G77*H77*1.5 -> 0 | K77: 11.15 | L77: =K77*'Chart of Accounts'!$E$68 -> 7.4705 | O77: =I77+J77+L77 -> 78.4737
B78: P-000073 | C78: 45662 | D78: CG-028 | E78: Hourly | F78: 3.83 | G78: 0 | H78: 17.99 | I78: =F78*H78 -> 68.9017 | J78: =G78*H78*1.5 -> 0 | K78: 10.03 | L78: =K78*'Chart of Accounts'!$E$68 -> 6.7201 | O78: =I78+J78+L78 -> 75.6218
B79: P-000074 | C79: 45662 | D79: CG-034 | E79: Hourly | F79: 3.79 | G79: 0 | H79: 17.1 | I79: =F79*H79 -> 64.809 | J79: =G79*H79*1.5 -> 0 | K79: 11.46 | L79: =K79*'Chart of Accounts'!$E$68 -> 7.6782 | O79: =I79+J79+L79 -> 72.4872
B80: P-000075 | C80: 45663 | D80: CG-003 | E80: Per Visit | H80: 66.48 | M80: 1 | N80: =M80*H80 -> 66.48 | O80: =N80 -> 66.48
B81: P-000076 | C81: 45663 | D81: CG-004 | E81: Hourly | F81: 3.69 | G81: 0 | H81: 16.05 | I81: =F81*H81 -> 59.2245 | J81: =G81*H81*1.5 -> 0 | K81: 8.55 | L81: =K81*'Chart of Accounts'!$E$68 -> 5.7285 | O81: =I81+J81+L81 -> 64.953
B82: P-000077 | C82: 45663 | D82: CG-005 | E82: Hourly | F82: 4.45 | G82: 0 | H82: 16 | I82: =F82*H82 -> 71.2 | J82: =G82*H82*1.5 -> 0 | K82: 10.02 | L82: =K82*'Chart of Accounts'!$E$68 -> 6.7134 | O82: =I82+J82+L82 -> 77.9134
B83: P-000078 | C83: 45663 | D83: CG-008 | E83: Hourly | F83: 6.76 | G83: 0 | H83: 15.19 | I83: =F83*H83 -> 102.6844 | J83: =G83*H83*1.5 -> 0 | K83: 21.67 | L83: =K83*'Chart of Accounts'!$E$68 -> 14.5189 | O83: =I83+J83+L83 -> 117.2033
B84: P-000079 | C84: 45663 | D84: CG-010 | E84: Hourly | F84: 4.34 | G84: 0 | H84: 16.36 | I84: =F84*H84 -> 71.0024 | J84: =G84*H84*1.5 -> 0 | K84: 13.71 | L84: =K84*'Chart of Accounts'!$E$68 -> 9.1857 | O84: =I84+J84+L84 -> 80.1881
B85: P-000080 | C85: 45663 | D85: CG-033 | E85: Per Visit | H85: 57.54 | M85: 1 | N85: =M85*H85 -> 57.54 | O85: =N85 -> 57.54
B86: P-000081 | C86: 45663 | D86: CG-006 | E86: Hourly | F86: 6.01 | G86: 0 | H86: 15.05 | I86: =F86*H86 -> 90.4505 | J86: =G86*H86*1.5 -> 0 | K86: 15.16 | L86: =K86*'Chart of Accounts'!$E$68 -> 10.1572 | O86: =I86+J86+L86 -> 100.6077
B87: P-000082 | C87: 45663 | D87: CG-002 | E87: Hourly | F87: 4.31 | G87: 0 | H87: 17.34 | I87: =F87*H87 -> 74.7354 | J87: =G87*H87*1.5 -> 0 | K87: 13.6 | L87: =K87*'Chart of Accounts'!$E$68 -> 9.112 | O87: =I87+J87+L87 -> 83.8474
B88: P-000083 | C88: 45663 | D88: CG-011 | E88: Hourly | F88: 6.3 | G88: 0 | H88: 16.65 | I88: =F88*H88 -> 104.895 | J88: =G88*H88*1.5 -> 0 | K88: 17.27 | L88: =K88*'Chart of Accounts'!$E$68 -> 11.5709 | O88: =I88+J88+L88 -> 116.4659
B89: P-000084 | C89: 45663 | D89: CG-016 | E89: Hourly | F89: 4.29 | G89: 0 | H89: 16.19 | I89: =F89*H89 -> 69.4551 | J89: =G89*H89*1.5 -> 0 | K89: 14.91 | L89: =K89*'Chart of Accounts'!$E$68 -> 9.9897 | O89: =I89+J89+L89 -> 79.4448
B90: P-000085 | C90: 45663 | D90: CG-013 | E90: Hourly | F90: 7.17 | G90: 0 | H90: 16.71 | I90: =F90*H90 -> 119.8107 | J90: =G90*H90*1.5 -> 0 | K90: 23.77 | L90: =K90*'Chart of Accounts'!$E$68 -> 15.9259 | O90: =I90+J90+L90 -> 135.7366
B91: P-000086 | C91: 45663 | D91: CG-017 | E91: Hourly | F91: 4.21 | G91: 0 | H91: 16.43 | I91: =F91*H91 -> 69.1703 | J91: =G91*H91*1.5 -> 0 | K91: 12.62 | L91: =K91*'Chart of Accounts'!$E$68 -> 8.4554 | O91: =I91+J91+L91 -> 77.6257
B92: P-000087 | C92: 45663 | D92: CG-019 | E92: Hourly | F92: 8.16 | G92: 0 | H92: 14.93 | I92: =F92*H92 -> 121.8288 | J92: =G92*H92*1.5 -> 0 | K92: 28.98 | L92: =K92*'Chart of Accounts'!$E$68 -> 19.4166 | O92: =I92+J92+L92 -> 141.2454
B93: P-000088 | C93: 45663 | D93: CG-001 | E93: Hourly | F93: 8.87 | G93: 0 | H93: 14.56 | I93: =F93*H93 -> 129.1472 | J93: =G93*H93*1.5 -> 0 | K93: 28.45 | L93: =K93*'Chart of Accounts'!$E$68 -> 19.0615 | O93: =I93+J93+L93 -> 148.2087
B94: P-000089 | C94: 45663 | D94: CG-023 | E94: Hourly | F94: 7.3 | G94: 0 | H94: 16.17 | I94: =F94*H94 -> 118.041 | J94: =G94*H94*1.5 -> 0 | K94: 23.73 | L94: =K94*'Chart of Accounts'!$E$68 -> 15.8991 | O94: =I94+J94+L94 -> 133.9401
B95: P-000090 | C95: 45663 | D95: CG-028 | E95: Hourly | F95: 6.9 | G95: 0 | H95: 17.99 | I95: =F95*H95 -> 124.131 | J95: =G95*H95*1.5 -> 0 | K95: 21.41 | L95: =K95*'Chart of Accounts'!$E$68 -> 14.3447 | O95: =I95+J95+L95 -> 138.4757
B96: P-000091 | C96: 45663 | D96: CG-018 | E96: Hourly | F96: 7.12 | G96: 0 | H96: 17.84 | I96: =F96*H96 -> 127.0208 | J96: =G96*H96*1.5 -> 0 | K96: 17.95 | L96: =K96*'Chart of Accounts'!$E$68 -> 12.0265 | O96: =I96+J96+L96 -> 139.0473
B97: P-000092 | C97: 45663 | D97: CG-038 | E97: Hourly | F97: 7.53 | G97: 0 | H97: 16.02 | I97: =F97*H97 -> 120.6306 | J97: =G97*H97*1.5 -> 0 | K97: 17.94 | L97: =K97*'Chart of Accounts'!$E$68 -> 12.0198 | O97: =I97+J97+L97 -> 132.6504
... B101: P-000096 | C101: 45664 | D101: CG-004 | E101: Hourly | F101: 4.23 | G101: 0 | H101: 16.05 | I101: =F101*H101 -> 67.8915 | J101: =G101*H101*1.5 -> 0 | K101: 12.84 | L101: =K101*'Chart of Accounts'!$E$68 -> 8.6028 | O101: =I101+J101+L101 -> 76.4943
B102: P-000097 | C102: 45664 | D102: CG-012 | E102: Per Visit | H102: 73.58 | M102: 2 | N102: =M102*H102 -> 147.16 | O102: =N102 -> 147.16
B103: P-000098 | C103: 45664 | D103: CG-002 | E103: Hourly | F103: 4.13 | G103: 0 | H103: 17.34 | I103: =F103*H103 -> 71.6142 | J103: =G103*H103*1.5 -> 0 | K103: 13.03 | L103: =K103*'Chart of Accounts'!$E$68 -> 8.7301 | O103: =I103+J103+L103 -> 80.3443
B104: P-000099 | C104: 45664 | D104: CG-024 | E104: Per Visit | H104: 89.53 | M104: 2 | N104: =M104*H104 -> 179.06 | O104: =N104 -> 179.06
B105: P-000100 | C105: 45664 | D105: CG-016 | E105: Hourly | F105: 3.9 | G105: 0 | H105: 16.19 | I105: =F105*H105 -> 63.141 | J105: =G105*H105*1.5 -> 0 | K105: 9.25 | L105: =K105*'Chart of Accounts'!$E$68 -> 6.1975 | O105: =I105+J105+L105 -> 69.3385
B106: P-000101 | C106: 45664 | D106: CG-040 | E106: Per Visit | H106: 75.18 | M106: 1 | N106: =M106*H106 -> 75.18 | O106: =N106 -> 75.18
B107: P-000102 | C107: 45664 | D107: CG-021 | E107: Per Visit | H107: 51.07 | M107: 1 | N107: =M107*H107 -> 51.07 | O107: =N107 -> 51.07
B108: P-000103 | C108: 45664 | D108: CG-017 | E108: Hourly | F108: 3.98 | G108: 0 | H108: 16.43 | I108: =F108*H108 -> 65.3914 | J108: =G108*H108*1.5 -> 0 | K108: 9.14 | L108: =K108*'Chart of Accounts'!$E$68 -> 6.1238 | O108: =I108+J108+L108 -> 71.5152
B109: P-000104 | C109: 45664 | D109: CG-013 | E109: Hourly | F109: 4.39 | G109: 0 | H109: 16.71 | I109: =F109*H109 -> 73.3569 | J109: =G109*H109*1.5 -> 0 | K109: 14.96 | L109: =K109*'Chart of Accounts'!$E$68 -> 10.0232 | O109: =I109+J109+L109 -> 83.3801
B110: P-000105 | C110: 45664 | D110: CG-030 | E110: Hourly | F110: 4.28 | G110: 0 | H110: 16.48 | I110: =F110*H110 -> 70.5344 | J110: =G110*H110*1.5 -> 0 | K110: 12.76 | L110: =K110*'Chart of Accounts'!$E$68 -> 8.5492 | O110: =I110+J110+L110 -> 79.0836
...

Sheet Missed Visits Log
B2: Missed Visits Log
B3: Uncovered or cancelled visits and the revenue lost - an operational KPI, not just a billing gap.
B5: Date | C5: Client ID | D5: Payer | E5: Reason | F5: Lost Units | G5: Lost Revenue
B6: 45658 | C6: CL-045 | D6: Medicaid Waiver | E6: Client cancelled same-day | F6: 4.56 | G6: 120.84
B7: 45672 | C7: CL-054 | D7: Medicaid Waiver | E7: Client cancelled same-day | F7: 4.01 | G7: 106.27
B8: 45681 | C8: CL-024 | D8: Private Pay | E8: Weather/transportation issue | F8: 4.3 | G8: 146.2
B9: 45687 | C9: CL-024 | D9: Private Pay | E9: Caregiver call-off, no replacement found | F9: 4.28 | G9: 145.52
B10: 45690 | C10: CL-055 | D10: Private Pay | E10: Client cancelled same-day | F10: 3.94 | G10: 133.96
B11: 45691 | C11: CL-016 | D11: Private Pay | E11: Client cancelled same-day | F11: 4.17 | G11: 141.78
B12: 45694 | C12: CL-004 | D12: Private Pay | E12: Client cancelled same-day | F12: 4.16 | G12: 141.44
B13: 45694 | C13: CL-015 | D13: Medicaid Waiver | E13: Client cancelled same-day | F13: 2.97 | G13: 78.7
B14: 45695 | C14: CL-014 | D14: Private Insurance | E14: Caregiver call-off, no replacement found | F14: 1.05 | G14: 141.75
B15: 45695 | C15: CL-040 | D15: Medicare (Skilled) | E15: Client cancelled same-day | F15: 0.93 | G15: 153.45
B16: 45697 | C16: CL-039 | D16: Private Pay | E16: Caregiver call-off, no replacement found | F16: 4.04 | G16: 137.36
B17: 45698 | C17: CL-004 | D17: Private Pay | E17: Weather/transportation issue | F17: 4.35 | G17: 147.9
... B212: 46020 | C212: CL-064 | D212: Medicaid Waiver | E212: Caregiver call-off, no replacement found | F212: 3 | G212: 79.5
B214: TOTAL LOST REVENUE (Year) | G214: =SUM(G6:G212) -> 25605.39
B215: Total Missed Visit Events | C215: =COUNTA(B6:B212) -> 207

Sheet Payroll Summary
B2: Payroll Summary - Monthly Rollup
B3: Aggregated from Daily Payroll Register via date-range SUMIFS. Employer burden applied to gross wages.
C5: Jan-2025 | D5: Feb-2025 | E5: Mar-2025 | F5: Apr-2025 | G5: May-2025 | H5: Jun-2025 | I5: Jul-2025 | J5: Aug-2025 | K5: Sep-2025 | L5: Oct-2025 | M5: Nov-2025 | N5: Dec-2025 | O5: FY Total
B6: Regular Wages (Hourly) | C6: =SUMIFS('Daily Payroll Register'!$I$6:$I$5978,'Daily Payroll Register'!$C$6:$C$5978,">="&DATE(2025,1,1),'Daily Payroll Register'!$C$6:$C$5978,"<"&DATE(2025,2,1)) -> 32619.694 | D6: =SUMIFS('Daily Payroll Register'!$I$6:$I$5978,'Daily Payroll Register'!$C$6:$C$5978,">="&DATE(2025,2,1),'Daily Payroll Register'!$C$6:$C$5978,"<"&DATE(2025,3,1)) -> 28107.475 | E6: =SUMIFS('Daily Payroll Register'!$I$6:$I$5978,'Daily Payroll Register'!$C$6:$C$5978,">="&DATE(2025,3,1),'Daily Payroll Register'!$C$6:$C$5978,"<"&DATE(2025,4,1)) -> 30891.1 | F6: =SUMIFS('Daily Payroll Register'!$I$6:$I$5978,'Daily Payroll Register'!$C$6:$C$5978,">="&DATE(2025,4,1),'Daily Payroll Register'!$C$6:$C$5978,"<"&DATE(2025,5,1)) -> 31877.566 | G6: =SUMIFS('Daily Payroll Register'!$I$6:$I$5978,'Daily Payroll Register'!$C$6:$C$5978,">="&DATE(2025,5,1),'Daily Payroll Register'!$C$6:$C$5978,"<"&DATE(2025,6,1)) -> 33491.019 | H6: =SUMIFS('Daily Payroll Register'!$I$6:$I$5978,'Daily Payroll Register'!$C$6:$C$5978,">="&DATE(2025,6,1),'Daily Payroll Register'!$C$6:$C$5978,"<"&DATE(2025,7,1)) -> 33038.073 | I6: =SUMIFS('Daily Payroll Register'!$I$6:$I$5978,'Daily Payroll Register'!$C$6:$C$5978,">="&DATE(2025,7,1),'Daily Payroll Register'!$C$6:$C$5978,"<"&DATE(2025,8,1)) -> 34800.117 | J6: =SUMIFS('Daily Payroll Register'!$I$6:$I$5978,'Daily Payroll Register'!$C$6:$C$5978,">="&DATE(2025,8,1),'Daily Payroll Register'!$C$6:$C$5978,"<"&DATE(2025,9,1)) -> 36518.632 | K6: =SUMIFS('Daily Payroll Register'!$I$6:$I$5978,'Daily Payroll Register'!$C$6:$C$5978,">="&DATE(2025,9,1),'Daily Payroll Register'!$C$6:$C$5978,"<"&DATE(2025,10,1)) -> 36743.121 | L6: =SUMIFS('Daily Payroll Register'!$I$6:$I$5978,'Daily Payroll Register'!$C$6:$C$5978,">="&DATE(2025,10,1),'Daily Payroll Register'!$C$6:$C$5978,"<"&DATE(2025,11,1)) -> 40819.497 | M6: =SUMIFS('Daily Payroll Register'!$I$6:$I$5978,'Daily Payroll Register'!$C$6:$C$5978,">="&DATE(2025,11,1),'Daily Payroll Register'!$C$6:$C$5978,"<"&DATE(2025,12,1)) -> 37196.333 | N6: =SUMIFS('Daily Payroll Register'!$I$6:$I$5978,'Daily Payroll Register'!$C$6:$C$5978,">="&DATE(2025,12,1),'Daily Payroll Register'!$C$6:$C$5978,"<"&DATE(2026,1,1)) -> 40241.366 | O6: =SUM(C6:N6) -> 416343.99
B7: Overtime Wages (Hourly) | C7: =SUMIFS('Daily Payroll Register'!$J$6:$J$5978,'Daily Payroll Register'!$C$6:$C$5978,">="&DATE(2025,1,1),'Daily Payroll Register'!$C$6:$C$5978,"<"&DATE(2025,2,1)) -> 0 | D7: =SUMIFS('Daily Payroll Register'!$J$6:$J$5978,'Daily Payroll Register'!$C$6:$C$5978,">="&DATE(2025,2,1),'Daily Payroll Register'!$C$6:$C$5978,"<"&DATE(2025,3,1)) -> 0 | E7: =SUMIFS('Daily Payroll Register'!$J$6:$J$5978,'Daily Payroll Register'!$C$6:$C$5978,">="&DATE(2025,3,1),'Daily Payroll Register'!$C$6:$C$5978,"<"&DATE(2025,4,1)) -> 0 | F7: =SUMIFS('Daily Payroll Register'!$J$6:$J$5978,'Daily Payroll Register'!$C$6:$C$5978,">="&DATE(2025,4,1),'Daily Payroll Register'!$C$6:$C$5978,"<"&DATE(2025,5,1)) -> 0 | G7: =SUMIFS('Daily Payroll Register'!$J$6:$J$5978,'Daily Payroll Register'!$C$6:$C$5978,">="&DATE(2025,5,1),'Daily Payroll Register'!$C$6:$C$5978,"<"&DATE(2025,6,1)) -> 36.240855 | H7: =SUMIFS('Daily Payroll Register'!$J$6:$J$5978,'Daily Payroll Register'!$C$6:$C$5978,">="&DATE(2025,6,1),'Daily Payroll Register'!$C$6:$C$5978,"<"&DATE(2025,7,1)) -> 140.17293 | I7: =SUMIFS('Daily Payroll Register'!$J$6:$J$5978,'Daily Payroll Register'!$C$6:$C$5978,">="&DATE(2025,7,1),'Daily Payroll Register'!$C$6:$C$5978,"<"&DATE(2025,8,1)) -> 505.92061 | J7: =SUMIFS('Daily Payroll Register'!$J$6:$J$5978,'Daily Payroll Register'!$C$6:$C$5978,">="&DATE(2025,8,1),'Daily Payroll Register'!$C$6:$C$5978,"<"&DATE(2025,9,1)) -> 1027.6718 | K7: =SUMIFS('Daily Payroll Register'!$J$6:$J$5978,'Daily Payroll Register'!$C$6:$C$5978,">="&DATE(2025,9,1),'Daily Payroll Register'!$C$6:$C$5978,"<"&DATE(2025,10,1)) -> 1573.3105 | L7: =SUMIFS('Daily Payroll Register'!$J$6:$J$5978,'Daily Payroll Register'!$C$6:$C$5978,">="&DATE(2025,10,1),'Daily Payroll Register'!$C$6:$C$5978,"<"&DATE(2025,11,1)) -> 734.2698 | M7: =SUMIFS('Daily Payroll Register'!$J$6:$J$5978,'Daily Payroll Register'!$C$6:$C$5978,">="&DATE(2025,11,1),'Daily Payroll Register'!$C$6:$C$5978,"<"&DATE(2025,12,1)) -> 879.38878 | N7: =SUMIFS('Daily Payroll Register'!$J$6:$J$5978,'Daily Payroll Register'!$C$6:$C$5978,">="&DATE(2025,12,1),'Daily Payroll Register'!$C$6:$C$5978,"<"&DATE(2026,1,1)) -> 1062.9302 | O7: =SUM(C7:N7) -> 5959.9054
B8: Mileage Reimbursement | C8: =SUMIFS('Daily Payroll Register'!$L$6:$L$5978,'Daily Payroll Register'!$C$6:$C$5978,">="&DATE(2025,1,1),'Daily Payroll Register'!$C$6:$C$5978,"<"&DATE(2025,2,1)) -> 3883.9833 | D8: =SUMIFS('Daily Payroll Register'!$L$6:$L$5978,'Daily Payroll Register'!$C$6:$C$5978,">="&DATE(2025,2,1),'Daily Payroll Register'!$C$6:$C$5978,"<"&DATE(2025,3,1)) -> 3341.089 | E8: =SUMIFS('Daily Payroll Register'!$L$6:$L$5978,'Daily Payroll Register'!$C$6:$C$5978,">="&DATE(2025,3,1),'Daily Payroll Register'!$C$6:$C$5978,"<"&DATE(2025,4,1)) -> 3648.6726 | F8: =SUMIFS('Daily Payroll Register'!$L$6:$L$5978,'Daily Payroll Register'!$C$6:$C$5978,">="&DATE(2025,4,1),'Daily Payroll Register'!$C$6:$C$5978,"<"&DATE(2025,5,1)) -> 3732.3958 | G8: =SUMIFS('Daily Payroll Register'!$L$6:$L$5978,'Daily Payroll Register'!$C$6:$C$5978,">="&DATE(2025,5,1),'Daily Payroll Register'!$C$6:$C$5978,"<"&DATE(2025,6,1)) -> 3998.3724 | H8: =SUMIFS('Daily Payroll Register'!$L$6:$L$5978,'Daily Payroll Register'!$C$6:$C$5978,">="&DATE(2025,6,1),'Daily Payroll Register'!$C$6:$C$5978,"<"&DATE(2025,7,1)) -> 3872.2717 | I8: =SUMIFS('Daily Payroll Register'!$L$6:$L$5978,'Daily Payroll Register'!$C$6:$C$5978,">="&DATE(2025,7,1),'Daily Payroll Register'!$C$6:$C$5978,"<"&DATE(2025,8,1)) -> 4171.0515 | J8: =SUMIFS('Daily Payroll Register'!$L$6:$L$5978,'Daily Payroll Register'!$C$6:$C$5978,">="&DATE(2025,8,1),'Daily Payroll Register'!$C$6:$C$5978,"<"&DATE(2025,9,1)) -> 4414.7104 | K8: =SUMIFS('Daily Payroll Register'!$L$6:$L$5978,'Daily Payroll Register'!$C$6:$C$5978,">="&DATE(2025,9,1),'Daily Payroll Register'!$C$6:$C$5978,"<"&DATE(2025,10,1)) -> 4562.365 | L8: =SUMIFS('Daily Payroll Register'!$L$6:$L$5978,'Daily Payroll Register'!$C$6:$C$5978,">="&DATE(2025,10,1),'Daily Payroll Register'!$C$6:$C$5978,"<"&DATE(2025,11,1)) -> 4933.4646 | M8: =SUMIFS('Daily Payroll Register'!$L$6:$L$5978,'Daily Payroll Register'!$C$6:$C$5978,">="&DATE(2025,11,1),'Daily Payroll Register'!$C$6:$C$5978,"<"&DATE(2025,12,1)) -> 4502.1722 | N8: =SUMIFS('Daily Payroll Register'!$L$6:$L$5978,'Daily Payroll Register'!$C$6:$C$5978,">="&DATE(2025,12,1),'Daily Payroll Register'!$C$6:$C$5978,"<"&DATE(2026,1,1)) -> 4834.4855 | O8: =SUM(C8:N8) -> 49895.034
B9: Per-Visit Pay (Skilled) | C9: =SUMIFS('Daily Payroll Register'!$N$6:$N$5978,'Daily Payroll Register'!$C$6:$C$5978,">="&DATE(2025,1,1),'Daily Payroll Register'!$C$6:$C$5978,"<"&DATE(2025,2,1)) -> 7029.21 | D9: =SUMIFS('Daily Payroll Register'!$N$6:$N$5978,'Daily Payroll Register'!$C$6:$C$5978,">="&DATE(2025,2,1),'Daily Payroll Register'!$C$6:$C$5978,"<"&DATE(2025,3,1)) -> 6264.43 | E9: =SUMIFS('Daily Payroll Register'!$N$6:$N$5978,'Daily Payroll Register'!$C$6:$C$5978,">="&DATE(2025,3,1),'Daily Payroll Register'!$C$6:$C$5978,"<"&DATE(2025,4,1)) -> 6667.57 | F9: =SUMIFS('Daily Payroll Register'!$N$6:$N$5978,'Daily Payroll Register'!$C$6:$C$5978,">="&DATE(2025,4,1),'Daily Payroll Register'!$C$6:$C$5978,"<"&DATE(2025,5,1)) -> 7998.63 | G9: =SUMIFS('Daily Payroll Register'!$N$6:$N$5978,'Daily Payroll Register'!$C$6:$C$5978,">="&DATE(2025,5,1),'Daily Payroll Register'!$C$6:$C$5978,"<"&DATE(2025,6,1)) -> 7517.88 | H9: =SUMIFS('Daily Payroll Register'!$N$6:$N$5978,'Daily Payroll Register'!$C$6:$C$5978,">="&DATE(2025,6,1),'Daily Payroll Register'!$C$6:$C$5978,"<"&DATE(2025,7,1)) -> 6958.45 | I9: =SUMIFS('Daily Payroll Register'!$N$6:$N$5978,'Daily Payroll Register'!$C$6:$C$5978,">="&DATE(2025,7,1),'Daily Payroll Register'!$C$6:$C$5978,"<"&DATE(2025,8,1)) -> 7887.95 | J9: =SUMIFS('Daily Payroll Register'!$N$6:$N$5978,'Daily Payroll Register'!$C$6:$C$5978,">="&DATE(2025,8,1),'Daily Payroll Register'!$C$6:$C$5978,"<"&DATE(2025,9,1)) -> 9050.45 | K9: =SUMIFS('Daily Payroll Register'!$N$6:$N$5978,'Daily Payroll Register'!$C$6:$C$5978,">="&DATE(2025,9,1),'Daily Payroll Register'!$C$6:$C$5978,"<"&DATE(2025,10,1)) -> 8731.54 | L9: =SUMIFS('Daily Payroll Register'!$N$6:$N$5978,'Daily Payroll Register'!$C$6:$C$5978,">="&DATE(2025,10,1),'Daily Payroll Register'!$C$6:$C$5978,"<"&DATE(2025,11,1)) -> 9218.36 | M9: =SUMIFS('Daily Payroll Register'!$N$6:$N$5978,'Daily Payroll Register'!$C$6:$C$5978,">="&DATE(2025,11,1),'Daily Payroll Register'!$C$6:$C$5978,"<"&DATE(2025,12,1)) -> 7880.77 | N9: =SUMIFS('Daily Payroll Register'!$N$6:$N$5978,'Daily Payroll Register'!$C$6:$C$5978,">="&DATE(2025,12,1),'Daily Payroll Register'!$C$6:$C$5978,"<"&DATE(2026,1,1)) -> 9517.01 | O9: =SUM(C9:N9) -> 94722.25
B10: Gross Payroll (Subtotal) | C10: =SUM(C6:C9) -> 43532.887 | D10: =SUM(D6:D9) -> 37712.994 | E10: =SUM(E6:E9) -> 41207.343 | F10: =SUM(F6:F9) -> 43608.592 | G10: =SUM(G6:G9) -> 45043.512 | H10: =SUM(H6:H9) -> 44008.968 | I10: =SUM(I6:I9) -> 47365.04 | J10: =SUM(J6:J9) -> 51011.464 | ... N10: =SUM(N6:N9) -> 55655.791 | O10: =SUM(C10:N10) -> 566921.18
B11: Payroll Tax & Burden (Employer) | C11: =C10*'Chart of Accounts'!$E$67 -> 6312.2686 | D11: =D10*'Chart of Accounts'!$E$67 -> 5468.3841 | E11: =E10*'Chart of Accounts'!$E$67 -> 5975.0647 | F11: =F10*'Chart of Accounts'!$E$67 -> 6323.2458 | G11: =G10*'Chart of Accounts'!$E$67 -> 6531.3093 | H11: =H10*'Chart of Accounts'!$E$67 -> 6381.3004 | I11: =I10*'Chart of Accounts'!$E$67 -> 6867.9307 | J11: =J10*'Chart of Accounts'!$E$67 -> 7396.6622 | ... N11: =N10*'Chart of Accounts'!$E$67 -> 8070.0898 | O11: =SUM(C11:N11) -> 82203.571
B12: TOTAL FULLY-LOADED PAYROLL | C12: =C10+C11 -> 49845.156 | D12: =D10+D11 -> 43181.378 | E12: =E10+E11 -> 47182.407 | F12: =F10+F11 -> 49931.838 | G12: =G10+G11 -> 51574.821 | H12: =H10+H11 -> 50390.268 | I12: =I10+I11 -> 54232.97 | J12: =J10+J11 -> 58408.126 | ... N12: =N10+N11 -> 63725.881 | O12: =SUM(C12:N12) -> 649124.75

Sheet Revenue by Payer
B2: Revenue Summary by Payer - Monthly
B3: Net billed revenue by payer, rolled up from the Daily Visit Register via date-range SUMIFS.
C5: Jan-2025 | D5: Feb-2025 | E5: Mar-2025 | F5: Apr-2025 | G5: May-2025 | H5: Jun-2025 | I5: Jul-2025 | J5: Aug-2025 | K5: Sep-2025 | L5: Oct-2025 | M5: Nov-2025 | N5: Dec-2025 | O5: FY Total
B6: Medicaid Waiver | C6: =SUMIFS('Daily Visit Register'!$L$6:$L$8129,'Daily Visit Register'!$C$6:$C$8129,">="&DATE(2025,1,1),'Daily Visit Register'!$C$6:$C$8129,"<"&DATE(2025,2,1),'Daily Visit Register'!$E$6:$E$8129,"Medicaid Waiver") -> 25017.06 | D6: =SUMIFS('Daily Visit Register'!$L$6:$L$8129,'Daily Visit Register'!$C$6:$C$8129,">="&DATE(2025,2,1),'Daily Visit Register'!$C$6:$C$8129,"<"&DATE(2025,3,1),'Daily Visit Register'!$E$6:$E$8129,"Medicaid Waiver") -> 21519.828 | E6: =SUMIFS('Daily Visit Register'!$L$6:$L$8129,'Daily Visit Register'!$C$6:$C$8129,">="&DATE(2025,3,1),'Daily Visit Register'!$C$6:$C$8129,"<"&DATE(2025,4,1),'Daily Visit Register'!$E$6:$E$8129,"Medicaid Waiver") -> 23212.198 | F6: =SUMIFS('Daily Visit Register'!$L$6:$L$8129,'Daily Visit Register'!$C$6:$C$8129,">="&DATE(2025,4,1),'Daily Visit Register'!$C$6:$C$8129,"<"&DATE(2025,5,1),'Daily Visit Register'!$E$6:$E$8129,"Medicaid Waiver") -> 24571.038 | G6: =SUMIFS('Daily Visit Register'!$L$6:$L$8129,'Daily Visit Register'!$C$6:$C$8129,">="&DATE(2025,5,1),'Daily Visit Register'!$C$6:$C$8129,"<"&DATE(2025,6,1),'Daily Visit Register'!$E$6:$E$8129,"Medicaid Waiver") -> 26282.541 | H6: =SUMIFS('Daily Visit Register'!$L$6:$L$8129,'Daily Visit Register'!$C$6:$C$8129,">="&DATE(2025,6,1),'Daily Visit Register'!$C$6:$C$8129,"<"&DATE(2025,7,1),'Daily Visit Register'!$E$6:$E$8129,"Medicaid Waiver") -> 26254.716 | I6: =SUMIFS('Daily Visit Register'!$L$6:$L$8129,'Daily Visit Register'!$C$6:$C$8129,">="&DATE(2025,7,1),'Daily Visit Register'!$C$6:$C$8129,"<"&DATE(2025,8,1),'Daily Visit Register'!$E$6:$E$8129,"Medicaid Waiver") -> 28362.659 | J6: =SUMIFS('Daily Visit Register'!$L$6:$L$8129,'Daily Visit Register'!$C$6:$C$8129,">="&DATE(2025,8,1),'Daily Visit Register'!$C$6:$C$8129,"<"&DATE(2025,9,1),'Daily Visit Register'!$E$6:$E$8129,"Medicaid Waiver") -> 31689.76 | K6: =SUMIFS('Daily Visit Register'!$L$6:$L$8129,'Daily Visit Register'!$C$6:$C$8129,">="&DATE(2025,9,1),'Daily Visit Register'!$C$6:$C$8129,"<"&DATE(2025,10,1),'Daily Visit Register'!$E$6:$E$8129,"Medicaid Waiver") -> 32711.547 | L6: =SUMIFS('Daily Visit Register'!$L$6:$L$8129,'Daily Visit Register'!$C$6:$C$8129,">="&DATE(2025,10,1),'Daily Visit Register'!$C$6:$C$8129,"<"&DATE(2025,11,1),'Daily Visit Register'!$E$6:$E$8129,"Medicaid Waiver") -> 37470.974 | M6: =SUMIFS('Daily Visit Register'!$L$6:$L$8129,'Daily Visit Register'!$C$6:$C$8129,">="&DATE(2025,11,1),'Daily Visit Register'!$C$6:$C$8129,"<"&DATE(2025,12,1),'Daily Visit Register'!$E$6:$E$8129,"Medicaid Waiver") -> 34034.374 | N6: =SUMIFS('Daily Visit Register'!$L$6:$L$8129,'Daily Visit Register'!$C$6:$C$8129,">="&DATE(2025,12,1),'Daily Visit Register'!$C$6:$C$8129,"<"&DATE(2026,1,1),'Daily Visit Register'!$E$6:$E$8129,"Medicaid Waiver") -> 36215.589 | O6: =SUM(C6:N6) -> 347342.28
B7: Private Pay | C7: =SUMIFS('Daily Visit Register'!$L$6:$L$8129,'Daily Visit Register'!$C$6:$C$8129,">="&DATE(2025,1,1),'Daily Visit Register'!$C$6:$C$8129,"<"&DATE(2025,2,1),'Daily Visit Register'!$E$6:$E$8129,"Private Pay") -> 35328.38 | D7: =SUMIFS('Daily Visit Register'!$L$6:$L$8129,'Daily Visit Register'!$C$6:$C$8129,">="&DATE(2025,2,1),'Daily Visit Register'!$C$6:$C$8129,"<"&DATE(2025,3,1),'Daily Visit Register'!$E$6:$E$8129,"Private Pay") -> 30413.68 | E7: =SUMIFS('Daily Visit Register'!$L$6:$L$8129,'Daily Visit Register'!$C$6:$C$8129,">="&DATE(2025,3,1),'Daily Visit Register'!$C$6:$C$8129,"<"&DATE(2025,4,1),'Daily Visit Register'!$E$6:$E$8129,"Private Pay") -> 34039.78 | F7: =SUMIFS('Daily Visit Register'!$L$6:$L$8129,'Daily Visit Register'!$C$6:$C$8129,">="&DATE(2025,4,1),'Daily Visit Register'!$C$6:$C$8129,"<"&DATE(2025,5,1),'Daily Visit Register'!$E$6:$E$8129,"Private Pay") -> 34412.42 | G7: =SUMIFS('Daily Visit Register'!$L$6:$L$8129,'Daily Visit Register'!$C$6:$C$8129,">="&DATE(2025,5,1),'Daily Visit Register'!$C$6:$C$8129,"<"&DATE(2025,6,1),'Daily Visit Register'!$E$6:$E$8129,"Private Pay") -> 35663.96 | H7: =SUMIFS('Daily Visit Register'!$L$6:$L$8129,'Daily Visit Register'!$C$6:$C$8129,">="&DATE(2025,6,1),'Daily Visit Register'!$C$6:$C$8129,"<"&DATE(2025,7,1),'Daily Visit Register'!$E$6:$E$8129,"Private Pay") -> 34950.64 | I7: =SUMIFS('Daily Visit Register'!$L$6:$L$8129,'Daily Visit Register'!$C$6:$C$8129,">="&DATE(2025,7,1),'Daily Visit Register'!$C$6:$C$8129,"<"&DATE(2025,8,1),'Daily Visit Register'!$E$6:$E$8129,"Private Pay") -> 36579.92 | J7: =SUMIFS('Daily Visit Register'!$L$6:$L$8129,'Daily Visit Register'!$C$6:$C$8129,">="&DATE(2025,8,1),'Daily Visit Register'!$C$6:$C$8129,"<"&DATE(2025,9,1),'Daily Visit Register'!$E$6:$E$8129,"Private Pay") -> 36759.1 | K7: =SUMIFS('Daily Visit Register'!$L$6:$L$8129,'Daily Visit Register'!$C$6:$C$8129,">="&DATE(2025,9,1),'Daily Visit Register'!$C$6:$C$8129,"<"&DATE(2025,10,1),'Daily Visit Register'!$E$6:$E$8129,"Private Pay") -> 36789.36 | L7: =SUMIFS('Daily Visit Register'!$L$6:$L$8129,'Daily Visit Register'!$C$6:$C$8129,">="&DATE(2025,10,1),'Daily Visit Register'!$C$6:$C$8129,"<"&DATE(2025,11,1),'Daily Visit Register'!$E$6:$E$8129,"Private Pay") -> 38184.72 | M7: =SUMIFS('Daily Visit Register'!$L$6:$L$8129,'Daily Visit Register'!$C$6:$C$8129,">="&DATE(2025,11,1),'Daily Visit Register'!$C$6:$C$8129,"<"&DATE(2025,12,1),'Daily Visit Register'!$E$6:$E$8129,"Private Pay") -> 34995.86 | N7: =SUMIFS('Daily Visit Register'!$L$6:$L$8129,'Daily Visit Register'!$C$6:$C$8129,">="&DATE(2025,12,1),'Daily Visit Register'!$C$6:$C$8129,"<"&DATE(2026,1,1),'Daily Visit Register'!$E$6:$E$8129,"Private Pay") -> 38631.14 | O7: =SUM(C7:N7) -> 426748.96
B8: Medicare (Skilled) | C8: =SUMIFS('Daily Visit Register'!$L$6:$L$8129,'Daily Visit Register'!$C$6:$C$8129,">="&DATE(2025,1,1),'Daily Visit Register'!$C$6:$C$8129,"<"&DATE(2025,2,1),'Daily Visit Register'!$E$6:$E$8129,"Medicare (Skilled)") -> 11347.875 | D8: =SUMIFS('Daily Visit Register'!$L$6:$L$8129,'Daily Visit Register'!$C$6:$C$8129,">="&DATE(2025,2,1),'Daily Visit Register'!$C$6:$C$8129,"<"&DATE(2025,3,1),'Daily Visit Register'!$E$6:$E$8129,"Medicare (Skilled)") -> 9729.72 | E8: =SUMIFS('Daily Visit Register'!$L$6:$L$8129,'Daily Visit Register'!$C$6:$C$8129,">="&DATE(2025,3,1),'Daily Visit Register'!$C$6:$C$8129,"<"&DATE(2025,4,1),'Daily Visit Register'!$E$6:$E$8129,"Medicare (Skilled)") -> 10317.615 | F8: =SUMIFS('Daily Visit Register'!$L$6:$L$8129,'Daily Visit Register'!$C$6:$C$8129,">="&DATE(2025,4,1),'Daily Visit Register'!$C$6:$C$8129,"<"&DATE(2025,5,1),'Daily Visit Register'!$E$6:$E$8129,"Medicare (Skilled)") -> 13051.665 | G8: =SUMIFS('Daily Visit Register'!$L$6:$L$8129,'Daily Visit Register'!$C$6:$C$8129,">="&DATE(2025,5,1),'Daily Visit Register'!$C$6:$C$8129,"<"&DATE(2025,6,1),'Daily Visit Register'!$E$6:$E$8129,"Medicare (Skilled)") -> 12436.71 | H8: =SUMIFS('Daily Visit Register'!$L$6:$L$8129,'Daily Visit Register'!$C$6:$C$8129,">="&DATE(2025,6,1),'Daily Visit Register'!$C$6:$C$8129,"<"&DATE(2025,7,1),'Daily Visit Register'!$E$6:$E$8129,"Medicare (Skilled)") -> 11561.22 | I8: =SUMIFS('Daily Visit Register'!$L$6:$L$8129,'Daily Visit Register'!$C$6:$C$8129,">="&DATE(2025,7,1),'Daily Visit Register'!$C$6:$C$8129,"<"&DATE(2025,8,1),'Daily Visit Register'!$E$6:$E$8129,"Medicare (Skilled)") -> 12212.64 | J8: =SUMIFS('Daily Visit Register'!$L$6:$L$8129,'Daily Visit Register'!$C$6:$C$8129,">="&DATE(2025,8,1),'Daily Visit Register'!$C$6:$C$8129,"<"&DATE(2025,9,1),'Daily Visit Register'!$E$6:$E$8129,"Medicare (Skilled)") -> 13058.1 | K8: =SUMIFS('Daily Visit Register'!$L$6:$L$8129,'Daily Visit Register'!$C$6:$C$8129,">="&DATE(2025,9,1),'Daily Visit Register'!$C$6:$C$8129,"<"&DATE(2025,10,1),'Daily Visit Register'!$E$6:$E$8129,"Medicare (Skilled)") -> 12439.35 | L8: =SUMIFS('Daily Visit Register'!$L$6:$L$8129,'Daily Visit Register'!$C$6:$C$8129,">="&DATE(2025,10,1),'Daily Visit Register'!$C$6:$C$8129,"<"&DATE(2025,11,1),'Daily Visit Register'!$E$6:$E$8129,"Medicare (Skilled)") -> 13411.53 | M8: =SUMIFS('Daily Visit Register'!$L$6:$L$8129,'Daily Visit Register'!$C$6:$C$8129,">="&DATE(2025,11,1),'Daily Visit Register'!$C$6:$C$8129,"<"&DATE(2025,12,1),'Daily Visit Register'!$E$6:$E$8129,"Medicare (Skilled)") -> 11347.215 | N8: =SUMIFS('Daily Visit Register'!$L$6:$L$8129,'Daily Visit Register'!$C$6:$C$8129,">="&DATE(2025,12,1),'Daily Visit Register'!$C$6:$C$8129,"<"&DATE(2026,1,1),'Daily Visit Register'!$E$6:$E$8129,"Medicare (Skilled)") -> 14140.83 | O8: =SUM(C8:N8) -> 145054.47
B9: Private Insurance | C9: =SUMIFS('Daily Visit Register'!$L$6:$L$8129,'Daily Visit Register'!$C$6:$C$8129,">="&DATE(2025,1,1),'Daily Visit Register'!$C$6:$C$8129,"<"&DATE(2025,2,1),'Daily Visit Register'!$E$6:$E$8129,"Private Insurance") -> 4425.3 | D9: =SUMIFS('Daily Visit Register'!$L$6:$L$8129,'Daily Visit Register'!$C$6:$C$8129,">="&DATE(2025,2,1),'Daily Visit Register'!$C$6:$C$8129,"<"&DATE(2025,3,1),'Daily Visit Register'!$E$6:$E$8129,"Private Insurance") -> 4236.435 | E9: =SUMIFS('Daily Visit Register'!$L$6:$L$8129,'Daily Visit Register'!$C$6:$C$8129,">="&DATE(2025,3,1),'Daily Visit Register'!$C$6:$C$8129,"<"&DATE(2025,4,1),'Daily Visit Register'!$E$6:$E$8129,"Private Insurance") -> 4891.455 | F9: =SUMIFS('Daily Visit Register'!$L$6:$L$8129,'Daily Visit Register'!$C$6:$C$8129,">="&DATE(2025,4,1),'Daily Visit Register'!$C$6:$C$8129,"<"&DATE(2025,5,1),'Daily Visit Register'!$E$6:$E$8129,"Private Insurance") -> 5301.99 | G9: =SUMIFS('Daily Visit Register'!$L$6:$L$8129,'Daily Visit Register'!$C$6:$C$8129,">="&DATE(2025,5,1),'Daily Visit Register'!$C$6:$C$8129,"<"&DATE(2025,6,1),'Daily Visit Register'!$E$6:$E$8129,"Private Insurance") -> 5038.74 | H9: =SUMIFS('Daily Visit Register'!$L$6:$L$8129,'Daily Visit Register'!$C$6:$C$8129,">="&DATE(2025,6,1),'Daily Visit Register'!$C$6:$C$8129,"<"&DATE(2025,7,1),'Daily Visit Register'!$E$6:$E$8129,"Private Insurance") -> 4664.925 | I9: =SUMIFS('Daily Visit Register'!$L$6:$L$8129,'Daily Visit Register'!$C$6:$C$8129,">="&DATE(2025,7,1),'Daily Visit Register'!$C$6:$C$8129,"<"&DATE(2025,8,1),'Daily Visit Register'!$E$6:$E$8129,"Private Insurance") -> 5655.15 | J9: =SUMIFS('Daily Visit Register'!$L$6:$L$8129,'Daily Visit Register'!$C$6:$C$8129,">="&DATE(2025,8,1),'Daily Visit Register'!$C$6:$C$8129,"<"&DATE(2025,9,1),'Daily Visit Register'!$E$6:$E$8129,"Private Insurance") -> 7852.005 | K9: =SUMIFS('Daily Visit Register'!$L$6:$L$8129,'Daily Visit Register'!$C$6:$C$8129,">="&DATE(2025,9,1),'Daily Visit Register'!$C$6:$C$8129,"<"&DATE(2025,10,1),'Daily Visit Register'!$E$6:$E$8129,"Private Insurance") -> 8065.98 | L9: =SUMIFS('Daily Visit Register'!$L$6:$L$8129,'Daily Visit Register'!$C$6:$C$8129,">="&DATE(2025,10,1),'Daily Visit Register'!$C$6:$C$8129,"<"&DATE(2025,11,1),'Daily Visit Register'!$E$6:$E$8129,"Private Insurance") -> 8589.105 | M9: =SUMIFS('Daily Visit Register'!$L$6:$L$8129,'Daily Visit Register'!$C$6:$C$8129,">="&DATE(2025,11,1),'Daily Visit Register'!$C$6:$C$8129,"<"&DATE(2025,12,1),'Daily Visit Register'!$E$6:$E$8129,"Private Insurance") -> 7525.71 | N9: =SUMIFS('Daily Visit Register'!$L$6:$L$8129,'Daily Visit Register'!$C$6:$C$8129,">="&DATE(2025,12,1),'Daily Visit Register'!$C$6:$C$8129,"<"&DATE(2026,1,1),'Daily Visit Register'!$E$6:$E$8129,"Private Insurance") -> 8691.165 | O9: =SUM(C9:N9) -> 74937.96
B10: TOTAL NET REVENUE | C10: =SUM(C6:C9) -> 76118.615 | D10: =SUM(D6:D9) -> 65899.663 | E10: =SUM(E6:E9) -> 72461.048 | F10: =SUM(F6:F9) -> 77337.114 | G10: =SUM(G6:G9) -> 79421.951 | H10: =SUM(H6:H9) -> 77431.501 | I10: =SUM(I6:I9) -> 82810.368 | J10: =SUM(J6:J9) -> 89358.965 | ... N10: =SUM(N6:N9) -> 97678.724 | O10: =SUM(C10:N10) -> 994083.67

Sheet AR Aging
B2: Accounts Receivable - Month-End Balance by Payer
B3: Reflects each payer's real collection speed: Private Pay collects fast, Medicaid/Medicare/Insurance lag.
B5: Cash Collected ($) | C5: Jan-2025 | D5: Feb-2025 | E5: Mar-2025 | F5: Apr-2025 | G5: May-2025 | H5: Jun-2025 | I5: Jul-2025 | J5: Aug-2025 | K5: Sep-2025 | L5: Oct-2025 | M5: Nov-2025 | N5: Dec-2025
B6: Medicaid Waiver | C6: 456.49 | D6: 5162.89 | E6: 14130.74 | F6: 23202.85 | G6: 23635 | H6: 26079 | I6: 25056.23 | J6: 28374.76 | K6: 25468.07 | L6: 32369.92 | M6: 32690.27 | N6: 35783.44 | O6: =SUM(C6:N6) -> 272409.66
B7: Private Pay | C7: 20497.92 | D7: 31788.98 | E7: 34877.2 | F7: 35015.92 | G7: 34825.52 | H7: 35025.44 | I7: 35753.72 | J7: 37050.14 | K7: 35363.4 | L7: 37923.26 | M7: 36583.32 | N7: 36926.38 | O7: =SUM(C7:N7) -> 411631.2
B8: Medicare (Skilled) | C8: 833.25 | D8: 4184.06 | E8: 9574.78 | F8: 11008.43 | G8: 12466.39 | H8: 11919.56 | I8: 12037.4 | J8: 13960.46 | K8: 10867.38 | L8: 12798.54 | M8: 10984.36 | N8: 15389.87 | O8: =SUM(C8:N8) -> 126024.48
B9: Private Insurance | C9: 0 | D9: 1406.7 | E9: 4145.98 | F9: 4572.31 | G9: 5066.81 | H9: 4628.87 | I9: 4487.4 | J9: 4983.53 | K9: 7177.67 | L9: 7718.08 | M9: 8317.61 | N9: 7977 | O9: =SUM(C9:N9) -> 60481.96
B10: Total Cash Collected | C10: =SUM(C6:C9) -> 21787.66 | D10: =SUM(D6:D9) -> 42542.63 | E10: =SUM(E6:E9) -> 62728.7 | F10: =SUM(F6:F9) -> 73799.51 | G10: =SUM(G6:G9) -> 75993.72 | H10: =SUM(H6:H9) -> 77652.87 | I10: =SUM(I6:I9) -> 77334.75 | J10: =SUM(J6:J9) -> 84368.89 | ... N10: =SUM(N6:N9) -> 96076.69 | O10: =SUM(C10:N10) -> 870547.3
B12: AR Balance, Month-End ($) | C12: Jan-2025 | D12: Feb-2025 | E12: Mar-2025 | F12: Apr-2025 | G12: May-2025 | H12: Jun-2025 | I12: Jul-2025 | J12: Aug-2025 | K12: Sep-2025 | L12: Oct-2025 | M12: Nov-2025 | N12: Dec-2025
B13: Medicaid Waiver | C13: ='Revenue by Payer'!C6-C6 -> 24560.57 | D13: =C13+'Revenue by Payer'!D6-D6 -> 40917.509 | E13: =D13+'Revenue by Payer'!E6-E6 -> 49998.967 | F13: =E13+'Revenue by Payer'!F6-F6 -> 51367.155 | G13: =F13+'Revenue by Payer'!G6-G6 -> 54014.696 | H13: =G13+'Revenue by Payer'!H6-H6 -> 54190.412 | I13: =H13+'Revenue by Payer'!I6-I6 -> 57496.84 | J13: =I13+'Revenue by Payer'!J6-J6 -> 60811.84 | K13: =J13+'Revenue by Payer'!K6-K6 -> 68055.318 | ... N13: =M13+'Revenue by Payer'!N6-N6 -> 74932.624
B14: Private Pay | C14: ='Revenue by Payer'!C7-C7 -> 14830.46 | D14: =C14+'Revenue by Payer'!D7-D7 -> 13455.16 | E14: =D14+'Revenue by Payer'!E7-E7 -> 12617.74 | F14: =E14+'Revenue by Payer'!F7-F7 -> 12014.24 | G14: =F14+'Revenue by Payer'!G7-G7 -> 12852.68 | H14: =G14+'Revenue by Payer'!H7-H7 -> 12777.88 | I14: =H14+'Revenue by Payer'!I7-I7 -> 13604.08 | J14: =I14+'Revenue by Payer'!J7-J7 -> 13313.04 | K14: =J14+'Revenue by Payer'!K7-K7 -> 14739 | ... N14: =M14+'Revenue by Payer'!N7-N7 -> 15117.76
B15: Medicare (Skilled) | C15: ='Revenue by Payer'!C8-C8 -> 10514.625 | D15: =C15+'Revenue by Payer'!D8-D8 -> 16060.285 | E15: =D15+'Revenue by Payer'!E8-E8 -> 16803.12 | F15: =E15+'Revenue by Payer'!F8-F8 -> 18846.355 | G15: =F15+'Revenue by Payer'!G8-G8 -> 18816.675 | H15: =G15+'Revenue by Payer'!H8-H8 -> 18458.335 | I15: =H15+'Revenue by Payer'!I8-I8 -> 18633.575 | J15: =I15+'Revenue by Payer'!J8-J8 -> 17731.215 | K15: =J15+'Revenue by Payer'!K8-K8 -> 19303.185 | ... N15: =M15+'Revenue by Payer'!N8-N8 -> 19029.99
B16: Private Insurance | C16: ='Revenue by Payer'!C9-C9 -> 4425.3 | D16: =C16+'Revenue by Payer'!D9-D9 -> 7255.035 | E16: =D16+'Revenue by Payer'!E9-E9 -> 8000.51 | F16: =E16+'Revenue by Payer'!F9-F9 -> 8730.19 | G16: =F16+'Revenue by Payer'!G9-G9 -> 8702.12 | H16: =G16+'Revenue by Payer'!H9-H9 -> 8738.175 | I16: =H16+'Revenue by Payer'!I9-I9 -> 9905.925 | J16: =I16+'Revenue by Payer'!J9-J9 -> 12774.4 | K16: =J16+'Revenue by Payer'!K9-K9 -> 13662.71 | ... N16: =M16+'Revenue by Payer'!N9-N9 -> 14456
B17: TOTAL AR OUTSTANDING | C17: =SUM(C13:C16) -> 54330.955 | D17: =SUM(D13:D16) -> 77687.989 | E17: =SUM(E13:E16) -> 87420.337 | F17: =SUM(F13:F16) -> 90957.94 | G17: =SUM(G13:G16) -> 94386.171 | H17: =SUM(H13:H16) -> 94164.802 | I17: =SUM(I13:I16) -> 99640.42 | J17: =SUM(J13:J16) -> 104630.5 | ... N17: =SUM(N13:N16) -> 123536.37
B19: Approx. Days Sales Outstanding (Year-End AR ÷ Avg Daily Revenue)
B20: Payer | C20: Year-End AR | D20: Annual Revenue | E20: Approx DSO
B21: Medicaid Waiver | C21: =N13 -> 74932.624 | D21: ='Revenue by Payer'!O6 -> 347342.28 | E21: =IFERROR(C21/(D21/365),0) -> 78.741947
B22: Private Pay | C22: =N14 -> 15117.76 | D22: ='Revenue by Payer'!O7 -> 426748.96 | E22: =IFERROR(C22/(D22/365),0) -> 12.930277
B23: Medicare (Skilled) | C23: =N15 -> 19029.99 | D23: ='Revenue by Payer'!O8 -> 145054.47 | E23: =IFERROR(C23/(D23/365),0) -> 47.88509
B24: Private Insurance | C24: =N16 -> 14456 | D24: ='Revenue by Payer'!O9 -> 74937.96 | E24: =IFERROR(C24/(D24/365),0) -> 70.410777

Sheet AR Detail Ledger
B2: AR Detail Ledger - Every Invoice, Full Year
B3: 8,124 invoices (one per visit). Shows exactly which claims remain open at year-end and how long they have been outstanding.
B5: Invoice ID | C5: Visit ID | D5: Client ID | E5: Payer | F5: Billed Date | G5: Amount | H5: Paid Date | I5: Status | J5: Days Outstanding (at 12/31 if open)
B6: INV-000001 | C6: V-000001 | D6: CL-001 | E6: Medicare (Skilled) | F6: 45658 | G6: 150.15 | H6: 45691 | I6: Paid | J6: =IF(I6="Open",DATE(2025,12,31)-F6,"-") -> -
B7: INV-000002 | C7: V-000002 | D7: CL-003 | E7: Medicare (Skilled) | F7: 45658 | G7: 163.35 | H7: 45696 | I7: Paid | J7: =IF(I7="Open",DATE(2025,12,31)-F7,"-") -> -
B8: INV-000003 | C8: V-000003 | D8: CL-004 | E8: Private Pay | F8: 45658 | G8: 149.26 | H8: 45670 | I8: Paid | J8: =IF(I8="Open",DATE(2025,12,31)-F8,"-") -> -
B9: INV-000004 | C9: V-000004 | D9: CL-005 | E9: Medicaid Waiver | F9: 45658 | G9: 133.3 | H9: 45710 | I9: Paid | J9: =IF(I9="Open",DATE(2025,12,31)-F9,"-") -> -
B10: INV-000005 | C10: V-000005 | D10: CL-012 | E10: Medicaid Waiver | F10: 45658 | G10: 106 | H10: 45700 | I10: Paid | J10: =IF(I10="Open",DATE(2025,12,31)-F10,"-") -> -
B11: INV-000006 | C11: V-000006 | D11: CL-014 | E11: Private Insurance | F11: 45658 | G11: 145.8 | H11: 45725 | I11: Paid | J11: =IF(I11="Open",DATE(2025,12,31)-F11,"-") -> -
B12: INV-000007 | C12: V-000007 | D12: CL-016 | E12: Private Pay | F12: 45658 | G12: 129.54 | H12: 45668 | I12: Paid | J12: =IF(I12="Open",DATE(2025,12,31)-F12,"-") -> -
B13: INV-000008 | C13: V-000008 | D13: CL-020 | E13: Medicaid Waiver | F13: 45658 | G13: 111.56 | H13: 45766 | I13: Paid | J13: =IF(I13="Open",DATE(2025,12,31)-F13,"-") -> -
B14: INV-000009 | C14: V-000009 | D14: CL-024 | E14: Private Pay | F14: 45658 | G14: 129.88 | H14: 45668 | I14: Paid | J14: =IF(I14="Open",DATE(2025,12,31)-F14,"-") -> -
B15: INV-000010 | C15: V-000010 | D15: CL-027 | E15: Medicaid Waiver | F15: 45658 | G15: 101.23 | H15: 45723 | I15: Paid | J15: =IF(I15="Open",DATE(2025,12,31)-F15,"-") -> -
B16: INV-000011 | C16: V-000011 | D16: CL-029 | E16: Medicaid Waiver | F16: 45658 | G16: 81.88 | H16: 45690 | I16: Paid | J16: =IF(I16="Open",DATE(2025,12,31)-F16,"-") -> -
B17: INV-000012 | C17: V-000012 | D17: CL-036 | E17: Medicaid Waiver | F17: 45658 | G17: 91.95 | H17: 45699 | I17: Paid | J17: =IF(I17="Open",DATE(2025,12,31)-F17,"-") -> -
... B5140: INV-005135 | C5140: V-005135 | D5140: CL-057 | E5140: Private Pay | F5140: 45903 | G5140: 143.48 | H5140: 45912 | I5140: Paid | J5140: =IF(I5140="Open",DATE(2025,12,31)-F5140,"-") -> -
B5141: INV-005136 | C5141: V-005136 | D5141: CL-059 | E5141: Medicaid Waiver | F5141: 45903 | G5141: 81.35 | H5141: - | I5141: Open | J5141: =IF(I5141="Open",DATE(2025,12,31)-F5141,"-") -> 119
B5142: INV-005137 | C5142: V-005137 | D5142: CL-060 | E5142: Private Pay | F5142: 45903 | G5142: 123.76 | H5142: 45906 | I5142: Paid | J5142: =IF(I5142="Open",DATE(2025,12,31)-F5142,"-") -> -
B5143: INV-005138 | C5143: V-005138 | D5143: CL-061 | E5143: Private Pay | F5143: 45903 | G5143: 126.82 | H5143: 45907 | I5143: Paid | J5143: =IF(I5143="Open",DATE(2025,12,31)-F5143,"-") -> -
B5144: INV-005139 | C5144: V-005139 | D5144: CL-064 | E5144: Medicaid Waiver | F5144: 45903 | G5144: 84.8 | H5144: 45962 | I5144: Paid | J5144: =IF(I5144="Open",DATE(2025,12,31)-F5144,"-") -> -
B5145: INV-005140 | C5145: V-005140 | D5145: CL-065 | E5145: Medicaid Waiver | F5145: 45903 | G5145: 121.9 | H5145: 45979 | I5145: Paid | J5145: =IF(I5145="Open",DATE(2025,12,31)-F5145,"-") -> -
B5146: INV-005141 | C5146: V-005141 | D5146: CL-004 | E5146: Private Pay | F5146: 45904 | G5146: 135.32 | H5146: 45910 | I5146: Paid | J5146: =IF(I5146="Open",DATE(2025,12,31)-F5146,"-") -> -
B5147: INV-005142 | C5147: V-005142 | D5147: CL-008 | E5147: Private Pay | F5147: 45904 | G5147: 99.62 | H5147: 45922 | I5147: Paid | J5147: =IF(I5147="Open",DATE(2025,12,31)-F5147,"-") -> -
B5148: INV-005143 | C5148: V-005143 | D5148: CL-015 | E5148: Medicaid Waiver | F5148: 45904 | G5148: 82.94 | H5148: 45987 | I5148: Paid | J5148: =IF(I5148="Open",DATE(2025,12,31)-F5148,"-") -> -
B5149: INV-005144 | C5149: V-005144 | D5149: CL-016 | E5149: Private Pay | F5149: 45904 | G5149: 148.92 | H5149: 45912 | I5149: Paid | J5149: =IF(I5149="Open",DATE(2025,12,31)-F5149,"-") -> -
B5150: INV-005145 | C5150: V-005145 | D5150: CL-018 | E5150: Private Pay | F5150: 45904 | G5150: 102.68 | H5150: 45917 | I5150: Paid | J5150: =IF(I5150="Open",DATE(2025,12,31)-F5150,"-") -> -
B5151: INV-005146 | C5151: V-005146 | D5151: CL-020 | E5151: Medicaid Waiver | F5151: 45904 | G5151: 95.4 | H5151: 45951 | I5151: Paid | J5151: =IF(I5151="Open",DATE(2025,12,31)-F5151,"-") -> -
B5152: INV-005147 | C5152: V-005147 | D5152: CL-022 | E5152: Medicaid Waiver | F5152: 45904 | G5152: 73.41 | H5152: 45988 | I5152: Paid | J5152: =IF(I5152="Open",DATE(2025,12,31)-F5152,"-") -> -
B5153: INV-005148 | C5153: V-005148 | D5153: CL-024 | E5153: Private Pay | F5153: 45904 | G5153: 136 | H5153: 45916 | I5153: Paid | J5153: =IF(I5153="Open",DATE(2025,12,31)-F5153,"-") -> -
... B5259: INV-005254 | C5259: V-005254 | D5259: CL-019 | E5259: Medicare (Skilled) | F5259: 45909 | G5259: 150.15 | H5259: 45937 | I5259: Paid | J5259: =IF(I5259="Open",DATE(2025,12,31)-F5259,"-") -> -
B5260: INV-005255 | C5260: V-005255 | D5260: CL-020 | E5260: Medicaid Waiver | F5260: 45909 | G5260: 116.6 | H5260: - | I5260: Open | J5260: =IF(I5260="Open",DATE(2025,12,31)-F5260,"-") -> 113
B5261: INV-005256 | C5261: V-005256 | D5261: CL-021 | E5261: Private Insurance | F5261: 45909 | G5261: 130.95 | H5261: 45939 | I5261: Paid | J5261: =IF(I5261="Open",DATE(2025,12,31)-F5261,"-") -> -
B5262: INV-005257 | C5262: V-005257 | D5262: CL-023 | E5262: Medicare (Skilled) | F5262: 45909 | G5262: 160.05 | H5262: 45937 | I5262: Paid | J5262: =IF(I5262="Open",DATE(2025,12,31)-F5262,"-") -> -
B5263: INV-005258 | C5263: V-005258 | D5263: CL-024 | E5263: Private Pay | F5263: 45909 | G5263: 145.18 | H5263: 45930 | I5263: Paid | J5263: =IF(I5263="Open",DATE(2025,12,31)-F5263,"-") -> -
B5264: INV-005259 | C5264: V-005259 | D5264: CL-034 | E5264: Medicaid Waiver | F5264: 45909 | G5264: 95.11 | H5264: 45969 | I5264: Paid | J5264: =IF(I5264="Open",DATE(2025,12,31)-F5264,"-") -> -
B5265: INV-005260 | C5265: V-005260 | D5265: CL-039 | E5265: Private Pay | F5265: 45909 | G5265: 145.52 | H5265: 45922 | I5265: Paid | J5265: =IF(I5265="Open",DATE(2025,12,31)-F5265,"-") -> -
B5266: INV-005261 | C5266: V-005261 | D5266: CL-040 | E5266: Medicare (Skilled) | F5266: 45909 | G5266: 141.07 | H5266: 45970 | I5266: Paid | J5266: =IF(I5266="Open",DATE(2025,12,31)-F5266,"-") -> -
B5267: INV-005262 | C5267: V-005262 | D5267: CL-042 | E5267: Medicaid Waiver | F5267: 45909 | G5267: 103.88 | H5267: 45939 | I5267: Paid | J5267: =IF(I5267="Open",DATE(2025,12,31)-F5267,"-") -> -
B5268: INV-005263 | C5268: V-005263 | D5268: CL-044 | E5268: Private Insurance | F5268: 45909 | G5268: 132.3 | H5268: 45978 | I5268: Paid | J5268: =IF(I5268="Open",DATE(2025,12,31)-F5268,"-") -> -
B5269: INV-005264 | C5269: V-005264 | D5269: CL-050 | E5269: Medicare (Skilled) | F5269: 45909 | G5269: 155.1 | H5269: 46006 | I5269: Paid | J5269: =IF(I5269="Open",DATE(2025,12,31)-F5269,"-") -> -
B5270: INV-005265 | C5270: V-005265 | D5270: CL-051 | E5270: Medicare (Skilled) | F5270: 45909 | G5270: 163.35 | H5270: 45938 | I5270: Paid | J5270: =IF(I5270="Open",DATE(2025,12,31)-F5270,"-") -> -
B5271: INV-005266 | C5271: V-005266 | D5271: CL-053 | E5271: Medicaid Waiver | F5271: 45909 | G5271: 107.32 | H5271: 45998 | I5271: Paid | J5271: =IF(I5271="Open",DATE(2025,12,31)-F5271,"-") -> -
B5272: INV-005267 | C5272: V-005267 | D5272: CL-055 | E5272: Private Pay | F5272: 45909 | G5272: 135.66 | H5272: 45917 | I5272: Paid | J5272: =IF(I5272="Open",DATE(2025,12,31)-F5272,"-") -> -
... B5293: INV-005288 | C5293: V-005288 | D5293: CL-042 | E5293: Medicaid Waiver | F5293: 45910 | G5293: 116.07 | H5293: 45953 | I5293: Paid | J5293: =IF(I5293="Open",DATE(2025,12,31)-F5293,"-") -> -
B5294: INV-005289 | C5294: V-005289 | D5294: CL-045 | E5294: Medicaid Waiver | F5294: 45910 | G5294: 124.55 | H5294: - | I5294: Open | J5294: =IF(I5294="Open",DATE(2025,12,31)-F5294,"-") -> 112
B5295: INV-005290 | C5295: V-005290 | D5295: CL-049 | E5295: Private Pay | F5295: 45910 | G5295: 167.28 | H5295: 45918 | I5295: Paid | J5295: =IF(I5295="Open",DATE(2025,12,31)-F5295,"-") -> -
B5296: INV-005291 | C5296: V-005291 | D5296: CL-052 | E5296: Private Pay | F5296: 45910 | G5296: 126.48 | H5296: 45922 | I5296: Paid | J5296: =IF(I5296="Open",DATE(2025,12,31)-F5296,"-") -> -
B5297: INV-005292 | C5297: V-005292 | D5297: CL-053 | E5297: Medicaid Waiver | F5297: 45910 | G5297: 100.75 | H5297: 45957 | I5297: Paid | J5297: =IF(I5297="Open",DATE(2025,12,31)-F5297,"-") -> -
B5298: INV-005293 | C5298: V-005293 | D5298: CL-054 | E5298: Medicaid Waiver | F5298: 45910 | G5298: 114.21 | H5298: 46014 | I5298: Paid | J5298: =IF(I5298="Open",DATE(2025,12,31)-F5298,"-") -> -
B5299: INV-005294 | C5299: V-005294 | D5299: CL-055 | E5299: Private Pay | F5299: 45910 | G5299: 143.82 | H5299: 45920 | I5299: Paid | J5299: =IF(I5299="Open",DATE(2025,12,31)-F5299,"-") -> -
B5300: INV-005295 | C5300: V-005295 | D5300: CL-056 | E5300: Medicare (Skilled) | F5300: 45910 | G5300: 173.25 | H5300: 45962 | I5300: Paid | J5300: =IF(I5300="Open",DATE(2025,12,31)-F5300,"-") -> -
B5301: INV-005296 | C5301: V-005296 | D5301: CL-057 | E5301: Private Pay | F5301: 45910 | G5301: 147.22 | H5301: 45926 | I5301: Paid | J5301: =IF(I5301="Open",DATE(2025,12,31)-F5301,"-") -> -
B5302: INV-005297 | C5302: V-005297 | D5302: CL-059 | E5302: Medicaid Waiver | F5302: 45910 | G5302: 91.77 | H5302: 46016 | I5302: Paid | J5302: =IF(I5302="Open",DATE(2025,12,31)-F5302,"-") -> -
B5303: INV-005298 | C5303: V-005298 | D5303: CL-060 | E5303: Private Pay | F5303: 45910 | G5303: 133.96 | H5303: 45919 | I5303: Paid | J5303: =IF(I5303="Open",DATE(2025,12,31)-F5303,"-") -> -
B5304: INV-005299 | C5304: V-005299 | D5304: CL-061 | E5304: Private Pay | F5304: 45910 | G5304: 149.26 | H5304: 45916 | I5304: Paid | J5304: =IF(I5304="Open",DATE(2025,12,31)-F5304,"-") -> -
B5305: INV-005300 | C5305: V-005300 | D5305: CL-064 | E5305: Medicaid Waiver | F5305: 45910 | G5305: 95.93 | H5305: 45962 | I5305: Paid | J5305: =IF(I5305="Open",DATE(2025,12,31)-F5305,"-") -> -
B5306: INV-005301 | C5306: V-005301 | D5306: CL-065 | E5306: Medicaid Waiver | F5306: 45910 | G5306: 135.15 | H5306: - | I5306: Open | J5306: =IF(I5306="Open",DATE(2025,12,31)-F5306,"-") -> 112
B5307: INV-005302 | C5307: V-005302 | D5307: CL-004 | E5307: Private Pay | F5307: 45911 | G5307: 147.56 | H5307: 45931 | I5307: Paid | J5307: =IF(I5307="Open",DATE(2025,12,31)-F5307,"-") -> -
B5308: INV-005303 | C5308: V-005303 | D5308: CL-008 | E5308: Private Pay | F5308: 45911 | G5308: 94.52 | H5308: 45925 | I5308: Paid | J5308: =IF(I5308="Open",DATE(2025,12,31)-F5308,"-") -> -
B5309: INV-005304 | C5309: V-005304 | D5309: CL-015 | E5309: Medicaid Waiver | F5309: 45911 | G5309: 78.7 | H5309: 45988 | I5309: Paid | J5309: =IF(I5309="Open",DATE(2025,12,31)-F5309,"-") -> -
B5310: INV-005305 | C5310: V-005305 | D5310: CL-016 | E5310: Private Pay | F5310: 45911 | G5310: 123.76 | H5310: 45927 | I5310: Paid | J5310: =IF(I5310="Open",DATE(2025,12,31)-F5310,"-") -> -
B5311: INV-005306 | C5311: V-005306 | D5311: CL-018 | E5311: Private Pay | F5311: 45911 | G5311: 98.94 | H5311: 45923 | I5311: Paid | J5311: =IF(I5311="Open",DATE(2025,12,31)-F5311,"-") -> -
B5312: INV-005307 | C5312: V-005307 | D5312: CL-020 | E5312: Medicaid Waiver | F5312: 45911 | G5312: 104.12 | H5312: - | I5312: Open | J5312: =IF(I5312="Open",DATE(2025,12,31)-F5312,"-") -> 111
B5313: INV-005308 | C5313: V-005308 | D5313: CL-022 | E5313: Medicaid Waiver | F5313: 45911 | G5313: 69.91 | H5313: 45985 | I5313: Paid | J5313: =IF(I5313="Open",DATE(2025,12,31)-F5313,"-") -> -
B5314: INV-005309 | C5314: V-005309 | D5314: CL-024 | E5314: Private Pay | F5314: 45911 | G5314: 135.66 | H5314: 45918 | I5314: Paid | J5314: =IF(I5314="Open",DATE(2025,12,31)-F5314,"-") -> -
B5315: INV-005310 | C5315: V-005310 | D5315: CL-025 | E5315: Private Pay | F5315: 45911 | G5315: 140.42 | H5315: 45918 | I5315: Paid | J5315: =IF(I5315="Open",DATE(2025,12,31)-F5315,"-") -> -
B5316: INV-005311 | C5316: V-005311 | D5316: CL-030 | E5316: Private Pay | F5316: 45911 | G5316: 93.84 | H5316: 45924 | I5316: Paid | J5316: =IF(I5316="Open",DATE(2025,12,31)-F5316,"-") -> -
B5317: INV-005312 | C5317: V-005312 | D5317: CL-031 | E5317: Medicaid Waiver | F5317: 45911 | G5317: 111.83 | H5317: 45966 | I5317: Paid | J5317: =IF(I5317="Open",DATE(2025,12,31)-F5317,"-") -> -
B5318: INV-005313 | C5318: V-005313 | D5318: CL-034 | E5318: Medicaid Waiver | F5318: 45911 | G5318: 109.98 | H5318: - | I5318: Open | J5318: =IF(I5318="Open",DATE(2025,12,31)-F5318,"-") -> 111
B5319: INV-005314 | C5319: V-005314 | D5319: CL-035 | E5319: Medicaid Waiver | F5319: 45911 | G5319: 82.68 | H5319: 45952 | I5319: Paid | J5319: =IF(I5319="Open",DATE(2025,12,31)-F5319,"-") -> -
B5320: INV-005315 | C5320: V-005315 | D5320: CL-039 | E5320: Private Pay | F5320: 45911 | G5320: 141.1 | H5320: 45917 | I5320: Paid | J5320: =IF(I5320="Open",DATE(2025,12,31)-F5320,"-") -> -
B5321: INV-005316 | C5321: V-005316 | D5321: CL-041 | E5321: Private Pay | F5321: 45911 | G5321: 139.4 | H5321: 45928 | I5321: Paid | J5321: =IF(I5321="Open",DATE(2025,12,31)-F5321,"-") -> -
B5322: INV-005317 | C5322: V-005317 | D5322: CL-042 | E5322: Medicaid Waiver | F5322: 45911 | G5322: 115.01 | H5322: 45993 | I5322: Paid | J5322: =IF(I5322="Open",DATE(2025,12,31)-F5322,"-") -> -
B5323: INV-005318 | C5323: V-005318 | D5323: CL-047 | E5323: Private Pay | F5323: 45911 | G5323: 105.74 | H5323: 45921 | I5323: Paid | J5323: =IF(I5323="Open",DATE(2025,12,31)-F5323,"-") -> -
B5324: INV-005319 | C5324: V-005319 | D5324: CL-048 | E5324: Medicaid Waiver | F5324: 45911 | G5324: 109.44 | H5324: 45967 | I5324: Paid | J5324: =IF(I5324="Open",DATE(2025,12,31)-F5324,"-") -> -
B5325: INV-005320 | C5325: V-005320 | D5325: CL-053 | E5325: Medicaid Waiver | F5325: 45911 | G5325: 112.1 | H5325: 45961 | I5325: Paid | J5325: =IF(I5325="Open",DATE(2025,12,31)-F5325,"-") -> -
B5326: INV-005321 | C5326: V-005321 | D5326: CL-055 | E5326: Private Pay | F5326: 45911 | G5326: 143.14 | H5326: 45913 | I5326: Paid | J5326: =IF(I5326="Open",DATE(2025,12,31)-F5326,"-") -> -
B5327: INV-005322 | C5327: V-005322 | D5327: CL-057 | E5327: Private Pay | F5327: 45911 | G5327: 131.24 | H5327: 45920 | I5327: Paid | J5327: =IF(I5327="Open",DATE(2025,12,31)-F5327,"-") -> -
B5328: INV-005323 | C5328: V-005323 | D5328: CL-060 | E5328: Private Pay | F5328: 45911 | G5328: 147.56 | H5328: 45925 | I5328: Paid | J5328: =IF(I5328="Open",DATE(2025,12,31)-F5328,"-") -> -
B5329: INV-005324 | C5329: V-005324 | D5329: CL-004 | E5329: Private Pay | F5329: 45912 | G5329: 144.16 | H5329: 45921 | I5329: Paid | J5329: =IF(I5329="Open",DATE(2025,12,31)-F5329,"-") -> -
B5330: INV-005325 | C5330: V-005325 | D5330: CL-005 | E5330: Medicaid Waiver | F5330: 45912 | G5330: 133.3 | H5330: 45991 | I5330: Paid | J5330: =IF(I5330="Open",DATE(2025,12,31)-F5330,"-") -> -
... B5343: INV-005338 | C5343: V-005338 | D5343: CL-024 | E5343: Private Pay | F5343: 45912 | G5343: 148.24 | H5343: 45933 | I5343: Paid | J5343: =IF(I5343="Open",DATE(2025,12,31)-F5343,"-") -> -
B5344: INV-005339 | C5344: V-005339 | D5344: CL-027 | E5344: Medicaid Waiver | F5344: 45912 | G5344: 108.38 | H5344: - | I5344: Open | J5344: =IF(I5344="Open",DATE(2025,12,31)-F5344,"-") -> 110
B5345: INV-005340 | C5345: V-005340 | D5345: CL-029 | E5345: Medicaid Waiver | F5345: 45912 | G5345: 85.86 | H5345: 45980 | I5345: Paid | J5345: =IF(I5345="Open",DATE(2025,12,31)-F5345,"-") -> -
B5346: INV-005341 | C5346: V-005341 | D5346: CL-033 | E5346: Medicaid Waiver | F5346: 45912 | G5346: 116.97 | H5346: 45951 | I5346: Paid | J5346: =IF(I5346="Open",DATE(2025,12,31)-F5346,"-") -> -
B5347: INV-005342 | C5347: V-005342 | D5347: CL-034 | E5347: Medicaid Waiver | F5347: 45912 | G5347: 99.98 | H5347: 45973 | I5347: Paid | J5347: =IF(I5347="Open",DATE(2025,12,31)-F5347,"-") -> -
B5348: INV-005343 | C5348: V-005343 | D5348: CL-036 | E5348: Medicaid Waiver | F5348: 45912 | G5348: 96.46 | H5348: 45947 | I5348: Paid | J5348: =IF(I5348="Open",DATE(2025,12,31)-F5348,"-") -> -
B5349: INV-005344 | C5349: V-005344 | D5349: CL-037 | E5349: Medicaid Waiver | F5349: 45912 | G5349: 90.9 | H5349: 45959 | I5349: Paid | J5349: =IF(I5349="Open",DATE(2025,12,31)-F5349,"-") -> -
B5350: INV-005345 | C5350: V-005345 | D5350: CL-038 | E5350: Medicaid Waiver | F5350: 45912 | G5350: 92.8 | H5350: 46019 | I5350: Paid | J5350: =IF(I5350="Open",DATE(2025,12,31)-F5350,"-") -> -
B5351: INV-005346 | C5351: V-005346 | D5351: CL-039 | E5351: Private Pay | F5351: 45912 | G5351: 132.94 | H5351: 45928 | I5351: Paid | J5351: =IF(I5351="Open",DATE(2025,12,31)-F5351,"-") -> -
B5352: INV-005347 | C5352: V-005347 | D5352: CL-040 | E5352: Medicare (Skilled) | F5352: 45912 | G5352: 171.6 | H5352: 45943 | I5352: Paid | J5352: =IF(I5352="Open",DATE(2025,12,31)-F5352,"-") -> -
B5353: INV-005348 | C5353: V-005348 | D5353: CL-042 | E5353: Medicaid Waiver | F5353: 45912 | G5353: 100.97 | H5353: 45975 | I5353: Paid | J5353: =IF(I5353="Open",DATE(2025,12,31)-F5353,"-") -> -
B5354: INV-005349 | C5354: V-005349 | D5354: CL-044 | E5354: Private Insurance | F5354: 45912 | G5354: 147.15 | H5354: 45963 | I5354: Paid | J5354: =IF(I5354="Open",DATE(2025,12,31)-F5354,"-") -> -
B5355: INV-005350 | C5355: V-005350 | D5355: CL-045 | E5355: Medicaid Waiver | F5355: 45912 | G5355: 118.45 | H5355: 45949 | I5355: Paid | J5355: =IF(I5355="Open",DATE(2025,12,31)-F5355,"-") -> -
B5356: INV-005351 | C5356: V-005351 | D5356: CL-049 | E5356: Private Pay | F5356: 45912 | G5356: 154.7 | H5356: 45922 | I5356: Paid | J5356: =IF(I5356="Open",DATE(2025,12,31)-F5356,"-") -> -
... B5398: INV-005393 | C5398: V-005393 | D5398: CL-025 | E5398: Private Pay | F5398: 45915 | G5398: 123.76 | H5398: 45934 | I5398: Paid | J5398: =IF(I5398="Open",DATE(2025,12,31)-F5398,"-") -> -
B5399: INV-005394 | C5399: V-005394 | D5399: CL-027 | E5399: Medicaid Waiver | F5399: 45915 | G5399: 98.84 | H5399: - | I5399: Open | J5399: =IF(I5399="Open",DATE(2025,12,31)-F5399,"-") -> 107
B5400: INV-005395 | C5400: V-005395 | D5400: CL-029 | E5400: Medicaid Waiver | F5400: 45915 | G5400: 80.56 | H5400: 45980 | I5400: Paid | J5400: =IF(I5400="Open",DATE(2025,12,31)-F5400,"-") -> -
B5401: INV-005396 | C5401: V-005396 | D5401: CL-030 | E5401: Private Pay | F5401: 45915 | G5401: 102.68 | H5401: 45930 | I5401: Paid | J5401: =IF(I5401="Open",DATE(2025,12,31)-F5401,"-") -> -
B5402: INV-005397 | C5402: V-005397 | D5402: CL-031 | E5402: Medicaid Waiver | F5402: 45915 | G5402: 97.18 | H5402: 45963 | I5402: Paid | J5402: =IF(I5402="Open",DATE(2025,12,31)-F5402,"-") -> -
...

Sheet AR Aging Buckets
B2: AR Aging Buckets - Standard Aging Report (Year-End)
B3: The report a real AR/collections team works from: how much is owed, by payer, broken into aging buckets.
B5: Payer | C5: Current | D5: 1-30 Days | E5: 31-60 Days | F5: 61-90 Days | G5: 90+ Days | H5: Total
B6: Medicaid Waiver | C6: =SUMIFS('AR Detail Ledger'!$G$6:$G$8129,'AR Detail Ledger'!$E$6:$E$8129,"Medicaid Waiver",'AR Detail Ledger'!$I$6:$I$8129,"Open",'AR Detail Ledger'!$J$6:$J$8129,"<=0") -> 1892.16 | D6: =SUMIFS('AR Detail Ledger'!$G$6:$G$8129,'AR Detail Ledger'!$E$6:$E$8129,"Medicaid Waiver",'AR Detail Ledger'!$I$6:$I$8129,"Open",'AR Detail Ledger'!$J$6:$J$8129,">0",'AR Detail Ledger'!$J$6:$J$8129,"<=30") -> 33909.53 | E6: =SUMIFS('AR Detail Ledger'!$G$6:$G$8129,'AR Detail Ledger'!$E$6:$E$8129,"Medicaid Waiver",'AR Detail Ledger'!$I$6:$I$8129,"Open",'AR Detail Ledger'!$J$6:$J$8129,">30",'AR Detail Ledger'!$J$6:$J$8129,"<=60") -> 24943.43 | F6: =SUMIFS('AR Detail Ledger'!$G$6:$G$8129,'AR Detail Ledger'!$E$6:$E$8129,"Medicaid Waiver",'AR Detail Ledger'!$I$6:$I$8129,"Open",'AR Detail Ledger'!$J$6:$J$8129,">60",'AR Detail Ledger'!$J$6:$J$8129,"<=90") -> 11072.34 | G6: =SUMIFS('AR Detail Ledger'!$G$6:$G$8129,'AR Detail Ledger'!$E$6:$E$8129,"Medicaid Waiver",'AR Detail Ledger'!$I$6:$I$8129,"Open",'AR Detail Ledger'!$J$6:$J$8129,">90") -> 3114.76 | H6: =SUM(C6:G6) -> 74932.22
B7: Private Pay | C7: =SUMIFS('AR Detail Ledger'!$G$6:$G$8129,'AR Detail Ledger'!$E$6:$E$8129,"Private Pay",'AR Detail Ledger'!$I$6:$I$8129,"Open",'AR Detail Ledger'!$J$6:$J$8129,"<=0") -> 1411 | D7: =SUMIFS('AR Detail Ledger'!$G$6:$G$8129,'AR Detail Ledger'!$E$6:$E$8129,"Private Pay",'AR Detail Ledger'!$I$6:$I$8129,"Open",'AR Detail Ledger'!$J$6:$J$8129,">0",'AR Detail Ledger'!$J$6:$J$8129,"<=30") -> 13706.76 | E7: =SUMIFS('AR Detail Ledger'!$G$6:$G$8129,'AR Detail Ledger'!$E$6:$E$8129,"Private Pay",'AR Detail Ledger'!$I$6:$I$8129,"Open",'AR Detail Ledger'!$J$6:$J$8129,">30",'AR Detail Ledger'!$J$6:$J$8129,"<=60") -> 0 | F7: =SUMIFS('AR Detail Ledger'!$G$6:$G$8129,'AR Detail Ledger'!$E$6:$E$8129,"Private Pay",'AR Detail Ledger'!$I$6:$I$8129,"Open",'AR Detail Ledger'!$J$6:$J$8129,">60",'AR Detail Ledger'!$J$6:$J$8129,"<=90") -> 0 | G7: =SUMIFS('AR Detail Ledger'!$G$6:$G$8129,'AR Detail Ledger'!$E$6:$E$8129,"Private Pay",'AR Detail Ledger'!$I$6:$I$8129,"Open",'AR Detail Ledger'!$J$6:$J$8129,">90") -> 0 | H7: =SUM(C7:G7) -> 15117.76
B8: Medicare (Skilled) | C8: =SUMIFS('AR Detail Ledger'!$G$6:$G$8129,'AR Detail Ledger'!$E$6:$E$8129,"Medicare (Skilled)",'AR Detail Ledger'!$I$6:$I$8129,"Open",'AR Detail Ledger'!$J$6:$J$8129,"<=0") -> 486.75 | D8: =SUMIFS('AR Detail Ledger'!$G$6:$G$8129,'AR Detail Ledger'!$E$6:$E$8129,"Medicare (Skilled)",'AR Detail Ledger'!$I$6:$I$8129,"Open",'AR Detail Ledger'!$J$6:$J$8129,">0",'AR Detail Ledger'!$J$6:$J$8129,"<=30") -> 12534.71 | E8: =SUMIFS('AR Detail Ledger'!$G$6:$G$8129,'AR Detail Ledger'!$E$6:$E$8129,"Medicare (Skilled)",'AR Detail Ledger'!$I$6:$I$8129,"Open",'AR Detail Ledger'!$J$6:$J$8129,">30",'AR Detail Ledger'!$J$6:$J$8129,"<=60") -> 4323.66 | F8: =SUMIFS('AR Detail Ledger'!$G$6:$G$8129,'AR Detail Ledger'!$E$6:$E$8129,"Medicare (Skilled)",'AR Detail Ledger'!$I$6:$I$8129,"Open",'AR Detail Ledger'!$J$6:$J$8129,">60",'AR Detail Ledger'!$J$6:$J$8129,"<=90") -> 1514.7 | G8: =SUMIFS('AR Detail Ledger'!$G$6:$G$8129,'AR Detail Ledger'!$E$6:$E$8129,"Medicare (Skilled)",'AR Detail Ledger'!$I$6:$I$8129,"Open",'AR Detail Ledger'!$J$6:$J$8129,">90") -> 169.95 | H8: =SUM(C8:G8) -> 19029.77
B9: Private Insurance | C9: =SUMIFS('AR Detail Ledger'!$G$6:$G$8129,'AR Detail Ledger'!$E$6:$E$8129,"Private Insurance",'AR Detail Ledger'!$I$6:$I$8129,"Open",'AR Detail Ledger'!$J$6:$J$8129,"<=0") -> 292.95 | D9: =SUMIFS('AR Detail Ledger'!$G$6:$G$8129,'AR Detail Ledger'!$E$6:$E$8129,"Private Insurance",'AR Detail Ledger'!$I$6:$I$8129,"Open",'AR Detail Ledger'!$J$6:$J$8129,">0",'AR Detail Ledger'!$J$6:$J$8129,"<=30") -> 7990.51 | E9: =SUMIFS('AR Detail Ledger'!$G$6:$G$8129,'AR Detail Ledger'!$E$6:$E$8129,"Private Insurance",'AR Detail Ledger'!$I$6:$I$8129,"Open",'AR Detail Ledger'!$J$6:$J$8129,">30",'AR Detail Ledger'!$J$6:$J$8129,"<=60") -> 3905.95 | F9: =SUMIFS('AR Detail Ledger'!$G$6:$G$8129,'AR Detail Ledger'!$E$6:$E$8129,"Private Insurance",'AR Detail Ledger'!$I$6:$I$8129,"Open",'AR Detail Ledger'!$J$6:$J$8129,">60",'AR Detail Ledger'!$J$6:$J$8129,"<=90") -> 2124.76 | G9: =SUMIFS('AR Detail Ledger'!$G$6:$G$8129,'AR Detail Ledger'!$E$6:$E$8129,"Private Insurance",'AR Detail Ledger'!$I$6:$I$8129,"Open",'AR Detail Ledger'!$J$6:$J$8129,">90") -> 141.75 | H9: =SUM(C9:G9) -> 14455.92
B10: TOTAL | C10: =SUM(C6:C9) -> 4082.86 | D10: =SUM(D6:D9) -> 68141.51 | E10: =SUM(E6:E9) -> 33173.04 | F10: =SUM(F6:F9) -> 14711.8 | G10: =SUM(G6:G9) -> 3426.46 | H10: =SUM(H6:H9) -> 123535.67
B12: % OF TOTAL AR BY BUCKET
C13: Current | D13: 1-30 | E13: 31-60 | F13: 61-90 | G13: 90+
C14: =IFERROR(C10/$H$10,0) -> 0.033050049 | D14: =IFERROR(D10/$H$10,0) -> 0.5515938 | E14: =IFERROR(E10/$H$10,0) -> 0.26853005 | F14: =IFERROR(F10/$H$10,0) -> 0.11908949 | G14: =IFERROR(G10/$H$10,0) -> 0.027736604

Sheet Daily Overhead Register
B2: Daily Overhead Register - Every Expense Transaction, Full Year
B3: 833 transactions. Source of truth for all overhead - filterable by any date range.
B5: Transaction ID | C5: Date | D5: Category | E5: Amount | F5: Bank Account
B6: OH-00001 | C6: 45658 | D6: Office Rent | E6: 2079.87 | F6: Operating Account
B7: OH-00002 | C7: 45669 | D7: Office Utilities - Electric | E7: 87.47 | F7: Operating Account
B8: OH-00003 | C8: 45672 | D8: Office Utilities - Electric | E8: 57.1 | F8: Operating Account
B9: OH-00004 | C9: 45688 | D9: Office Utilities - Electric | E9: 73.3 | F9: Operating Account
B10: OH-00005 | C10: 45658 | D10: Office Utilities - Water/Sewer | E10: 24.33 | F10: Operating Account
B11: OH-00006 | C11: 45671 | D11: Office Utilities - Water/Sewer | E11: 15.84 | F11: Operating Account
B12: OH-00007 | C12: 45674 | D12: Office Utilities - Water/Sewer | E12: 12.13 | F12: Operating Account
B13: OH-00008 | C13: 45677 | D13: Office Utilities - Water/Sewer | E13: 12.92 | F13: Operating Account
B14: OH-00009 | C14: 45659 | D14: Office Utilities - Gas/Heat | E14: 23.47 | F14: Operating Account
B15: OH-00010 | C15: 45663 | D15: Office Utilities - Gas/Heat | E15: 18.42 | F15: Operating Account
B16: OH-00011 | C16: 45670 | D16: Office Utilities - Gas/Heat | E16: 14.57 | F16: Operating Account
B17: OH-00012 | C17: 45685 | D17: Office Utilities - Gas/Heat | E17: 44.63 | F17: Operating Account
... B838: OH-00833 | C838: 46022 | D838: Line of Credit Interest | E838: 0 | F838: Non-Cash
B840: TOTAL OVERHEAD (Year) | E840: =SUM(E6:E838) -> 286716.65

Sheet Overhead (Opex)
B2: Overhead / Operating Expenses - Monthly Rollup
B3: Rolled up from the Daily Overhead Register via date-range SUMIFS. Includes non-cash depreciation and LOC interest.
C5: Jan-2025 | D5: Feb-2025 | E5: Mar-2025 | F5: Apr-2025 | G5: May-2025 | H5: Jun-2025 | I5: Jul-2025 | J5: Aug-2025 | K5: Sep-2025 | L5: Oct-2025 | M5: Nov-2025 | N5: Dec-2025 | O5: FY Total
B6: Admin Salaries - Billing Clerk | C6: =SUMIFS('Daily Overhead Register'!$E$6:$E$838,'Daily Overhead Register'!$C$6:$C$838,">="&DATE(2025,1,1),'Daily Overhead Register'!$C$6:$C$838,"<"&DATE(2025,2,1),'Daily Overhead Register'!$D$6:$D$838,"Admin Salaries - Billing Clerk") -> 1341.23 | D6: =SUMIFS('Daily Overhead Register'!$E$6:$E$838,'Daily Overhead Register'!$C$6:$C$838,">="&DATE(2025,2,1),'Daily Overhead Register'!$C$6:$C$838,"<"&DATE(2025,3,1),'Daily Overhead Register'!$D$6:$D$838,"Admin Salaries - Billing Clerk") -> 1334.81 | E6: =SUMIFS('Daily Overhead Register'!$E$6:$E$838,'Daily Overhead Register'!$C$6:$C$838,">="&DATE(2025,3,1),'Daily Overhead Register'!$C$6:$C$838,"<"&DATE(2025,4,1),'Daily Overhead Register'!$D$6:$D$838,"Admin Salaries - Billing Clerk") -> 1357.85 | F6: =SUMIFS('Daily Overhead Register'!$E$6:$E$838,'Daily Overhead Register'!$C$6:$C$838,">="&DATE(2025,4,1),'Daily Overhead Register'!$C$6:$C$838,"<"&DATE(2025,5,1),'Daily Overhead Register'!$D$6:$D$838,"Admin Salaries - Billing Clerk") -> 1328.57 | G6: =SUMIFS('Daily Overhead Register'!$E$6:$E$838,'Daily Overhead Register'!$C$6:$C$838,">="&DATE(2025,5,1),'Daily Overhead Register'!$C$6:$C$838,"<"&DATE(2025,6,1),'Daily Overhead Register'!$D$6:$D$838,"Admin Salaries - Billing Clerk") -> 1433.04 | H6: =SUMIFS('Daily Overhead Register'!$E$6:$E$838,'Daily Overhead Register'!$C$6:$C$838,">="&DATE(2025,6,1),'Daily Overhead Register'!$C$6:$C$838,"<"&DATE(2025,7,1),'Daily Overhead Register'!$D$6:$D$838,"Admin Salaries - Billing Clerk") -> 1325.19 | I6: =SUMIFS('Daily Overhead Register'!$E$6:$E$838,'Daily Overhead Register'!$C$6:$C$838,">="&DATE(2025,7,1),'Daily Overhead Register'!$C$6:$C$838,"<"&DATE(2025,8,1),'Daily Overhead Register'!$D$6:$D$838,"Admin Salaries - Billing Clerk") -> 1354.34 | J6: =SUMIFS('Daily Overhead Register'!$E$6:$E$838,'Daily Overhead Register'!$C$6:$C$838,">="&DATE(2025,8,1),'Daily Overhead Register'!$C$6:$C$838,"<"&DATE(2025,9,1),'Daily Overhead Register'!$D$6:$D$838,"Admin Salaries - Billing Clerk") -> 1359.16 | K6: =SUMIFS('Daily Overhead Register'!$E$6:$E$838,'Daily Overhead Register'!$C$6:$C$838,">="&DATE(2025,9,1),'Daily Overhead Register'!$C$6:$C$838,"<"&DATE(2025,10,1),'Daily Overhead Register'!$D$6:$D$838,"Admin Salaries - Billing Clerk") -> 1420.82 | L6: =SUMIFS('Daily Overhead Register'!$E$6:$E$838,'Daily Overhead Register'!$C$6:$C$838,">="&DATE(2025,10,1),'Daily Overhead Register'!$C$6:$C$838,"<"&DATE(2025,11,1),'Daily Overhead Register'!$D$6:$D$838,"Admin Salaries - Billing Clerk") -> 1402.68 | M6: =SUMIFS('Daily Overhead Register'!$E$6:$E$838,'Daily Overhead Register'!$C$6:$C$838,">="&DATE(2025,11,1),'Daily Overhead Register'!$C$6:$C$838,"<"&DATE(2025,12,1),'Daily Overhead Register'!$D$6:$D$838,"Admin Salaries - Billing Clerk") -> 1386.91 | N6: =SUMIFS('Daily Overhead Register'!$E$6:$E$838,'Daily Overhead Register'!$C$6:$C$838,">="&DATE(2025,12,1),'Daily Overhead Register'!$C$6:$C$838,"<"&DATE(2026,1,1),'Daily Overhead Register'!$D$6:$D$838,"Admin Salaries - Billing Clerk") -> 1463.11 | O6: =SUM(C6:N6) -> 16507.71
B7: Admin Salaries - Office Manager | C7: =SUMIFS('Daily Overhead Register'!$E$6:$E$838,'Daily Overhead Register'!$C$6:$C$838,">="&DATE(2025,1,1),'Daily Overhead Register'!$C$6:$C$838,"<"&DATE(2025,2,1),'Daily Overhead Register'!$D$6:$D$838,"Admin Salaries - Office Manager") -> 3079.96 | D7: =SUMIFS('Daily Overhead Register'!$E$6:$E$838,'Daily Overhead Register'!$C$6:$C$838,">="&DATE(2025,2,1),'Daily Overhead Register'!$C$6:$C$838,"<"&DATE(2025,3,1),'Daily Overhead Register'!$D$6:$D$838,"Admin Salaries - Office Manager") -> 3035.19 | E7: =SUMIFS('Daily Overhead Register'!$E$6:$E$838,'Daily Overhead Register'!$C$6:$C$838,">="&DATE(2025,3,1),'Daily Overhead Register'!$C$6:$C$838,"<"&DATE(2025,4,1),'Daily Overhead Register'!$D$6:$D$838,"Admin Salaries - Office Manager") -> 3404.89 | F7: =SUMIFS('Daily Overhead Register'!$E$6:$E$838,'Daily Overhead Register'!$C$6:$C$838,">="&DATE(2025,4,1),'Daily Overhead Register'!$C$6:$C$838,"<"&DATE(2025,5,1),'Daily Overhead Register'!$D$6:$D$838,"Admin Salaries - Office Manager") -> 3397.47 | G7: =SUMIFS('Daily Overhead Register'!$E$6:$E$838,'Daily Overhead Register'!$C$6:$C$838,">="&DATE(2025,5,1),'Daily Overhead Register'!$C$6:$C$838,"<"&DATE(2025,6,1),'Daily Overhead Register'!$D$6:$D$838,"Admin Salaries - Office Manager") -> 3142.1 | H7: =SUMIFS('Daily Overhead Register'!$E$6:$E$838,'Daily Overhead Register'!$C$6:$C$838,">="&DATE(2025,6,1),'Daily Overhead Register'!$C$6:$C$838,"<"&DATE(2025,7,1),'Daily Overhead Register'!$D$6:$D$838,"Admin Salaries - Office Manager") -> 3384.83 | I7: =SUMIFS('Daily Overhead Register'!$E$6:$E$838,'Daily Overhead Register'!$C$6:$C$838,">="&DATE(2025,7,1),'Daily Overhead Register'!$C$6:$C$838,"<"&DATE(2025,8,1),'Daily Overhead Register'!$D$6:$D$838,"Admin Salaries - Office Manager") -> 3279.87 | J7: =SUMIFS('Daily Overhead Register'!$E$6:$E$838,'Daily Overhead Register'!$C$6:$C$838,">="&DATE(2025,8,1),'Daily Overhead Register'!$C$6:$C$838,"<"&DATE(2025,9,1),'Daily Overhead Register'!$D$6:$D$838,"Admin Salaries - Office Manager") -> 3408.28 | K7: =SUMIFS('Daily Overhead Register'!$E$6:$E$838,'Daily Overhead Register'!$C$6:$C$838,">="&DATE(2025,9,1),'Daily Overhead Register'!$C$6:$C$838,"<"&DATE(2025,10,1),'Daily Overhead Register'!$D$6:$D$838,"Admin Salaries - Office Manager") -> 3346.63 | L7: =SUMIFS('Daily Overhead Register'!$E$6:$E$838,'Daily Overhead Register'!$C$6:$C$838,">="&DATE(2025,10,1),'Daily Overhead Register'!$C$6:$C$838,"<"&DATE(2025,11,1),'Daily Overhead Register'!$D$6:$D$838,"Admin Salaries - Office Manager") -> 3058.34 | M7: =SUMIFS('Daily Overhead Register'!$E$6:$E$838,'Daily Overhead Register'!$C$6:$C$838,">="&DATE(2025,11,1),'Daily Overhead Register'!$C$6:$C$838,"<"&DATE(2025,12,1),'Daily Overhead Register'!$D$6:$D$838,"Admin Salaries - Office Manager") -> 3013.11 | N7: =SUMIFS('Daily Overhead Register'!$E$6:$E$838,'Daily Overhead Register'!$C$6:$C$838,">="&DATE(2025,12,1),'Daily Overhead Register'!$C$6:$C$838,"<"&DATE(2026,1,1),'Daily Overhead Register'!$D$6:$D$838,"Admin Salaries - Office Manager") -> 3370.81 | O7: =SUM(C7:N7) -> 38921.48
B8: Admin Salaries - Scheduler/Coordinator | C8: =SUMIFS('Daily Overhead Register'!$E$6:$E$838,'Daily Overhead Register'!$C$6:$C$838,">="&DATE(2025,1,1),'Daily Overhead Register'!$C$6:$C$838,"<"&DATE(2025,2,1),'Daily Overhead Register'!$D$6:$D$838,"Admin Salaries - Scheduler/Coordinator") -> 2747.76 | D8: =SUMIFS('Daily Overhead Register'!$E$6:$E$838,'Daily Overhead Register'!$C$6:$C$838,">="&DATE(2025,2,1),'Daily Overhead Register'!$C$6:$C$838,"<"&DATE(2025,3,1),'Daily Overhead Register'!$D$6:$D$838,"Admin Salaries - Scheduler/Coordinator") -> 2626.51 | E8: =SUMIFS('Daily Overhead Register'!$E$6:$E$838,'Daily Overhead Register'!$C$6:$C$838,">="&DATE(2025,3,1),'Daily Overhead Register'!$C$6:$C$838,"<"&DATE(2025,4,1),'Daily Overhead Register'!$D$6:$D$838,"Admin Salaries - Scheduler/Coordinator") -> 2731.09 | F8: =SUMIFS('Daily Overhead Register'!$E$6:$E$838,'Daily Overhead Register'!$C$6:$C$838,">="&DATE(2025,4,1),'Daily Overhead Register'!$C$6:$C$838,"<"&DATE(2025,5,1),'Daily Overhead Register'!$D$6:$D$838,"Admin Salaries - Scheduler/Coordinator") -> 2457.84 | G8: =SUMIFS('Daily Overhead Register'!$E$6:$E$838,'Daily Overhead Register'!$C$6:$C$838,">="&DATE(2025,5,1),'Daily Overhead Register'!$C$6:$C$838,"<"&DATE(2025,6,1),'Daily Overhead Register'!$D$6:$D$838,"Admin Salaries - Scheduler/Coordinator") -> 2704.65 | H8: =SUMIFS('Daily Overhead Register'!$E$6:$E$838,'Daily Overhead Register'!$C$6:$C$838,">="&DATE(2025,6,1),'Daily Overhead Register'!$C$6:$C$838,"<"&DATE(2025,7,1),'Daily Overhead Register'!$D$6:$D$838,"Admin Salaries - Scheduler/Coordinator") -> 2666.46 | I8: =SUMIFS('Daily Overhead Register'!$E$6:$E$838,'Daily Overhead Register'!$C$6:$C$838,">="&DATE(2025,7,1),'Daily Overhead Register'!$C$6:$C$838,"<"&DATE(2025,8,1),'Daily Overhead Register'!$D$6:$D$838,"Admin Salaries - Scheduler/Coordinator") -> 2797.96 | J8: =SUMIFS('Daily Overhead Register'!$E$6:$E$838,'Daily Overhead Register'!$C$6:$C$838,">="&DATE(2025,8,1),'Daily Overhead Register'!$C$6:$C$838,"<"&DATE(2025,9,1),'Daily Overhead Register'!$D$6:$D$838,"Admin Salaries - Scheduler/Coordinator") -> 2672.61 | K8: =SUMIFS('Daily Overhead Register'!$E$6:$E$838,'Daily Overhead Register'!$C$6:$C$838,">="&DATE(2025,9,1),'Daily Overhead Register'!$C$6:$C$838,"<"&DATE(2025,10,1),'Daily Overhead Register'!$D$6:$D$838,"Admin Salaries - Scheduler/Coordinator") -> 2804.33 | L8: =SUMIFS('Daily Overhead Register'!$E$6:$E$838,'Daily Overhead Register'!$C$6:$C$838,">="&DATE(2025,10,1),'Daily Overhead Register'!$C$6:$C$838,"<"&DATE(2025,11,1),'Daily Overhead Register'!$D$6:$D$838,"Admin Salaries - Scheduler/Coordinator") -> 2479.52 | M8: =SUMIFS('Daily Overhead Register'!$E$6:$E$838,'Daily Overhead Register'!$C$6:$C$838,">="&DATE(2025,11,1),'Daily Overhead Register'!$C$6:$C$838,"<"&DATE(2025,12,1),'Daily Overhead Register'!$D$6:$D$838,"Admin Salaries - Scheduler/Coordinator") -> 2774.36 | N8: =SUMIFS('Daily Overhead Register'!$E$6:$E$838,'Daily Overhead Register'!$C$6:$C$838,">="&DATE(2025,12,1),'Daily Overhead Register'!$C$6:$C$838,"<"&DATE(2026,1,1),'Daily Overhead Register'!$D$6:$D$838,"Admin Salaries - Scheduler/Coordinator") -> 2658.03 | O8: =SUM(C8:N8) -> 32121.12
B9: Background Checks and Licensing | C9: =SUMIFS('Daily Overhead Register'!$E$6:$E$838,'Daily Overhead Register'!$C$6:$C$838,">="&DATE(2025,1,1),'Daily Overhead Register'!$C$6:$C$838,"<"&DATE(2025,2,1),'Daily Overhead Register'!$D$6:$D$838,"Background Checks and Licensing") -> 250.43 | D9: =SUMIFS('Daily Overhead Register'!$E$6:$E$838,'Daily Overhead Register'!$C$6:$C$838,">="&DATE(2025,2,1),'Daily Overhead Register'!$C$6:$C$838,"<"&DATE(2025,3,1),'Daily Overhead Register'!$D$6:$D$838,"Background Checks and Licensing") -> 252.39 | E9: =SUMIFS('Daily Overhead Register'!$E$6:$E$838,'Daily Overhead Register'!$C$6:$C$838,">="&DATE(2025,3,1),'Daily Overhead Register'!$C$6:$C$838,"<"&DATE(2025,4,1),'Daily Overhead Register'!$D$6:$D$838,"Background Checks and Licensing") -> 251.18 | F9: =SUMIFS('Daily Overhead Register'!$E$6:$E$838,'Daily Overhead Register'!$C$6:$C$838,">="&DATE(2025,4,1),'Daily Overhead Register'!$C$6:$C$838,"<"&DATE(2025,5,1),'Daily Overhead Register'!$D$6:$D$838,"Background Checks and Licensing") -> 258.02 | G9: =SUMIFS('Daily Overhead Register'!$E$6:$E$838,'Daily Overhead Register'!$C$6:$C$838,">="&DATE(2025,5,1),'Daily Overhead Register'!$C$6:$C$838,"<"&DATE(2025,6,1),'Daily Overhead Register'!$D$6:$D$838,"Background Checks and Licensing") -> 261.91 | H9: =SUMIFS('Daily Overhead Register'!$E$6:$E$838,'Daily Overhead Register'!$C$6:$C$838,">="&DATE(2025,6,1),'Daily Overhead Register'!$C$6:$C$838,"<"&DATE(2025,7,1),'Daily Overhead Register'!$D$6:$D$838,"Background Checks and Licensing") -> 247.58 | I9: =SUMIFS('Daily Overhead Register'!$E$6:$E$838,'Daily Overhead Register'!$C$6:$C$838,">="&DATE(2025,7,1),'Daily Overhead Register'!$C$6:$C$838,"<"&DATE(2025,8,1),'Daily Overhead Register'!$D$6:$D$838,"Background Checks and Licensing") -> 258.84 | J9: =SUMIFS('Daily Overhead Register'!$E$6:$E$838,'Daily Overhead Register'!$C$6:$C$838,">="&DATE(2025,8,1),'Daily Overhead Register'!$C$6:$C$838,"<"&DATE(2025,9,1),'Daily Overhead Register'!$D$6:$D$838,"Background Checks and Licensing") -> 262.08 | K9: =SUMIFS('Daily Overhead Register'!$E$6:$E$838,'Daily Overhead Register'!$C$6:$C$838,">="&DATE(2025,9,1),'Daily Overhead Register'!$C$6:$C$838,"<"&DATE(2025,10,1),'Daily Overhead Register'!$D$6:$D$838,"Background Checks and Licensing") -> 256.61 | L9: =SUMIFS('Daily Overhead Register'!$E$6:$E$838,'Daily Overhead Register'!$C$6:$C$838,">="&DATE(2025,10,1),'Daily Overhead Register'!$C$6:$C$838,"<"&DATE(2025,11,1),'Daily Overhead Register'!$D$6:$D$838,"Background Checks and Licensing") -> 262.45 | M9: =SUMIFS('Daily Overhead Register'!$E$6:$E$838,'Daily Overhead Register'!$C$6:$C$838,">="&DATE(2025,11,1),'Daily Overhead Register'!$C$6:$C$838,"<"&DATE(2025,12,1),'Daily Overhead Register'!$D$6:$D$838,"Background Checks and Licensing") -> 250.42 | N9: =SUMIFS('Daily Overhead Register'!$E$6:$E$838,'Daily Overhead Register'!$C$6:$C$838,">="&DATE(2025,12,1),'Daily Overhead Register'!$C$6:$C$838,"<"&DATE(2026,1,1),'Daily Overhead Register'!$D$6:$D$838,"Background Checks and Licensing") -> 265.34 | O9: =SUM(C9:N9) -> 3077.25
B10: Bad Debt / Claim Denials Write-off | C10: =SUMIFS('Daily Overhead Register'!$E$6:$E$838,'Daily Overhead Register'!$C$6:$C$838,">="&DATE(2025,1,1),'Daily Overhead Register'!$C$6:$C$838,"<"&DATE(2025,2,1),'Daily Overhead Register'!$D$6:$D$838,"Bad Debt / Claim Denials Write-off") -> 0 | D10: =SUMIFS('Daily Overhead Register'!$E$6:$E$838,'Daily Overhead Register'!$C$6:$C$838,">="&DATE(2025,2,1),'Daily Overhead Register'!$C$6:$C$838,"<"&DATE(2025,3,1),'Daily Overhead Register'!$D$6:$D$838,"Bad Debt / Claim Denials Write-off") -> 0 | E10: =SUMIFS('Daily Overhead Register'!$E$6:$E$838,'Daily Overhead Register'!$C$6:$C$838,">="&DATE(2025,3,1),'Daily Overhead Register'!$C$6:$C$838,"<"&DATE(2025,4,1),'Daily Overhead Register'!$D$6:$D$838,"Bad Debt / Claim Denials Write-off") -> 0 | F10: =SUMIFS('Daily Overhead Register'!$E$6:$E$838,'Daily Overhead Register'!$C$6:$C$838,">="&DATE(2025,4,1),'Daily Overhead Register'!$C$6:$C$838,"<"&DATE(2025,5,1),'Daily Overhead Register'!$D$6:$D$838,"Bad Debt / Claim Denials Write-off") -> 0 | G10: =SUMIFS('Daily Overhead Register'!$E$6:$E$838,'Daily Overhead Register'!$C$6:$C$838,">="&DATE(2025,5,1),'Daily Overhead Register'!$C$6:$C$838,"<"&DATE(2025,6,1),'Daily Overhead Register'!$D$6:$D$838,"Bad Debt / Claim Denials Write-off") -> 0 | H10: =SUMIFS('Daily Overhead Register'!$E$6:$E$838,'Daily Overhead Register'!$C$6:$C$838,">="&DATE(2025,6,1),'Daily Overhead Register'!$C$6:$C$838,"<"&DATE(2025,7,1),'Daily Overhead Register'!$D$6:$D$838,"Bad Debt / Claim Denials Write-off") -> 0 | I10: =SUMIFS('Daily Overhead Register'!$E$6:$E$838,'Daily Overhead Register'!$C$6:$C$838,">="&DATE(2025,7,1),'Daily Overhead Register'!$C$6:$C$838,"<"&DATE(2025,8,1),'Daily Overhead Register'!$D$6:$D$838,"Bad Debt / Claim Denials Write-off") -> 0 | J10: =SUMIFS('Daily Overhead Register'!$E$6:$E$838,'Daily Overhead Register'!$C$6:$C$838,">="&DATE(2025,8,1),'Daily Overhead Register'!$C$6:$C$838,"<"&DATE(2025,9,1),'Daily Overhead Register'!$D$6:$D$838,"Bad Debt / Claim Denials Write-off") -> 0 | K10: =SUMIFS('Daily Overhead Register'!$E$6:$E$838,'Daily Overhead Register'!$C$6:$C$838,">="&DATE(2025,9,1),'Daily Overhead Register'!$C$6:$C$838,"<"&DATE(2025,10,1),'Daily Overhead Register'!$D$6:$D$838,"Bad Debt / Claim Denials Write-off") -> 0 | L10: =SUMIFS('Daily Overhead Register'!$E$6:$E$838,'Daily Overhead Register'!$C$6:$C$838,">="&DATE(2025,10,1),'Daily Overhead Register'!$C$6:$C$838,"<"&DATE(2025,11,1),'Daily Overhead Register'!$D$6:$D$838,"Bad Debt / Claim Denials Write-off") -> 0 | M10: =SUMIFS('Daily Overhead Register'!$E$6:$E$838,'Daily Overhead Register'!$C$6:$C$838,">="&DATE(2025,11,1),'Daily Overhead Register'!$C$6:$C$838,"<"&DATE(2025,12,1),'Daily Overhead Register'!$D$6:$D$838,"Bad Debt / Claim Denials Write-off") -> 0 | N10: =SUMIFS('Daily Overhead Register'!$E$6:$E$838,'Daily Overhead Register'!$C$6:$C$838,">="&DATE(2025,12,1),'Daily Overhead Register'!$C$6:$C$838,"<"&DATE(2026,1,1),'Daily Overhead Register'!$D$6:$D$838,"Bad Debt / Claim Denials Write-off") -> 0 | O10: =SUM(C10:N10) -> 0
B11: Bank and Merchant Fees | C11: =SUMIFS('Daily Overhead Register'!$E$6:$E$838,'Daily Overhead Register'!$C$6:$C$838,">="&DATE(2025,1,1),'Daily Overhead Register'!$C$6:$C$838,"<"&DATE(2025,2,1),'Daily Overhead Register'!$D$6:$D$838,"Bank and Merchant Fees") -> 156.3 | D11: =SUMIFS('Daily Overhead Register'!$E$6:$E$838,'Daily Overhead Register'!$C$6:$C$838,">="&DATE(2025,2,1),'Daily Overhead Register'!$C$6:$C$838,"<"&DATE(2025,3,1),'Daily Overhead Register'!$D$6:$D$838,"Bank and Merchant Fees") -> 161.38 | E11: =SUMIFS('Daily Overhead Register'!$E$6:$E$838,'Daily Overhead Register'!$C$6:$C$838,">="&DATE(2025,3,1),'Daily Overhead Register'!$C$6:$C$838,"<"&DATE(2025,4,1),'Daily Overhead Register'!$D$6:$D$838,"Bank and Merchant Fees") -> 142.86 | F11: =SUMIFS('Daily Overhead Register'!$E$6:$E$838,'Daily Overhead Register'!$C$6:$C$838,">="&DATE(2025,4,1),'Daily Overhead Register'!$C$6:$C$838,"<"&DATE(2025,5,1),'Daily Overhead Register'!$D$6:$D$838,"Bank and Merchant Fees") -> 159.81 | G11: =SUMIFS('Daily Overhead Register'!$E$6:$E$838,'Daily Overhead Register'!$C$6:$C$838,">="&DATE(2025,5,1),'Daily Overhead Register'!$C$6:$C$838,"<"&DATE(2025,6,1),'Daily Overhead Register'!$D$6:$D$838,"Bank and Merchant Fees") -> 152.57 | H11: =SUMIFS('Daily Overhead Register'!$E$6:$E$838,'Daily Overhead Register'!$C$6:$C$838,">="&DATE(2025,6,1),'Daily Overhead Register'!$C$6:$C$838,"<"&DATE(2025,7,1),'Daily Overhead Register'!$D$6:$D$838,"Bank and Merchant Fees") -> 149.04 | I11: =SUMIFS('Daily Overhead Register'!$E$6:$E$838,'Daily Overhead Register'!$C$6:$C$838,">="&DATE(2025,7,1),'Daily Overhead Register'!$C$6:$C$838,"<"&DATE(2025,8,1),'Daily Overhead Register'!$D$6:$D$838,"Bank and Merchant Fees") -> 161.08 | J11: =SUMIFS('Daily Overhead Register'!$E$6:$E$838,'Daily Overhead Register'!$C$6:$C$838,">="&DATE(2025,8,1),'Daily Overhead Register'!$C$6:$C$838,"<"&DATE(2025,9,1),'Daily Overhead Register'!$D$6:$D$838,"Bank and Merchant Fees") -> 151.77 | K11: =SUMIFS('Daily Overhead Register'!$E$6:$E$838,'Daily Overhead Register'!$C$6:$C$838,">="&DATE(2025,9,1),'Daily Overhead Register'!$C$6:$C$838,"<"&DATE(2025,10,1),'Daily Overhead Register'!$D$6:$D$838,"Bank and Merchant Fees") -> 142.78 | L11: =SUMIFS('Daily Overhead Register'!$E$6:$E$838,'Daily Overhead Register'!$C$6:$C$838,">="&DATE(2025,10,1),'Daily Overhead Register'!$C$6:$C$838,"<"&DATE(2025,11,1),'Daily Overhead Register'!$D$6:$D$838,"Bank and Merchant Fees") -> 149.08 | M11: =SUMIFS('Daily Overhead Register'!$E$6:$E$838,'Daily Overhead Register'!$C$6:$C$838,">="&DATE(2025,11,1),'Daily Overhead Register'!$C$6:$C$838,"<"&DATE(2025,12,1),'Daily Overhead Register'!$D$6:$D$838,"Bank and Merchant Fees") -> 155.09 | N11: =SUMIFS('Daily Overhead Register'!$E$6:$E$838,'Daily Overhead Register'!$C$6:$C$838,">="&DATE(2025,12,1),'Daily Overhead Register'!$C$6:$C$838,"<"&DATE(2026,1,1),'Daily Overhead Register'!$D$6:$D$838,"Bank and Merchant Fees") -> 153.62 | O11: =SUM(C11:N11) -> 1835.38
B12: Continuing Education / Training | C12: =SUMIFS('Daily Overhead Register'!$E$6:$E$838,'Daily Overhead Register'!$C$6:$C$838,">="&DATE(2025,1,1),'Daily Overhead Register'!$C$6:$C$838,"<"&DATE(2025,2,1),'Daily Overhead Register'!$D$6:$D$838,"Continuing Education / Training") -> 188.68 | D12: =SUMIFS('Daily Overhead Register'!$E$6:$E$838,'Daily Overhead Register'!$C$6:$C$838,">="&DATE(2025,2,1),'Daily Overhead Register'!$C$6:$C$838,"<"&DATE(2025,3,1),'Daily Overhead Register'!$D$6:$D$838,"Continuing Education / Training") -> 185.27 | E12: =SUMIFS('Daily Overhead Register'!$E$6:$E$838,'Daily Overhead Register'!$C$6:$C$838,">="&DATE(2025,3,1),'Daily Overhead Register'!$C$6:$C$838,"<"&DATE(2025,4,1),'Daily Overhead Register'!$D$6:$D$838,"Continuing Education / Training") -> 187.13 | F12: =SUMIFS('Daily Overhead Register'!$E$6:$E$838,'Daily Overhead Register'!$C$6:$C$838,">="&DATE(2025,4,1),'Daily Overhead Register'!$C$6:$C$838,"<"&DATE(2025,5,1),'Daily Overhead Register'!$D$6:$D$838,"Continuing Education / Training") -> 173.46 | G12: =SUMIFS('Daily Overhead Register'!$E$6:$E$838,'Daily Overhead Register'!$C$6:$C$838,">="&DATE(2025,5,1),'Daily Overhead Register'!$C$6:$C$838,"<"&DATE(2025,6,1),'Daily Overhead Register'!$D$6:$D$838,"Continuing Education / Training") -> 190.72 | H12: =SUMIFS('Daily Overhead Register'!$E$6:$E$838,'Daily Overhead Register'!$C$6:$C$838,">="&DATE(2025,6,1),'Daily Overhead Register'!$C$6:$C$838,"<"&DATE(2025,7,1),'Daily Overhead Register'!$D$6:$D$838,"Continuing Education / Training") -> 191.55 | I12: =SUMIFS('Daily Overhead Register'!$E$6:$E$838,'Daily Overhead Register'!$C$6:$C$838,">="&DATE(2025,7,1),'Daily Overhead Register'!$C$6:$C$838,"<"&DATE(2025,8,1),'Daily Overhead Register'!$D$6:$D$838,"Continuing Education / Training") -> 177.14 | J12: =SUMIFS('Daily Overhead Register'!$E$6:$E$838,'Daily Overhead Register'!$C$6:$C$838,">="&DATE(2025,8,1),'Daily Overhead Register'!$C$6:$C$838,"<"&DATE(2025,9,1),'Daily Overhead Register'!$D$6:$D$838,"Continuing Education / Training") -> 189.47 | K12: =SUMIFS('Daily Overhead Register'!$E$6:$E$838,'Daily Overhead Register'!$C$6:$C$838,">="&DATE(2025,9,1),'Daily Overhead Register'!$C$6:$C$838,"<"&DATE(2025,10,1),'Daily Overhead Register'!$D$6:$D$838,"Continuing Education / Training") -> 191.39 | L12: =SUMIFS('Daily Overhead Register'!$E$6:$E$838,'Daily Overhead Register'!$C$6:$C$838,">="&DATE(2025,10,1),'Daily Overhead Register'!$C$6:$C$838,"<"&DATE(2025,11,1),'Daily Overhead Register'!$D$6:$D$838,"Continuing Education / Training") -> 179.86 | M12: =SUMIFS('Daily Overhead Register'!$E$6:$E$838,'Daily Overhead Register'!$C$6:$C$838,">="&DATE(2025,11,1),'Daily Overhead Register'!$C$6:$C$838,"<"&DATE(2025,12,1),'Daily Overhead Register'!$D$6:$D$838,"Continuing Education / Training") -> 178.06 | N12: =SUMIFS('Daily Overhead Register'!$E$6:$E$838,'Daily Overhead Register'!$C$6:$C$838,">="&DATE(2025,12,1),'Daily Overhead Register'!$C$6:$C$838,"<"&DATE(2026,1,1),'Daily Overhead Register'!$D$6:$D$838,"Continuing Education / Training") -> 190.26 | O12: =SUM(C12:N12) -> 2222.99
B13: Depreciation Expense | C13: =SUMIFS('Daily Overhead Register'!$E$6:$E$838,'Daily Overhead Register'!$C$6:$C$838,">="&DATE(2025,1,1),'Daily Overhead Register'!$C$6:$C$838,"<"&DATE(2025,2,1),'Daily Overhead Register'!$D$6:$D$838,"Depreciation Expense") -> 1123.42 | D13: =SUMIFS('Daily Overhead Register'!$E$6:$E$838,'Daily Overhead Register'!$C$6:$C$838,">="&DATE(2025,2,1),'Daily Overhead Register'!$C$6:$C$838,"<"&DATE(2025,3,1),'Daily Overhead Register'!$D$6:$D$838,"Depreciation Expense") -> 1201.2 | E13: =SUMIFS('Daily Overhead Register'!$E$6:$E$838,'Daily Overhead Register'!$C$6:$C$838,">="&DATE(2025,3,1),'Daily Overhead Register'!$C$6:$C$838,"<"&DATE(2025,4,1),'Daily Overhead Register'!$D$6:$D$838,"Depreciation Expense") -> 1301.2 | F13: =SUMIFS('Daily Overhead Register'!$E$6:$E$838,'Daily Overhead Register'!$C$6:$C$838,">="&DATE(2025,4,1),'Daily Overhead Register'!$C$6:$C$838,"<"&DATE(2025,5,1),'Daily Overhead Register'!$D$6:$D$838,"Depreciation Expense") -> 1332.03 | G13: =SUMIFS('Daily Overhead Register'!$E$6:$E$838,'Daily Overhead Register'!$C$6:$C$838,">="&DATE(2025,5,1),'Daily Overhead Register'!$C$6:$C$838,"<"&DATE(2025,6,1),'Daily Overhead Register'!$D$6:$D$838,"Depreciation Expense") -> 1382.03 | H13: =SUMIFS('Daily Overhead Register'!$E$6:$E$838,'Daily Overhead Register'!$C$6:$C$838,">="&DATE(2025,6,1),'Daily Overhead Register'!$C$6:$C$838,"<"&DATE(2025,7,1),'Daily Overhead Register'!$D$6:$D$838,"Depreciation Expense") -> 1382.03 | I13: =SUMIFS('Daily Overhead Register'!$E$6:$E$838,'Daily Overhead Register'!$C$6:$C$838,">="&DATE(2025,7,1),'Daily Overhead Register'!$C$6:$C$838,"<"&DATE(2025,8,1),'Daily Overhead Register'!$D$6:$D$838,"Depreciation Expense") -> 1382.03 | J13: =SUMIFS('Daily Overhead Register'!$E$6:$E$838,'Daily Overhead Register'!$C$6:$C$838,">="&DATE(2025,8,1),'Daily Overhead Register'!$C$6:$C$838,"<"&DATE(2025,9,1),'Daily Overhead Register'!$D$6:$D$838,"Depreciation Expense") -> 1765.36 | K13: =SUMIFS('Daily Overhead Register'!$E$6:$E$838,'Daily Overhead Register'!$C$6:$C$838,">="&DATE(2025,9,1),'Daily Overhead Register'!$C$6:$C$838,"<"&DATE(2025,10,1),'Daily Overhead Register'!$D$6:$D$838,"Depreciation Expense") -> 1765.36 | L13: =SUMIFS('Daily Overhead Register'!$E$6:$E$838,'Daily Overhead Register'!$C$6:$C$838,">="&DATE(2025,10,1),'Daily Overhead Register'!$C$6:$C$838,"<"&DATE(2025,11,1),'Daily Overhead Register'!$D$6:$D$838,"Depreciation Expense") -> 2065.36 | M13: =SUMIFS('Daily Overhead Register'!$E$6:$E$838,'Daily Overhead Register'!$C$6:$C$838,">="&DATE(2025,11,1),'Daily Overhead Register'!$C$6:$C$838,"<"&DATE(2025,12,1),'Daily Overhead Register'!$D$6:$D$838,"Depreciation Expense") -> 2065.36 | N13: =SUMIFS('Daily Overhead Register'!$E$6:$E$838,'Daily Overhead Register'!$C$6:$C$838,">="&DATE(2025,12,1),'Daily Overhead Register'!$C$6:$C$838,"<"&DATE(2026,1,1),'Daily Overhead Register'!$D$6:$D$838,"Depreciation Expense") -> 2065.36 | O13: =SUM(C13:N13) -> 18830.74
B14: Insurance - Bonding | C14: =SUMIFS('Daily Overhead Register'!$E$6:$E$838,'Daily Overhead Register'!$C$6:$C$838,">="&DATE(2025,1,1),'Daily Overhead Register'!$C$6:$C$838,"<"&DATE(2025,2,1),'Daily Overhead Register'!$D$6:$D$838,"Insurance - Bonding") -> 137.55 | D14: =SUMIFS('Daily Overhead Register'!$E$6:$E$838,'Daily Overhead Register'!$C$6:$C$838,">="&DATE(2025,2,1),'Daily Overhead Register'!$C$6:$C$838,"<"&DATE(2025,3,1),'Daily Overhead Register'!$D$6:$D$838,"Insurance - Bonding") -> 143.31 | E14: =SUMIFS('Daily Overhead Register'!$E$6:$E$838,'Daily Overhead Register'!$C$6:$C$838,">="&DATE(2025,3,1),'Daily Overhead Register'!$C$6:$C$838,"<"&DATE(2025,4,1),'Daily Overhead Register'!$D$6:$D$838,"Insurance - Bonding") -> 154.85 | F14: =SUMIFS('Daily Overhead Register'!$E$6:$E$838,'Daily Overhead Register'!$C$6:$C$838,">="&DATE(2025,4,1),'Daily Overhead Register'!$C$6:$C$838,"<"&DATE(2025,5,1),'Daily Overhead Register'!$D$6:$D$838,"Insurance - Bonding") -> 148.04 | G14: =SUMIFS('Daily Overhead Register'!$E$6:$E$838,'Daily Overhead Register'!$C$6:$C$838,">="&DATE(2025,5,1),'Daily Overhead Register'!$C$6:$C$838,"<"&DATE(2025,6,1),'Daily Overhead Register'!$D$6:$D$838,"Insurance - Bonding") -> 149.9 | H14: =SUMIFS('Daily Overhead Register'!$E$6:$E$838,'Daily Overhead Register'!$C$6:$C$838,">="&DATE(2025,6,1),'Daily Overhead Register'!$C$6:$C$838,"<"&DATE(2025,7,1),'Daily Overhead Register'!$D$6:$D$838,"Insurance - Bonding") -> 146.7 | I14: =SUMIFS('Daily Overhead Register'!$E$6:$E$838,'Daily Overhead Register'!$C$6:$C$838,">="&DATE(2025,7,1),'Daily Overhead Register'!$C$6:$C$838,"<"&DATE(2025,8,1),'Daily Overhead Register'!$D$6:$D$838,"Insurance - Bonding") -> 140.63 | J14: =SUMIFS('Daily Overhead Register'!$E$6:$E$838,'Daily Overhead Register'!$C$6:$C$838,">="&DATE(2025,8,1),'Daily Overhead Register'!$C$6:$C$838,"<"&DATE(2025,9,1),'Daily Overhead Register'!$D$6:$D$838,"Insurance - Bonding") -> 154.52 | K14: =SUMIFS('Daily Overhead Register'!$E$6:$E$838,'Daily Overhead Register'!$C$6:$C$838,">="&DATE(2025,9,1),'Daily Overhead Register'!$C$6:$C$838,"<"&DATE(2025,10,1),'Daily Overhead Register'!$D$6:$D$838,"Insurance - Bonding") -> 153.34 | L14: =SUMIFS('Daily Overhead Register'!$E$6:$E$838,'Daily Overhead Register'!$C$6:$C$838,">="&DATE(2025,10,1),'Daily Overhead Register'!$C$6:$C$838,"<"&DATE(2025,11,1),'Daily Overhead Register'!$D$6:$D$838,"Insurance - Bonding") -> 143.69 | M14: =SUMIFS('Daily Overhead Register'!$E$6:$E$838,'Daily Overhead Register'!$C$6:$C$838,">="&DATE(2025,11,1),'Daily Overhead Register'!$C$6:$C$838,"<"&DATE(2025,12,1),'Daily Overhead Register'!$D$6:$D$838,"Insurance - Bonding") -> 149.19 | N14: =SUMIFS('Daily Overhead Register'!$E$6:$E$838,'Daily Overhead Register'!$C$6:$C$838,">="&DATE(2025,12,1),'Daily Overhead Register'!$C$6:$C$838,"<"&DATE(2026,1,1),'Daily Overhead Register'!$D$6:$D$838,"Insurance - Bonding") -> 146.36 | O14: =SUM(C14:N14) -> 1768.08
B15: Insurance - General Liability (Monthly Amortization) | C15: =SUMIFS('Daily Overhead Register'!$E$6:$E$838,'Daily Overhead Register'!$C$6:$C$838,">="&DATE(2025,1,1),'Daily Overhead Register'!$C$6:$C$838,"<"&DATE(2025,2,1),'Daily Overhead Register'!$D$6:$D$838,"Insurance - General Liability (Monthly Amortization)") -> 950 | D15: =SUMIFS('Daily Overhead Register'!$E$6:$E$838,'Daily Overhead Register'!$C$6:$C$838,">="&DATE(2025,2,1),'Daily Overhead Register'!$C$6:$C$838,"<"&DATE(2025,3,1),'Daily Overhead Register'!$D$6:$D$838,"Insurance - General Liability (Monthly Amortization)") -> 950 | E15: =SUMIFS('Daily Overhead Register'!$E$6:$E$838,'Daily Overhead Register'!$C$6:$C$838,">="&DATE(2025,3,1),'Daily Overhead Register'!$C$6:$C$838,"<"&DATE(2025,4,1),'Daily Overhead Register'!$D$6:$D$838,"Insurance - General Liability (Monthly Amortization)") -> 950 | F15: =SUMIFS('Daily Overhead Register'!$E$6:$E$838,'Daily Overhead Register'!$C$6:$C$838,">="&DATE(2025,4,1),'Daily Overhead Register'!$C$6:$C$838,"<"&DATE(2025,5,1),'Daily Overhead Register'!$D$6:$D$838,"Insurance - General Liability (Monthly Amortization)") -> 950 | G15: =SUMIFS('Daily Overhead Register'!$E$6:$E$838,'Daily Overhead Register'!$C$6:$C$838,">="&DATE(2025,5,1),'Daily Overhead Register'!$C$6:$C$838,"<"&DATE(2025,6,1),'Daily Overhead Register'!$D$6:$D$838,"Insurance - General Liability (Monthly Amortization)") -> 950 | H15: =SUMIFS('Daily Overhead Register'!$E$6:$E$838,'Daily Overhead Register'!$C$6:$C$838,">="&DATE(2025,6,1),'Daily Overhead Register'!$C$6:$C$838,"<"&DATE(2025,7,1),'Daily Overhead Register'!$D$6:$D$838,"Insurance - General Liability (Monthly Amortization)") -> 950 | I15: =SUMIFS('Daily Overhead Register'!$E$6:$E$838,'Daily Overhead Register'!$C$6:$C$838,">="&DATE(2025,7,1),'Daily Overhead Register'!$C$6:$C$838,"<"&DATE(2025,8,1),'Daily Overhead Register'!$D$6:$D$838,"Insurance - General Liability (Monthly Amortization)") -> 950 | J15: =SUMIFS('Daily Overhead Register'!$E$6:$E$838,'Daily Overhead Register'!$C$6:$C$838,">="&DATE(2025,8,1),'Daily Overhead Register'!$C$6:$C$838,"<"&DATE(2025,9,1),'Daily Overhead Register'!$D$6:$D$838,"Insurance - General Liability (Monthly Amortization)") -> 950 | K15: =SUMIFS('Daily Overhead Register'!$E$6:$E$838,'Daily Overhead Register'!$C$6:$C$838,">="&DATE(2025,9,1),'Daily Overhead Register'!$C$6:$C$838,"<"&DATE(2025,10,1),'Daily Overhead Register'!$D$6:$D$838,"Insurance - General Liability (Monthly Amortization)") -> 950 | L15: =SUMIFS('Daily Overhead Register'!$E$6:$E$838,'Daily Overhead Register'!$C$6:$C$838,">="&DATE(2025,10,1),'Daily Overhead Register'!$C$6:$C$838,"<"&DATE(2025,11,1),'Daily Overhead Register'!$D$6:$D$838,"Insurance - General Liability (Monthly Amortization)") -> 950 | M15: =SUMIFS('Daily Overhead Register'!$E$6:$E$838,'Daily Overhead Register'!$C$6:$C$838,">="&DATE(2025,11,1),'Daily Overhead Register'!$C$6:$C$838,"<"&DATE(2025,12,1),'Daily Overhead Register'!$D$6:$D$838,"Insurance - General Liability (Monthly Amortization)") -> 950 | N15: =SUMIFS('Daily Overhead Register'!$E$6:$E$838,'Daily Overhead Register'!$C$6:$C$838,">="&DATE(2025,12,1),'Daily Overhead Register'!$C$6:$C$838,"<"&DATE(2026,1,1),'Daily Overhead Register'!$D$6:$D$838,"Insurance - General Liability (Monthly Amortization)") -> 950 | O15: =SUM(C15:N15) -> 11400
B16: Insurance - Professional Liability/Malpractice | C16: =SUMIFS('Daily Overhead Register'!$E$6:$E$838,'Daily Overhead Register'!$C$6:$C$838,">="&DATE(2025,1,1),'Daily Overhead Register'!$C$6:$C$838,"<"&DATE(2025,2,1),'Daily Overhead Register'!$D$6:$D$838,"Insurance - Professional Liability/Malpractice") -> 367.13 | D16: =SUMIFS('Daily Overhead Register'!$E$6:$E$838,'Daily Overhead Register'!$C$6:$C$838,">="&DATE(2025,2,1),'Daily Overhead Register'!$C$6:$C$838,"<"&DATE(2025,3,1),'Daily Overhead Register'!$D$6:$D$838,"Insurance - Professional Liability/Malpractice") -> 363.13 | E16: =SUMIFS('Daily Overhead Register'!$E$6:$E$838,'Daily Overhead Register'!$C$6:$C$838,">="&DATE(2025,3,1),'Daily Overhead Register'!$C$6:$C$838,"<"&DATE(2025,4,1),'Daily Overhead Register'!$D$6:$D$838,"Insurance - Professional Liability/Malpractice") -> 383.79 | F16: =SUMIFS('Daily Overhead Register'!$E$6:$E$838,'Daily Overhead Register'!$C$6:$C$838,">="&DATE(2025,4,1),'Daily Overhead Register'!$C$6:$C$838,"<"&DATE(2025,5,1),'Daily Overhead Register'!$D$6:$D$838,"Insurance - Professional Liability/Malpractice") -> 394.46 | G16: =SUMIFS('Daily Overhead Register'!$E$6:$E$838,'Daily Overhead Register'!$C$6:$C$838,">="&DATE(2025,5,1),'Daily Overhead Register'!$C$6:$C$838,"<"&DATE(2025,6,1),'Daily Overhead Register'!$D$6:$D$838,"Insurance - Professional Liability/Malpractice") -> 400.85 | H16: =SUMIFS('Daily Overhead Register'!$E$6:$E$838,'Daily Overhead Register'!$C$6:$C$838,">="&DATE(2025,6,1),'Daily Overhead Register'!$C$6:$C$838,"<"&DATE(2025,7,1),'Daily Overhead Register'!$D$6:$D$838,"Insurance - Professional Liability/Malpractice") -> 396.07 | I16: =SUMIFS('Daily Overhead Register'!$E$6:$E$838,'Daily Overhead Register'!$C$6:$C$838,">="&DATE(2025,7,1),'Daily Overhead Register'!$C$6:$C$838,"<"&DATE(2025,8,1),'Daily Overhead Register'!$D$6:$D$838,"Insurance - Professional Liability/Malpractice") -> 410.3 | J16: =SUMIFS('Daily Overhead Register'!$E$6:$E$838,'Daily Overhead Register'!$C$6:$C$838,">="&DATE(2025,8,1),'Daily Overhead Register'!$C$6:$C$838,"<"&DATE(2025,9,1),'Daily Overhead Register'!$D$6:$D$838,"Insurance - Professional Liability/Malpractice") -> 395.01 | K16: =SUMIFS('Daily Overhead Register'!$E$6:$E$838,'Daily Overhead Register'!$C$6:$C$838,">="&DATE(2025,9,1),'Daily Overhead Register'!$C$6:$C$838,"<"&DATE(2025,10,1),'Daily Overhead Register'!$D$6:$D$838,"Insurance - Professional Liability/Malpractice") -> 387.78 | L16: =SUMIFS('Daily Overhead Register'!$E$6:$E$838,'Daily Overhead Register'!$C$6:$C$838,">="&DATE(2025,10,1),'Daily Overhead Register'!$C$6:$C$838,"<"&DATE(2025,11,1),'Daily Overhead Register'!$D$6:$D$838,"Insurance - Professional Liability/Malpractice") -> 404.58 | M16: =SUMIFS('Daily Overhead Register'!$E$6:$E$838,'Daily Overhead Register'!$C$6:$C$838,">="&DATE(2025,11,1),'Daily Overhead Register'!$C$6:$C$838,"<"&DATE(2025,12,1),'Daily Overhead Register'!$D$6:$D$838,"Insurance - Professional Liability/Malpractice") -> 377.86 | N16: =SUMIFS('Daily Overhead Register'!$E$6:$E$838,'Daily Overhead Register'!$C$6:$C$838,">="&DATE(2025,12,1),'Daily Overhead Register'!$C$6:$C$838,"<"&DATE(2026,1,1),'Daily Overhead Register'!$D$6:$D$838,"Insurance - Professional Liability/Malpractice") -> 406.78 | O16: =SUM(C16:N16) -> 4687.74
B17: Legal and Professional Fees | C17: =SUMIFS('Daily Overhead Register'!$E$6:$E$838,'Daily Overhead Register'!$C$6:$C$838,">="&DATE(2025,1,1),'Daily Overhead Register'!$C$6:$C$838,"<"&DATE(2025,2,1),'Daily Overhead Register'!$D$6:$D$838,"Legal and Professional Fees") -> 485.58 | D17: =SUMIFS('Daily Overhead Register'!$E$6:$E$838,'Daily Overhead Register'!$C$6:$C$838,">="&DATE(2025,2,1),'Daily Overhead Register'!$C$6:$C$838,"<"&DATE(2025,3,1),'Daily Overhead Register'!$D$6:$D$838,"Legal and Professional Fees") -> 427.63 | E17: =SUMIFS('Daily Overhead Register'!$E$6:$E$838,'Daily Overhead Register'!$C$6:$C$838,">="&DATE(2025,3,1),'Daily Overhead Register'!$C$6:$C$838,"<"&DATE(2025,4,1),'Daily Overhead Register'!$D$6:$D$838,"Legal and Professional Fees") -> 453.21 | F17: =SUMIFS('Daily Overhead Register'!$E$6:$E$838,'Daily Overhead Register'!$C$6:$C$838,">="&DATE(2025,4,1),'Daily Overhead Register'!$C$6:$C$838,"<"&DATE(2025,5,1),'Daily Overhead Register'!$D$6:$D$838,"Legal and Professional Fees") -> 458.9 | G17: =SUMIFS('Daily Overhead Register'!$E$6:$E$838,'Daily Overhead Register'!$C$6:$C$838,">="&DATE(2025,5,1),'Daily Overhead Register'!$C$6:$C$838,"<"&DATE(2025,6,1),'Daily Overhead Register'!$D$6:$D$838,"Legal and Professional Fees") -> 423.83 | H17: =SUMIFS('Daily Overhead Register'!$E$6:$E$838,'Daily Overhead Register'!$C$6:$C$838,">="&DATE(2025,6,1),'Daily Overhead Register'!$C$6:$C$838,"<"&DATE(2025,7,1),'Daily Overhead Register'!$D$6:$D$838,"Legal and Professional Fees") -> 451.01 | I17: =SUMIFS('Daily Overhead Register'!$E$6:$E$838,'Daily Overhead Register'!$C$6:$C$838,">="&DATE(2025,7,1),'Daily Overhead Register'!$C$6:$C$838,"<"&DATE(2025,8,1),'Daily Overhead Register'!$D$6:$D$838,"Legal and Professional Fees") -> 469.65 | J17: =SUMIFS('Daily Overhead Register'!$E$6:$E$838,'Daily Overhead Register'!$C$6:$C$838,">="&DATE(2025,8,1),'Daily Overhead Register'!$C$6:$C$838,"<"&DATE(2025,9,1),'Daily Overhead Register'!$D$6:$D$838,"Legal and Professional Fees") -> 423.78 | K17: =SUMIFS('Daily Overhead Register'!$E$6:$E$838,'Daily Overhead Register'!$C$6:$C$838,">="&DATE(2025,9,1),'Daily Overhead Register'!$C$6:$C$838,"<"&DATE(2025,10,1),'Daily Overhead Register'!$D$6:$D$838,"Legal and Professional Fees") -> 450.73 | L17: =SUMIFS('Daily Overhead Register'!$E$6:$E$838,'Daily Overhead Register'!$C$6:$C$838,">="&DATE(2025,10,1),'Daily Overhead Register'!$C$6:$C$838,"<"&DATE(2025,11,1),'Daily Overhead Register'!$D$6:$D$838,"Legal and Professional Fees") -> 431.85 | M17: =SUMIFS('Daily Overhead Register'!$E$6:$E$838,'Daily Overhead Register'!$C$6:$C$838,">="&DATE(2025,11,1),'Daily Overhead Register'!$C$6:$C$838,"<"&DATE(2025,12,1),'Daily Overhead Register'!$D$6:$D$838,"Legal and Professional Fees") -> 454.18 | N17: =SUMIFS('Daily Overhead Register'!$E$6:$E$838,'Daily Overhead Register'!$C$6:$C$838,">="&DATE(2025,12,1),'Daily Overhead Register'!$C$6:$C$838,"<"&DATE(2026,1,1),'Daily Overhead Register'!$D$6:$D$838,"Legal and Professional Fees") -> 478.45 | O17: =SUM(C17:N17) -> 5408.8
B18: Line of Credit Interest | C18: =SUMIFS('Daily Overhead Register'!$E$6:$E$838,'Daily Overhead Register'!$C$6:$C$838,">="&DATE(2025,1,1),'Daily Overhead Register'!$C$6:$C$838,"<"&DATE(2025,2,1),'Daily Overhead Register'!$D$6:$D$838,"Line of Credit Interest") -> 0 | D18: =SUMIFS('Daily Overhead Register'!$E$6:$E$838,'Daily Overhead Register'!$C$6:$C$838,">="&DATE(2025,2,1),'Daily Overhead Register'!$C$6:$C$838,"<"&DATE(2025,3,1),'Daily Overhead Register'!$D$6:$D$838,"Line of Credit Interest") -> 0 | E18: =SUMIFS('Daily Overhead Register'!$E$6:$E$838,'Daily Overhead Register'!$C$6:$C$838,">="&DATE(2025,3,1),'Daily Overhead Register'!$C$6:$C$838,"<"&DATE(2025,4,1),'Daily Overhead Register'!$D$6:$D$838,"Line of Credit Interest") -> 0 | F18: =SUMIFS('Daily Overhead Register'!$E$6:$E$838,'Daily Overhead Register'!$C$6:$C$838,">="&DATE(2025,4,1),'Daily Overhead Register'!$C$6:$C$838,"<"&DATE(2025,5,1),'Daily Overhead Register'!$D$6:$D$838,"Line of Credit Interest") -> 0 | G18: =SUMIFS('Daily Overhead Register'!$E$6:$E$838,'Daily Overhead Register'!$C$6:$C$838,">="&DATE(2025,5,1),'Daily Overhead Register'!$C$6:$C$838,"<"&DATE(2025,6,1),'Daily Overhead Register'!$D$6:$D$838,"Line of Credit Interest") -> 0 | H18: =SUMIFS('Daily Overhead Register'!$E$6:$E$838,'Daily Overhead Register'!$C$6:$C$838,">="&DATE(2025,6,1),'Daily Overhead Register'!$C$6:$C$838,"<"&DATE(2025,7,1),'Daily Overhead Register'!$D$6:$D$838,"Line of Credit Interest") -> 0 | I18: =SUMIFS('Daily Overhead Register'!$E$6:$E$838,'Daily Overhead Register'!$C$6:$C$838,">="&DATE(2025,7,1),'Daily Overhead Register'!$C$6:$C$838,"<"&DATE(2025,8,1),'Daily Overhead Register'!$D$6:$D$838,"Line of Credit Interest") -> 0 | J18: =SUMIFS('Daily Overhead Register'!$E$6:$E$838,'Daily Overhead Register'!$C$6:$C$838,">="&DATE(2025,8,1),'Daily Overhead Register'!$C$6:$C$838,"<"&DATE(2025,9,1),'Daily Overhead Register'!$D$6:$D$838,"Line of Credit Interest") -> 0 | K18: =SUMIFS('Daily Overhead Register'!$E$6:$E$838,'Daily Overhead Register'!$C$6:$C$838,">="&DATE(2025,9,1),'Daily Overhead Register'!$C$6:$C$838,"<"&DATE(2025,10,1),'Daily Overhead Register'!$D$6:$D$838,"Line of Credit Interest") -> 0 | L18: =SUMIFS('Daily Overhead Register'!$E$6:$E$838,'Daily Overhead Register'!$C$6:$C$838,">="&DATE(2025,10,1),'Daily Overhead Register'!$C$6:$C$838,"<"&DATE(2025,11,1),'Daily Overhead Register'!$D$6:$D$838,"Line of Credit Interest") -> 0 | M18: =SUMIFS('Daily Overhead Register'!$E$6:$E$838,'Daily Overhead Register'!$C$6:$C$838,">="&DATE(2025,11,1),'Daily Overhead Register'!$C$6:$C$838,"<"&DATE(2025,12,1),'Daily Overhead Register'!$D$6:$D$838,"Line of Credit Interest") -> 0 | N18: =SUMIFS('Daily Overhead Register'!$E$6:$E$838,'Daily Overhead Register'!$C$6:$C$838,">="&DATE(2025,12,1),'Daily Overhead Register'!$C$6:$C$838,"<"&DATE(2026,1,1),'Daily Overhead Register'!$D$6:$D$838,"Line of Credit Interest") -> 0 | O18: =SUM(C18:N18) -> 0
B19: Marketing - Digital Ads | C19: =SUMIFS('Daily Overhead Register'!$E$6:$E$838,'Daily Overhead Register'!$C$6:$C$838,">="&DATE(2025,1,1),'Daily Overhead Register'!$C$6:$C$838,"<"&DATE(2025,2,1),'Daily Overhead Register'!$D$6:$D$838,"Marketing - Digital Ads") -> 368.87 | D19: =SUMIFS('Daily Overhead Register'!$E$6:$E$838,'Daily Overhead Register'!$C$6:$C$838,">="&DATE(2025,2,1),'Daily Overhead Register'!$C$6:$C$838,"<"&DATE(2025,3,1),'Daily Overhead Register'!$D$6:$D$838,"Marketing - Digital Ads") -> 359.5 | E19: =SUMIFS('Daily Overhead Register'!$E$6:$E$838,'Daily Overhead Register'!$C$6:$C$838,">="&DATE(2025,3,1),'Daily Overhead Register'!$C$6:$C$838,"<"&DATE(2025,4,1),'Daily Overhead Register'!$D$6:$D$838,"Marketing - Digital Ads") -> 335.55 | F19: =SUMIFS('Daily Overhead Register'!$E$6:$E$838,'Daily Overhead Register'!$C$6:$C$838,">="&DATE(2025,4,1),'Daily Overhead Register'!$C$6:$C$838,"<"&DATE(2025,5,1),'Daily Overhead Register'!$D$6:$D$838,"Marketing - Digital Ads") -> 329.98 | G19: =SUMIFS('Daily Overhead Register'!$E$6:$E$838,'Daily Overhead Register'!$C$6:$C$838,">="&DATE(2025,5,1),'Daily Overhead Register'!$C$6:$C$838,"<"&DATE(2025,6,1),'Daily Overhead Register'!$D$6:$D$838,"Marketing - Digital Ads") -> 352.8 | H19: =SUMIFS('Daily Overhead Register'!$E$6:$E$838,'Daily Overhead Register'!$C$6:$C$838,">="&DATE(2025,6,1),'Daily Overhead Register'!$C$6:$C$838,"<"&DATE(2025,7,1),'Daily Overhead Register'!$D$6:$D$838,"Marketing - Digital Ads") -> 329.82 | I19: =SUMIFS('Daily Overhead Register'!$E$6:$E$838,'Daily Overhead Register'!$C$6:$C$838,">="&DATE(2025,7,1),'Daily Overhead Register'!$C$6:$C$838,"<"&DATE(2025,8,1),'Daily Overhead Register'!$D$6:$D$838,"Marketing - Digital Ads") -> 350.01 | J19: =SUMIFS('Daily Overhead Register'!$E$6:$E$838,'Daily Overhead Register'!$C$6:$C$838,">="&DATE(2025,8,1),'Daily Overhead Register'!$C$6:$C$838,"<"&DATE(2025,9,1),'Daily Overhead Register'!$D$6:$D$838,"Marketing - Digital Ads") -> 344.6 | K19: =SUMIFS('Daily Overhead Register'!$E$6:$E$838,'Daily Overhead Register'!$C$6:$C$838,">="&DATE(2025,9,1),'Daily Overhead Register'!$C$6:$C$838,"<"&DATE(2025,10,1),'Daily Overhead Register'!$D$6:$D$838,"Marketing - Digital Ads") -> 329.11 | L19: =SUMIFS('Daily Overhead Register'!$E$6:$E$838,'Daily Overhead Register'!$C$6:$C$838,">="&DATE(2025,10,1),'Daily Overhead Register'!$C$6:$C$838,"<"&DATE(2025,11,1),'Daily Overhead Register'!$D$6:$D$838,"Marketing - Digital Ads") -> 359.63 | M19: =SUMIFS('Daily Overhead Register'!$E$6:$E$838,'Daily Overhead Register'!$C$6:$C$838,">="&DATE(2025,11,1),'Daily Overhead Register'!$C$6:$C$838,"<"&DATE(2025,12,1),'Daily Overhead Register'!$D$6:$D$838,"Marketing - Digital Ads") -> 341 | N19: =SUMIFS('Daily Overhead Register'!$E$6:$E$838,'Daily Overhead Register'!$C$6:$C$838,">="&DATE(2025,12,1),'Daily Overhead Register'!$C$6:$C$838,"<"&DATE(2026,1,1),'Daily Overhead Register'!$D$6:$D$838,"Marketing - Digital Ads") -> 334.8 | O19: =SUM(C19:N19) -> 4135.67
B20: Marketing - Referral Development/Events | C20: =SUMIFS('Daily Overhead Register'!$E$6:$E$838,'Daily Overhead Register'!$C$6:$C$838,">="&DATE(2025,1,1),'Daily Overhead Register'!$C$6:$C$838,"<"&DATE(2025,2,1),'Daily Overhead Register'!$D$6:$D$838,"Marketing - Referral Development/Events") -> 262.54 | D20: =SUMIFS('Daily Overhead Register'!$E$6:$E$838,'Daily Overhead Register'!$C$6:$C$838,">="&DATE(2025,2,1),'Daily Overhead Register'!$C$6:$C$838,"<"&DATE(2025,3,1),'Daily Overhead Register'!$D$6:$D$838,"Marketing - Referral Development/Events") -> 246.49 | E20: =SUMIFS('Daily Overhead Register'!$E$6:$E$838,'Daily Overhead Register'!$C$6:$C$838,">="&DATE(2025,3,1),'Daily Overhead Register'!$C$6:$C$838,"<"&DATE(2025,4,1),'Daily Overhead Register'!$D$6:$D$838,"Marketing - Referral Development/Events") -> 236.79 | F20: =SUMIFS('Daily Overhead Register'!$E$6:$E$838,'Daily Overhead Register'!$C$6:$C$838,">="&DATE(2025,4,1),'Daily Overhead Register'!$C$6:$C$838,"<"&DATE(2025,5,1),'Daily Overhead Register'!$D$6:$D$838,"Marketing - Referral Development/Events") -> 245.74 | G20: =SUMIFS('Daily Overhead Register'!$E$6:$E$838,'Daily Overhead Register'!$C$6:$C$838,">="&DATE(2025,5,1),'Daily Overhead Register'!$C$6:$C$838,"<"&DATE(2025,6,1),'Daily Overhead Register'!$D$6:$D$838,"Marketing - Referral Development/Events") -> 251.01 | H20: =SUMIFS('Daily Overhead Register'!$E$6:$E$838,'Daily Overhead Register'!$C$6:$C$838,">="&DATE(2025,6,1),'Daily Overhead Register'!$C$6:$C$838,"<"&DATE(2025,7,1),'Daily Overhead Register'!$D$6:$D$838,"Marketing - Referral Development/Events") -> 254.12 | I20: =SUMIFS('Daily Overhead Register'!$E$6:$E$838,'Daily Overhead Register'!$C$6:$C$838,">="&DATE(2025,7,1),'Daily Overhead Register'!$C$6:$C$838,"<"&DATE(2025,8,1),'Daily Overhead Register'!$D$6:$D$838,"Marketing - Referral Development/Events") -> 241.85 | J20: =SUMIFS('Daily Overhead Register'!$E$6:$E$838,'Daily Overhead Register'!$C$6:$C$838,">="&DATE(2025,8,1),'Daily Overhead Register'!$C$6:$C$838,"<"&DATE(2025,9,1),'Daily Overhead Register'!$D$6:$D$838,"Marketing - Referral Development/Events") -> 259.61 | K20: =SUMIFS('Daily Overhead Register'!$E$6:$E$838,'Daily Overhead Register'!$C$6:$C$838,">="&DATE(2025,9,1),'Daily Overhead Register'!$C$6:$C$838,"<"&DATE(2025,10,1),'Daily Overhead Register'!$D$6:$D$838,"Marketing - Referral Development/Events") -> 259.54 | L20: =SUMIFS('Daily Overhead Register'!$E$6:$E$838,'Daily Overhead Register'!$C$6:$C$838,">="&DATE(2025,10,1),'Daily Overhead Register'!$C$6:$C$838,"<"&DATE(2025,11,1),'Daily Overhead Register'!$D$6:$D$838,"Marketing - Referral Development/Events") -> 237.47 | M20: =SUMIFS('Daily Overhead Register'!$E$6:$E$838,'Daily Overhead Register'!$C$6:$C$838,">="&DATE(2025,11,1),'Daily Overhead Register'!$C$6:$C$838,"<"&DATE(2025,12,1),'Daily Overhead Register'!$D$6:$D$838,"Marketing - Referral Development/Events") -> 242.16 | N20: =SUMIFS('Daily Overhead Register'!$E$6:$E$838,'Daily Overhead Register'!$C$6:$C$838,">="&DATE(2025,12,1),'Daily Overhead Register'!$C$6:$C$838,"<"&DATE(2026,1,1),'Daily Overhead Register'!$D$6:$D$838,"Marketing - Referral Development/Events") -> 266.46 | O20: =SUM(C20:N20) -> 3003.78
B21: Misc / Other Admin | C21: =SUMIFS('Daily Overhead Register'!$E$6:$E$838,'Daily Overhead Register'!$C$6:$C$838,">="&DATE(2025,1,1),'Daily Overhead Register'!$C$6:$C$838,"<"&DATE(2025,2,1),'Daily Overhead Register'!$D$6:$D$838,"Misc / Other Admin") -> 197.69 | D21: =SUMIFS('Daily Overhead Register'!$E$6:$E$838,'Daily Overhead Register'!$C$6:$C$838,">="&DATE(2025,2,1),'Daily Overhead Register'!$C$6:$C$838,"<"&DATE(2025,3,1),'Daily Overhead Register'!$D$6:$D$838,"Misc / Other Admin") -> 190.89 | E21: =SUMIFS('Daily Overhead Register'!$E$6:$E$838,'Daily Overhead Register'!$C$6:$C$838,">="&DATE(2025,3,1),'Daily Overhead Register'!$C$6:$C$838,"<"&DATE(2025,4,1),'Daily Overhead Register'!$D$6:$D$838,"Misc / Other Admin") -> 179.05 | F21: =SUMIFS('Daily Overhead Register'!$E$6:$E$838,'Daily Overhead Register'!$C$6:$C$838,">="&DATE(2025,4,1),'Daily Overhead Register'!$C$6:$C$838,"<"&DATE(2025,5,1),'Daily Overhead Register'!$D$6:$D$838,"Misc / Other Admin") -> 186.67 | G21: =SUMIFS('Daily Overhead Register'!$E$6:$E$838,'Daily Overhead Register'!$C$6:$C$838,">="&DATE(2025,5,1),'Daily Overhead Register'!$C$6:$C$838,"<"&DATE(2025,6,1),'Daily Overhead Register'!$D$6:$D$838,"Misc / Other Admin") -> 189.95 | H21: =SUMIFS('Daily Overhead Register'!$E$6:$E$838,'Daily Overhead Register'!$C$6:$C$838,">="&DATE(2025,6,1),'Daily Overhead Register'!$C$6:$C$838,"<"&DATE(2025,7,1),'Daily Overhead Register'!$D$6:$D$838,"Misc / Other Admin") -> 203.47 | I21: =SUMIFS('Daily Overhead Register'!$E$6:$E$838,'Daily Overhead Register'!$C$6:$C$838,">="&DATE(2025,7,1),'Daily Overhead Register'!$C$6:$C$838,"<"&DATE(2025,8,1),'Daily Overhead Register'!$D$6:$D$838,"Misc / Other Admin") -> 182.14 | J21: =SUMIFS('Daily Overhead Register'!$E$6:$E$838,'Daily Overhead Register'!$C$6:$C$838,">="&DATE(2025,8,1),'Daily Overhead Register'!$C$6:$C$838,"<"&DATE(2025,9,1),'Daily Overhead Register'!$D$6:$D$838,"Misc / Other Admin") -> 194.37 | K21: =SUMIFS('Daily Overhead Register'!$E$6:$E$838,'Daily Overhead Register'!$C$6:$C$838,">="&DATE(2025,9,1),'Daily Overhead Register'!$C$6:$C$838,"<"&DATE(2025,10,1),'Daily Overhead Register'!$D$6:$D$838,"Misc / Other Admin") -> 198.05 | L21: =SUMIFS('Daily Overhead Register'!$E$6:$E$838,'Daily Overhead Register'!$C$6:$C$838,">="&DATE(2025,10,1),'Daily Overhead Register'!$C$6:$C$838,"<"&DATE(2025,11,1),'Daily Overhead Register'!$D$6:$D$838,"Misc / Other Admin") -> 194.18 | M21: =SUMIFS('Daily Overhead Register'!$E$6:$E$838,'Daily Overhead Register'!$C$6:$C$838,">="&DATE(2025,11,1),'Daily Overhead Register'!$C$6:$C$838,"<"&DATE(2025,12,1),'Daily Overhead Register'!$D$6:$D$838,"Misc / Other Admin") -> 201.31 | N21: =SUMIFS('Daily Overhead Register'!$E$6:$E$838,'Daily Overhead Register'!$C$6:$C$838,">="&DATE(2025,12,1),'Daily Overhead Register'!$C$6:$C$838,"<"&DATE(2026,1,1),'Daily Overhead Register'!$D$6:$D$838,"Misc / Other Admin") -> 204.78 | O21: =SUM(C21:N21) -> 2322.55
B22: Office Rent | C22: =SUMIFS('Daily Overhead Register'!$E$6:$E$838,'Daily Overhead Register'!$C$6:$C$838,">="&DATE(2025,1,1),'Daily Overhead Register'!$C$6:$C$838,"<"&DATE(2025,2,1),'Daily Overhead Register'!$D$6:$D$838,"Office Rent") -> 2079.87 | D22: =SUMIFS('Daily Overhead Register'!$E$6:$E$838,'Daily Overhead Register'!$C$6:$C$838,">="&DATE(2025,2,1),'Daily Overhead Register'!$C$6:$C$838,"<"&DATE(2025,3,1),'Daily Overhead Register'!$D$6:$D$838,"Office Rent") -> 2314.54 | E22: =SUMIFS('Daily Overhead Register'!$E$6:$E$838,'Daily Overhead Register'!$C$6:$C$838,">="&DATE(2025,3,1),'Daily Overhead Register'!$C$6:$C$838,"<"&DATE(2025,4,1),'Daily Overhead Register'!$D$6:$D$838,"Office Rent") -> 2110.92 | F22: =SUMIFS('Daily Overhead Register'!$E$6:$E$838,'Daily Overhead Register'!$C$6:$C$838,">="&DATE(2025,4,1),'Daily Overhead Register'!$C$6:$C$838,"<"&DATE(2025,5,1),'Daily Overhead Register'!$D$6:$D$838,"Office Rent") -> 2102.6 | G22: =SUMIFS('Daily Overhead Register'!$E$6:$E$838,'Daily Overhead Register'!$C$6:$C$838,">="&DATE(2025,5,1),'Daily Overhead Register'!$C$6:$C$838,"<"&DATE(2025,6,1),'Daily Overhead Register'!$D$6:$D$838,"Office Rent") -> 2086.67 | H22: =SUMIFS('Daily Overhead Register'!$E$6:$E$838,'Daily Overhead Register'!$C$6:$C$838,">="&DATE(2025,6,1),'Daily Overhead Register'!$C$6:$C$838,"<"&DATE(2025,7,1),'Daily Overhead Register'!$D$6:$D$838,"Office Rent") -> 2076.62 | I22: =SUMIFS('Daily Overhead Register'!$E$6:$E$838,'Daily Overhead Register'!$C$6:$C$838,">="&DATE(2025,7,1),'Daily Overhead Register'!$C$6:$C$838,"<"&DATE(2025,8,1),'Daily Overhead Register'!$D$6:$D$838,"Office Rent") -> 2322.11 | J22: =SUMIFS('Daily Overhead Register'!$E$6:$E$838,'Daily Overhead Register'!$C$6:$C$838,">="&DATE(2025,8,1),'Daily Overhead Register'!$C$6:$C$838,"<"&DATE(2025,9,1),'Daily Overhead Register'!$D$6:$D$838,"Office Rent") -> 2077.41 | K22: =SUMIFS('Daily Overhead Register'!$E$6:$E$838,'Daily Overhead Register'!$C$6:$C$838,">="&DATE(2025,9,1),'Daily Overhead Register'!$C$6:$C$838,"<"&DATE(2025,10,1),'Daily Overhead Register'!$D$6:$D$838,"Office Rent") -> 2101.34 | L22: =SUMIFS('Daily Overhead Register'!$E$6:$E$838,'Daily Overhead Register'!$C$6:$C$838,">="&DATE(2025,10,1),'Daily Overhead Register'!$C$6:$C$838,"<"&DATE(2025,11,1),'Daily Overhead Register'!$D$6:$D$838,"Office Rent") -> 2109.47 | M22: =SUMIFS('Daily Overhead Register'!$E$6:$E$838,'Daily Overhead Register'!$C$6:$C$838,">="&DATE(2025,11,1),'Daily Overhead Register'!$C$6:$C$838,"<"&DATE(2025,12,1),'Daily Overhead Register'!$D$6:$D$838,"Office Rent") -> 2219.97 | N22: =SUMIFS('Daily Overhead Register'!$E$6:$E$838,'Daily Overhead Register'!$C$6:$C$838,">="&DATE(2025,12,1),'Daily Overhead Register'!$C$6:$C$838,"<"&DATE(2026,1,1),'Daily Overhead Register'!$D$6:$D$838,"Office Rent") -> 2247.68 | O22: =SUM(C22:N22) -> 25849.2
B23: Office Supplies | C23: =SUMIFS('Daily Overhead Register'!$E$6:$E$838,'Daily Overhead Register'!$C$6:$C$838,">="&DATE(2025,1,1),'Daily Overhead Register'!$C$6:$C$838,"<"&DATE(2025,2,1),'Daily Overhead Register'!$D$6:$D$838,"Office Supplies") -> 158.82 | D23: =SUMIFS('Daily Overhead Register'!$E$6:$E$838,'Daily Overhead Register'!$C$6:$C$838,">="&DATE(2025,2,1),'Daily Overhead Register'!$C$6:$C$838,"<"&DATE(2025,3,1),'Daily Overhead Register'!$D$6:$D$838,"Office Supplies") -> 145.97 | E23: =SUMIFS('Daily Overhead Register'!$E$6:$E$838,'Daily Overhead Register'!$C$6:$C$838,">="&DATE(2025,3,1),'Daily Overhead Register'!$C$6:$C$838,"<"&DATE(2025,4,1),'Daily Overhead Register'!$D$6:$D$838,"Office Supplies") -> 156.07 | F23: =SUMIFS('Daily Overhead Register'!$E$6:$E$838,'Daily Overhead Register'!$C$6:$C$838,">="&DATE(2025,4,1),'Daily Overhead Register'!$C$6:$C$838,"<"&DATE(2025,5,1),'Daily Overhead Register'!$D$6:$D$838,"Office Supplies") -> 146.69 | G23: =SUMIFS('Daily Overhead Register'!$E$6:$E$838,'Daily Overhead Register'!$C$6:$C$838,">="&DATE(2025,5,1),'Daily Overhead Register'!$C$6:$C$838,"<"&DATE(2025,6,1),'Daily Overhead Register'!$D$6:$D$838,"Office Supplies") -> 158.21 | H23: =SUMIFS('Daily Overhead Register'!$E$6:$E$838,'Daily Overhead Register'!$C$6:$C$838,">="&DATE(2025,6,1),'Daily Overhead Register'!$C$6:$C$838,"<"&DATE(2025,7,1),'Daily Overhead Register'!$D$6:$D$838,"Office Supplies") -> 141.96 | I23: =SUMIFS('Daily Overhead Register'!$E$6:$E$838,'Daily Overhead Register'!$C$6:$C$838,">="&DATE(2025,7,1),'Daily Overhead Register'!$C$6:$C$838,"<"&DATE(2025,8,1),'Daily Overhead Register'!$D$6:$D$838,"Office Supplies") -> 157.21 | J23: =SUMIFS('Daily Overhead Register'!$E$6:$E$838,'Daily Overhead Register'!$C$6:$C$838,">="&DATE(2025,8,1),'Daily Overhead Register'!$C$6:$C$838,"<"&DATE(2025,9,1),'Daily Overhead Register'!$D$6:$D$838,"Office Supplies") -> 158.61 | K23: =SUMIFS('Daily Overhead Register'!$E$6:$E$838,'Daily Overhead Register'!$C$6:$C$838,">="&DATE(2025,9,1),'Daily Overhead Register'!$C$6:$C$838,"<"&DATE(2025,10,1),'Daily Overhead Register'!$D$6:$D$838,"Office Supplies") -> 141.48 | L23: =SUMIFS('Daily Overhead Register'!$E$6:$E$838,'Daily Overhead Register'!$C$6:$C$838,">="&DATE(2025,10,1),'Daily Overhead Register'!$C$6:$C$838,"<"&DATE(2025,11,1),'Daily Overhead Register'!$D$6:$D$838,"Office Supplies") -> 159.44 | M23: =SUMIFS('Daily Overhead Register'!$E$6:$E$838,'Daily Overhead Register'!$C$6:$C$838,">="&DATE(2025,11,1),'Daily Overhead Register'!$C$6:$C$838,"<"&DATE(2025,12,1),'Daily Overhead Register'!$D$6:$D$838,"Office Supplies") -> 141.49 | N23: =SUMIFS('Daily Overhead Register'!$E$6:$E$838,'Daily Overhead Register'!$C$6:$C$838,">="&DATE(2025,12,1),'Daily Overhead Register'!$C$6:$C$838,"<"&DATE(2026,1,1),'Daily Overhead Register'!$D$6:$D$838,"Office Supplies") -> 141.39 | O23: =SUM(C23:N23) -> 1807.34
B24: Office Utilities - Electric | C24: =SUMIFS('Daily Overhead Register'!$E$6:$E$838,'Daily Overhead Register'!$C$6:$C$838,">="&DATE(2025,1,1),'Daily Overhead Register'!$C$6:$C$838,"<"&DATE(2025,2,1),'Daily Overhead Register'!$D$6:$D$838,"Office Utilities - Electric") -> 217.87 | D24: =SUMIFS('Daily Overhead Register'!$E$6:$E$838,'Daily Overhead Register'!$C$6:$C$838,">="&DATE(2025,2,1),'Daily Overhead Register'!$C$6:$C$838,"<"&DATE(2025,3,1),'Daily Overhead Register'!$D$6:$D$838,"Office Utilities - Electric") -> 209.1 | E24: =SUMIFS('Daily Overhead Register'!$E$6:$E$838,'Daily Overhead Register'!$C$6:$C$838,">="&DATE(2025,3,1),'Daily Overhead Register'!$C$6:$C$838,"<"&DATE(2025,4,1),'Daily Overhead Register'!$D$6:$D$838,"Office Utilities - Electric") -> 221.05 | F24: =SUMIFS('Daily Overhead Register'!$E$6:$E$838,'Daily Overhead Register'!$C$6:$C$838,">="&DATE(2025,4,1),'Daily Overhead Register'!$C$6:$C$838,"<"&DATE(2025,5,1),'Daily Overhead Register'!$D$6:$D$838,"Office Utilities - Electric") -> 210.45 | G24: =SUMIFS('Daily Overhead Register'!$E$6:$E$838,'Daily Overhead Register'!$C$6:$C$838,">="&DATE(2025,5,1),'Daily Overhead Register'!$C$6:$C$838,"<"&DATE(2025,6,1),'Daily Overhead Register'!$D$6:$D$838,"Office Utilities - Electric") -> 218.31 | H24: =SUMIFS('Daily Overhead Register'!$E$6:$E$838,'Daily Overhead Register'!$C$6:$C$838,">="&DATE(2025,6,1),'Daily Overhead Register'!$C$6:$C$838,"<"&DATE(2025,7,1),'Daily Overhead Register'!$D$6:$D$838,"Office Utilities - Electric") -> 200.23 | I24: =SUMIFS('Daily Overhead Register'!$E$6:$E$838,'Daily Overhead Register'!$C$6:$C$838,">="&DATE(2025,7,1),'Daily Overhead Register'!$C$6:$C$838,"<"&DATE(2025,8,1),'Daily Overhead Register'!$D$6:$D$838,"Office Utilities - Electric") -> 197.44 | J24: =SUMIFS('Daily Overhead Register'!$E$6:$E$838,'Daily Overhead Register'!$C$6:$C$838,">="&DATE(2025,8,1),'Daily Overhead Register'!$C$6:$C$838,"<"&DATE(2025,9,1),'Daily Overhead Register'!$D$6:$D$838,"Office Utilities - Electric") -> 210.52 | K24: =SUMIFS('Daily Overhead Register'!$E$6:$E$838,'Daily Overhead Register'!$C$6:$C$838,">="&DATE(2025,9,1),'Daily Overhead Register'!$C$6:$C$838,"<"&DATE(2025,10,1),'Daily Overhead Register'!$D$6:$D$838,"Office Utilities - Electric") -> 221.52 | L24: =SUMIFS('Daily Overhead Register'!$E$6:$E$838,'Daily Overhead Register'!$C$6:$C$838,">="&DATE(2025,10,1),'Daily Overhead Register'!$C$6:$C$838,"<"&DATE(2025,11,1),'Daily Overhead Register'!$D$6:$D$838,"Office Utilities - Electric") -> 221.14 | M24: =SUMIFS('Daily Overhead Register'!$E$6:$E$838,'Daily Overhead Register'!$C$6:$C$838,">="&DATE(2025,11,1),'Daily Overhead Register'!$C$6:$C$838,"<"&DATE(2025,12,1),'Daily Overhead Register'!$D$6:$D$838,"Office Utilities - Electric") -> 213.6 | N24: =SUMIFS('Daily Overhead Register'!$E$6:$E$838,'Daily Overhead Register'!$C$6:$C$838,">="&DATE(2025,12,1),'Daily Overhead Register'!$C$6:$C$838,"<"&DATE(2026,1,1),'Daily Overhead Register'!$D$6:$D$838,"Office Utilities - Electric") -> 202.99 | O24: =SUM(C24:N24) -> 2544.22
B25: Office Utilities - Gas/Heat | C25: =SUMIFS('Daily Overhead Register'!$E$6:$E$838,'Daily Overhead Register'!$C$6:$C$838,">="&DATE(2025,1,1),'Daily Overhead Register'!$C$6:$C$838,"<"&DATE(2025,2,1),'Daily Overhead Register'!$D$6:$D$838,"Office Utilities - Gas/Heat") -> 101.09 | D25: =SUMIFS('Daily Overhead Register'!$E$6:$E$838,'Daily Overhead Register'!$C$6:$C$838,">="&DATE(2025,2,1),'Daily Overhead Register'!$C$6:$C$838,"<"&DATE(2025,3,1),'Daily Overhead Register'!$D$6:$D$838,"Office Utilities - Gas/Heat") -> 92.25 | E25: =SUMIFS('Daily Overhead Register'!$E$6:$E$838,'Daily Overhead Register'!$C$6:$C$838,">="&DATE(2025,3,1),'Daily Overhead Register'!$C$6:$C$838,"<"&DATE(2025,4,1),'Daily Overhead Register'!$D$6:$D$838,"Office Utilities - Gas/Heat") -> 94.28 | F25: =SUMIFS('Daily Overhead Register'!$E$6:$E$838,'Daily Overhead Register'!$C$6:$C$838,">="&DATE(2025,4,1),'Daily Overhead Register'!$C$6:$C$838,"<"&DATE(2025,5,1),'Daily Overhead Register'!$D$6:$D$838,"Office Utilities - Gas/Heat") -> 94.51 | G25: =SUMIFS('Daily Overhead Register'!$E$6:$E$838,'Daily Overhead Register'!$C$6:$C$838,">="&DATE(2025,5,1),'Daily Overhead Register'!$C$6:$C$838,"<"&DATE(2025,6,1),'Daily Overhead Register'!$D$6:$D$838,"Office Utilities - Gas/Heat") -> 96.93 | H25: =SUMIFS('Daily Overhead Register'!$E$6:$E$838,'Daily Overhead Register'!$C$6:$C$838,">="&DATE(2025,6,1),'Daily Overhead Register'!$C$6:$C$838,"<"&DATE(2025,7,1),'Daily Overhead Register'!$D$6:$D$838,"Office Utilities - Gas/Heat") -> 100.04 | I25: =SUMIFS('Daily Overhead Register'!$E$6:$E$838,'Daily Overhead Register'!$C$6:$C$838,">="&DATE(2025,7,1),'Daily Overhead Register'!$C$6:$C$838,"<"&DATE(2025,8,1),'Daily Overhead Register'!$D$6:$D$838,"Office Utilities - Gas/Heat") -> 94.79 | J25: =SUMIFS('Daily Overhead Register'!$E$6:$E$838,'Daily Overhead Register'!$C$6:$C$838,">="&DATE(2025,8,1),'Daily Overhead Register'!$C$6:$C$838,"<"&DATE(2025,9,1),'Daily Overhead Register'!$D$6:$D$838,"Office Utilities - Gas/Heat") -> 89.57 | K25: =SUMIFS('Daily Overhead Register'!$E$6:$E$838,'Daily Overhead Register'!$C$6:$C$838,">="&DATE(2025,9,1),'Daily Overhead Register'!$C$6:$C$838,"<"&DATE(2025,10,1),'Daily Overhead Register'!$D$6:$D$838,"Office Utilities - Gas/Heat") -> 93.7 | L25: =SUMIFS('Daily Overhead Register'!$E$6:$E$838,'Daily Overhead Register'!$C$6:$C$838,">="&DATE(2025,10,1),'Daily Overhead Register'!$C$6:$C$838,"<"&DATE(2025,11,1),'Daily Overhead Register'!$D$6:$D$838,"Office Utilities - Gas/Heat") -> 95.68 | M25: =SUMIFS('Daily Overhead Register'!$E$6:$E$838,'Daily Overhead Register'!$C$6:$C$838,">="&DATE(2025,11,1),'Daily Overhead Register'!$C$6:$C$838,"<"&DATE(2025,12,1),'Daily Overhead Register'!$D$6:$D$838,"Office Utilities - Gas/Heat") -> 100.15 | N25: =SUMIFS('Daily Overhead Register'!$E$6:$E$838,'Daily Overhead Register'!$C$6:$C$838,">="&DATE(2025,12,1),'Daily Overhead Register'!$C$6:$C$838,"<"&DATE(2026,1,1),'Daily Overhead Register'!$D$6:$D$838,"Office Utilities - Gas/Heat") -> 90.05 | O25: =SUM(C25:N25) -> 1143.04
B26: Office Utilities - Water/Sewer | C26: =SUMIFS('Daily Overhead Register'!$E$6:$E$838,'Daily Overhead Register'!$C$6:$C$838,">="&DATE(2025,1,1),'Daily Overhead Register'!$C$6:$C$838,"<"&DATE(2025,2,1),'Daily Overhead Register'!$D$6:$D$838,"Office Utilities - Water/Sewer") -> 65.22 | D26: =SUMIFS('Daily Overhead Register'!$E$6:$E$838,'Daily Overhead Register'!$C$6:$C$838,">="&DATE(2025,2,1),'Daily Overhead Register'!$C$6:$C$838,"<"&DATE(2025,3,1),'Daily Overhead Register'!$D$6:$D$838,"Office Utilities - Water/Sewer") -> 68.63 | E26: =SUMIFS('Daily Overhead Register'!$E$6:$E$838,'Daily Overhead Register'!$C$6:$C$838,">="&DATE(2025,3,1),'Daily Overhead Register'!$C$6:$C$838,"<"&DATE(2025,4,1),'Daily Overhead Register'!$D$6:$D$838,"Office Utilities - Water/Sewer") -> 65.17 | F26: =SUMIFS('Daily Overhead Register'!$E$6:$E$838,'Daily Overhead Register'!$C$6:$C$838,">="&DATE(2025,4,1),'Daily Overhead Register'!$C$6:$C$838,"<"&DATE(2025,5,1),'Daily Overhead Register'!$D$6:$D$838,"Office Utilities - Water/Sewer") -> 65.87 | G26: =SUMIFS('Daily Overhead Register'!$E$6:$E$838,'Daily Overhead Register'!$C$6:$C$838,">="&DATE(2025,5,1),'Daily Overhead Register'!$C$6:$C$838,"<"&DATE(2025,6,1),'Daily Overhead Register'!$D$6:$D$838,"Office Utilities - Water/Sewer") -> 62.44 | H26: =SUMIFS('Daily Overhead Register'!$E$6:$E$838,'Daily Overhead Register'!$C$6:$C$838,">="&DATE(2025,6,1),'Daily Overhead Register'!$C$6:$C$838,"<"&DATE(2025,7,1),'Daily Overhead Register'!$D$6:$D$838,"Office Utilities - Water/Sewer") -> 64.93 | I26: =SUMIFS('Daily Overhead Register'!$E$6:$E$838,'Daily Overhead Register'!$C$6:$C$838,">="&DATE(2025,7,1),'Daily Overhead Register'!$C$6:$C$838,"<"&DATE(2025,8,1),'Daily Overhead Register'!$D$6:$D$838,"Office Utilities - Water/Sewer") -> 63.5 | J26: =SUMIFS('Daily Overhead Register'!$E$6:$E$838,'Daily Overhead Register'!$C$6:$C$838,">="&DATE(2025,8,1),'Daily Overhead Register'!$C$6:$C$838,"<"&DATE(2025,9,1),'Daily Overhead Register'!$D$6:$D$838,"Office Utilities - Water/Sewer") -> 67.94 | K26: =SUMIFS('Daily Overhead Register'!$E$6:$E$838,'Daily Overhead Register'!$C$6:$C$838,">="&DATE(2025,9,1),'Daily Overhead Register'!$C$6:$C$838,"<"&DATE(2025,10,1),'Daily Overhead Register'!$D$6:$D$838,"Office Utilities - Water/Sewer") -> 61.41 | L26: =SUMIFS('Daily Overhead Register'!$E$6:$E$838,'Daily Overhead Register'!$C$6:$C$838,">="&DATE(2025,10,1),'Daily Overhead Register'!$C$6:$C$838,"<"&DATE(2025,11,1),'Daily Overhead Register'!$D$6:$D$838,"Office Utilities - Water/Sewer") -> 66.75 | M26: =SUMIFS('Daily Overhead Register'!$E$6:$E$838,'Daily Overhead Register'!$C$6:$C$838,">="&DATE(2025,11,1),'Daily Overhead Register'!$C$6:$C$838,"<"&DATE(2025,12,1),'Daily Overhead Register'!$D$6:$D$838,"Office Utilities - Water/Sewer") -> 69.5 | N26: =SUMIFS('Daily Overhead Register'!$E$6:$E$838,'Daily Overhead Register'!$C$6:$C$838,">="&DATE(2025,12,1),'Daily Overhead Register'!$C$6:$C$838,"<"&DATE(2026,1,1),'Daily Overhead Register'!$D$6:$D$838,"Office Utilities - Water/Sewer") -> 65.26 | O26: =SUM(C26:N26) -> 786.62
B27: Owner/Executive Compensation | C27: =SUMIFS('Daily Overhead Register'!$E$6:$E$838,'Daily Overhead Register'!$C$6:$C$838,">="&DATE(2025,1,1),'Daily Overhead Register'!$C$6:$C$838,"<"&DATE(2025,2,1),'Daily Overhead Register'!$D$6:$D$838,"Owner/Executive Compensation") -> 5169.63 | D27: =SUMIFS('Daily Overhead Register'!$E$6:$E$838,'Daily Overhead Register'!$C$6:$C$838,">="&DATE(2025,2,1),'Daily Overhead Register'!$C$6:$C$838,"<"&DATE(2025,3,1),'Daily Overhead Register'!$D$6:$D$838,"Owner/Executive Compensation") -> 4905.29 | E27: =SUMIFS('Daily Overhead Register'!$E$6:$E$838,'Daily Overhead Register'!$C$6:$C$838,">="&DATE(2025,3,1),'Daily Overhead Register'!$C$6:$C$838,"<"&DATE(2025,4,1),'Daily Overhead Register'!$D$6:$D$838,"Owner/Executive Compensation") -> 5018 | F27: =SUMIFS('Daily Overhead Register'!$E$6:$E$838,'Daily Overhead Register'!$C$6:$C$838,">="&DATE(2025,4,1),'Daily Overhead Register'!$C$6:$C$838,"<"&DATE(2025,5,1),'Daily Overhead Register'!$D$6:$D$838,"Owner/Executive Compensation") -> 5423.54 | G27: =SUMIFS('Daily Overhead Register'!$E$6:$E$838,'Daily Overhead Register'!$C$6:$C$838,">="&DATE(2025,5,1),'Daily Overhead Register'!$C$6:$C$838,"<"&DATE(2025,6,1),'Daily Overhead Register'!$D$6:$D$838,"Owner/Executive Compensation") -> 5271.48 | H27: =SUMIFS('Daily Overhead Register'!$E$6:$E$838,'Daily Overhead Register'!$C$6:$C$838,">="&DATE(2025,6,1),'Daily Overhead Register'!$C$6:$C$838,"<"&DATE(2025,7,1),'Daily Overhead Register'!$D$6:$D$838,"Owner/Executive Compensation") -> 4956.46 | I27: =SUMIFS('Daily Overhead Register'!$E$6:$E$838,'Daily Overhead Register'!$C$6:$C$838,">="&DATE(2025,7,1),'Daily Overhead Register'!$C$6:$C$838,"<"&DATE(2025,8,1),'Daily Overhead Register'!$D$6:$D$838,"Owner/Executive Compensation") -> 5080.14 | J27: =SUMIFS('Daily Overhead Register'!$E$6:$E$838,'Daily Overhead Register'!$C$6:$C$838,">="&DATE(2025,8,1),'Daily Overhead Register'!$C$6:$C$838,"<"&DATE(2025,9,1),'Daily Overhead Register'!$D$6:$D$838,"Owner/Executive Compensation") -> 4945.59 | K27: =SUMIFS('Daily Overhead Register'!$E$6:$E$838,'Daily Overhead Register'!$C$6:$C$838,">="&DATE(2025,9,1),'Daily Overhead Register'!$C$6:$C$838,"<"&DATE(2025,10,1),'Daily Overhead Register'!$D$6:$D$838,"Owner/Executive Compensation") -> 5126.16 | L27: =SUMIFS('Daily Overhead Register'!$E$6:$E$838,'Daily Overhead Register'!$C$6:$C$838,">="&DATE(2025,10,1),'Daily Overhead Register'!$C$6:$C$838,"<"&DATE(2025,11,1),'Daily Overhead Register'!$D$6:$D$838,"Owner/Executive Compensation") -> 5526.89 | M27: =SUMIFS('Daily Overhead Register'!$E$6:$E$838,'Daily Overhead Register'!$C$6:$C$838,">="&DATE(2025,11,1),'Daily Overhead Register'!$C$6:$C$838,"<"&DATE(2025,12,1),'Daily Overhead Register'!$D$6:$D$838,"Owner/Executive Compensation") -> 5443.76 | N27: =SUMIFS('Daily Overhead Register'!$E$6:$E$838,'Daily Overhead Register'!$C$6:$C$838,">="&DATE(2025,12,1),'Daily Overhead Register'!$C$6:$C$838,"<"&DATE(2026,1,1),'Daily Overhead Register'!$D$6:$D$838,"Owner/Executive Compensation") -> 5259.95 | O27: =SUM(C27:N27) -> 62126.89
